Workbook

Sheet 01_Executive_Dashboard
A1: RESEARCH INTELLIGENCE ENGINE (RIE) — COMMAND CENTER v1.0 | G1: DATA PROJECTION & SYSTEM STATUS
A2: Interactive Executive Console & Epistemic Governance Cockpit | Governed under Human Architect Level 5 — Human Architect | G2: Baseline: RIE_v1.5_GOLDEN_STATE | Rollback Anchors: v1.4.0 & v1.4.1 VERIFIED
A3: Cognitive Workflow: Question ➔ Discovery ➔ Understanding ➔ Verification ➔ Exploration ➔ Decision | G3: Phase Status: RIE v1.5 FULL CONTROLLED IMPLEMENTATION SEALED (PASS) | Mode: GOVERNED OPERATIONAL
A4: QUICK NAVIGATION: | B4: =HYPERLINK("#'02_Object_Registry'!A1", "➔ 2. OBJECT REGISTRY") | C4: =HYPERLINK("#'03_Relationship_Registry'!A1", "➔ 3. RELATIONSHIP REGISTRY") | D4: =HYPERLINK("#'04_Lineage_Explorer'!A1", "➔ 4. LINEAGE EXPLORER") | E4: =HYPERLINK("#'05_Knowledge_Frontier'!A1", "➔ 5. KNOWLEDGE FRONTIER") | F4: =HYPERLINK("#'06_Provenance_Register'!A1", "➔ 6. PROVENANCE REGISTER") | G4: =HYPERLINK("#'07_Human_Decision_Log'!A1", "➔ 7. HUMAN DECISION LOG") | H4: =HYPERLINK("#'DATA_KO'!A1", "➔ REPOSITORY DATA")
A6: 1. INTELLIGENCE INVENTORY & SUBSTRATE METRICS | E6: 2. HUMAN REVIEW STATUS (LEVEL 5 GOVERNANCE)
A7: Evidence Objects (EO) | B7: =COUNTA(DATA_EO!A2:A1000) | C7: Layer 1 ground truth empirical observations with exact timestamps | E7: Pending Review | F7: =COUNTIF(DATA_KO!H:H, "CANDIDATE") + COUNTIF(DATA_KO!H:H, "PENDING_HUMAN_REVIEW") | G7: Queued items awaiting Human Architect Level 5 evaluation
A8: Interpretation Objects (IO) | B8: =COUNTA(DATA_IO!A2:A1000) | C8: Layer 2 analytical models paired with competing counter-hypotheses | E8: Accepted (Ratified) | F8: =COUNTIF(DATA_KO!H:H, "CANONICAL") + COUNTIF(DATA_KO!I:I, "CANONICAL_RATIFIED") | G8: Knowledge objects formally ratified into Canonical status
A9: Knowledge Objects (KO) | B9: =COUNTA(DATA_KO!A2:A1000) | C9: Layer 3 synthesized institutional concepts awaiting Level 5 ratification | E9: Rejected / Quarantined | F9: =COUNTIF(DATA_KO!H:H, "REJECTED") + COUNTIF(DATA_KO!H:H, "QUARANTINED*") | G9: Rejected candidates & quarantined fixtures archived as negative/quarantined knowledge
A10: Total Relationships | B10: =COUNTA(DATA_RELATIONSHIPS!A2:A1000) | C10: Multi-layer semantic links (Substantiates, Synthesized Into, Coupled With) | E10: Deferred | F10: =COUNTIF(DATA_KO!H:H, "DEFERRED") + COUNTIF(DATA_KO!I:I, "CANDIDATE_REFINEMENT") | G10: Candidate concepts returned for further empirical refinement
A11: Origin Media Sources | B11: =COUNTA(DATA_SOURCE!A2:A1000) | C11: Verified upstream media source records ingested into repository | E11: Total Frontier Items | F11: =COUNTIF(DATA_KO!H:H, "CANDIDATE") + COUNTIF(DATA_KO!H:H, "PENDING_HUMAN_REVIEW") | G11: All queued items across candidate KOs, hypotheses, and frontiers
A13: 3. KNOWLEDGE FRONTIER FOCUS | E13: 4. SYSTEM STATUS & CANONICAL CONTROL
A14: Unresolved Frontier Items | B14: =COUNTIF(DATA_KO!H:H, "CANDIDATE") + COUNTIF(DATA_KO!H:H, "PENDING_HUMAN_REVIEW") | C14: Uncodified observations and hypotheses requiring human adjudication | E14: Current Production Baseline | F14: RIE_v1.5_GOLDEN_STATE | G14: Hybrid LLM Staged Batch + 10-Track Taxonomy v2.0 + AITG Bridge + SQLite Sidecar
A15: Candidate KOs | B15: =COUNTIF(DATA_KO!H:H, "CANDIDATE") | C15: Synthesized concepts pending formal Human Architect Level 5 ratification | E15: Development Candidate | F15: RIE_v1.4.1_REMEDIATED_SEALED | G15: Previous Golden State & v1.4.0 Rollback Anchor Preserved Untouched
A16: Pending Human Review | B16: =COUNTIF(DATA_KO!H:H, "PENDING_HUMAN_REVIEW") | C16: Candidate concepts routed to human architect review queue | E16: Validation Status | F16: PASS | G16: Validation Evidence: 21/21 Unit | 7/7 Adversarial | 6/6 v1.5 Feature Tests | ./rie audit PASS
A17: Total Epistemic Objects | B17: =(COUNTA(DATA_KO!A2:A1000)+COUNTA(DATA_IO!A2:A1000)+COUNTA(DATA_EO!A2:A1000)) | C17: Combined cardinality across Knowledge, Interpretation, and Evidence layers | E17: Promotion Status | F17: GOVERNED_OPERATIONAL_MODE | G17: RIE_COMMAND_CENTER.xlsx = SOLE HUMAN SSOT | rie_substrate.db = Performance Sidecar
A19: 5. INTELLIGENCE SEARCH & COGNITIVE DISCOVERY CONSOLE
A20: SEARCH KEYWORD: | B20: Enter Topic / Inquiry: | C20: Gold | D20: =HYPERLINK("#'01_Executive_Dashboard'!A20", "➔ [ SEARCH / REFRESH ]") | E20: =HYPERLINK("#'01_Executive_Dashboard'!A138", "➔ [ PREPARE INTELLIGENCE REPORT REQUEST ]")
A21: ACTIVE SELECTION: | B21: Selected KO for Investigation: | C21: {=IFERROR(INDEX(DATA_KO!A:A, MATCH(1, DATA_KO!K:K, 0)), "KO-FIN-DEBT-INTEREST-SPIRAL-001")} | D21: =HYPERLINK("#'04_Lineage_Explorer'!B6", "➔ [ OPEN LINEAGE EXPLORER ]") | E21: =IFERROR("Active Concept: " & VLOOKUP(C21, DATA_KO!A:B, 2, FALSE), "")
A22: ="SEARCH RESULTS FOR: " & UPPER($C$20) & " | Matched Knowledge Objects: " & COUNTIF(DATA_KO!J:J, 1) & " | Substrate Interpretations: " & COUNTIF(DATA_IO!J:J, 1) & " | Grounding Evidence: " & COUNTIF(DATA_EO!O:O, 1)
A23: HUMAN DECISION WORKFLOW: 1. Review Knowledge ➔ 2. Compare Evidence ➔ 3. Formulate Decision (ACCEPT / HOLD / REJECT / FURTHER RESEARCH) ➔ 4. [ RECORD DECISION IN LOG ]
A24: RETRIEVED KNOWLEDGE CONCEPTS (HUMAN MEANING FIRST — PROVENANCE LINEAGE ROOT)
A25: Concept Title (Human Meaning First) | B25: Object_ID & Domain | C25: Matched Because (Match Reason) | D25: Matched Specifics (Snippet) | E25: Substrate Profile | F25: Lineage Status | G25: Lineage Action | H25: Decision Action
A26: {=IFERROR(INDEX(DATA_KO!B:B, MATCH(1, DATA_KO!K:K, 0)), IF(1=1, "No intelligence objects found", ""))} | B26: {=IFERROR(INDEX(DATA_KO!A:A, MATCH(1, DATA_KO!K:K, 0)) & " | " & INDEX(DATA_KO!C:C, MATCH(1, DATA_KO!K:K, 0)), "")} | C26: {=IFERROR(INDEX(DATA_KO!O:O, MATCH(1, DATA_KO!K:K, 0)), "")} | D26: {=IFERROR(INDEX(DATA_KO!P:P, MATCH(1, DATA_KO!K:K, 0)), "")} | E26: {=IFERROR(INDEX(DATA_KO!T:T, MATCH(1, DATA_KO!K:K, 0)), "")} | F26: =IF(A26="","", IF(A26="No intelligence objects found", "", "LINKED")) | G26: =IF(A26="","", IF(A26="No intelligence objects found", "", HYPERLINK("#'04_Lineage_Explorer'!B6", "➔ Trace Lineage"))) | H26: =IF(A26="","", IF(A26="No intelligence objects found", "", HYPERLINK("#'07_Human_Decision_Log'!A1", "➔ Record Decision")))
A27: {=IFERROR(INDEX(DATA_KO!B:B, MATCH(2, DATA_KO!K:K, 0)), IF(2=1, "No intelligence objects found", ""))} | B27: {=IFERROR(INDEX(DATA_KO!A:A, MATCH(2, DATA_KO!K:K, 0)) & " | " & INDEX(DATA_KO!C:C, MATCH(2, DATA_KO!K:K, 0)), "")} | C27: {=IFERROR(INDEX(DATA_KO!O:O, MATCH(2, DATA_KO!K:K, 0)), "")} | D27: {=IFERROR(INDEX(DATA_KO!P:P, MATCH(2, DATA_KO!K:K, 0)), "")} | E27: {=IFERROR(INDEX(DATA_KO!T:T, MATCH(2, DATA_KO!K:K, 0)), "")} | F27: =IF(A27="","", IF(A27="No intelligence objects found", "", "LINKED")) | G27: =IF(A27="","", IF(A27="No intelligence objects found", "", HYPERLINK("#'04_Lineage_Explorer'!B6", "➔ Trace Lineage"))) | H27: =IF(A27="","", IF(A27="No intelligence objects found", "", HYPERLINK("#'07_Human_Decision_Log'!A1", "➔ Record Decision")))
A28: {=IFERROR(INDEX(DATA_KO!B:B, MATCH(3, DATA_KO!K:K, 0)), IF(3=1, "No intelligence objects found", ""))} | B28: {=IFERROR(INDEX(DATA_KO!A:A, MATCH(3, DATA_KO!K:K, 0)) & " | " & INDEX(DATA_KO!C:C, MATCH(3, DATA_KO!K:K, 0)), "")} | C28: {=IFERROR(INDEX(DATA_KO!O:O, MATCH(3, DATA_KO!K:K, 0)), "")} | D28: {=IFERROR(INDEX(DATA_KO!P:P, MATCH(3, DATA_KO!K:K, 0)), "")} | E28: {=IFERROR(INDEX(DATA_KO!T:T, MATCH(3, DATA_KO!K:K, 0)), "")} | F28: =IF(A28="","", IF(A28="No intelligence objects found", "", "LINKED")) | G28: =IF(A28="","", IF(A28="No intelligence objects found", "", HYPERLINK("#'04_Lineage_Explorer'!B6", "➔ Trace Lineage"))) | H28: =IF(A28="","", IF(A28="No intelligence objects found", "", HYPERLINK("#'07_Human_Decision_Log'!A1", "➔ Record Decision")))
A29: {=IFERROR(INDEX(DATA_KO!B:B, MATCH(4, DATA_KO!K:K, 0)), IF(4=1, "No intelligence objects found", ""))} | B29: {=IFERROR(INDEX(DATA_KO!A:A, MATCH(4, DATA_KO!K:K, 0)) & " | " & INDEX(DATA_KO!C:C, MATCH(4, DATA_KO!K:K, 0)), "")} | C29: {=IFERROR(INDEX(DATA_KO!O:O, MATCH(4, DATA_KO!K:K, 0)), "")} | D29: {=IFERROR(INDEX(DATA_KO!P:P, MATCH(4, DATA_KO!K:K, 0)), "")} | E29: {=IFERROR(INDEX(DATA_KO!T:T, MATCH(4, DATA_KO!K:K, 0)), "")} | F29: =IF(A29="","", IF(A29="No intelligence objects found", "", "LINKED")) | G29: =IF(A29="","", IF(A29="No intelligence objects found", "", HYPERLINK("#'04_Lineage_Explorer'!B6", "➔ Trace Lineage"))) | H29: =IF(A29="","", IF(A29="No intelligence objects found", "", HYPERLINK("#'07_Human_Decision_Log'!A1", "➔ Record Decision")))
A30: {=IFERROR(INDEX(DATA_KO!B:B, MATCH(5, DATA_KO!K:K, 0)), IF(5=1, "No intelligence objects found", ""))} | B30: {=IFERROR(INDEX(DATA_KO!A:A, MATCH(5, DATA_KO!K:K, 0)) & " | " & INDEX(DATA_KO!C:C, MATCH(5, DATA_KO!K:K, 0)), "")} | C30: {=IFERROR(INDEX(DATA_KO!O:O, MATCH(5, DATA_KO!K:K, 0)), "")} | D30: {=IFERROR(INDEX(DATA_KO!P:P, MATCH(5, DATA_KO!K:K, 0)), "")} | E30: {=IFERROR(INDEX(DATA_KO!T:T, MATCH(5, DATA_KO!K:K, 0)), "")} | F30: =IF(A30="","", IF(A30="No intelligence objects found", "", "LINKED")) | G30: =IF(A30="","", IF(A30="No intelligence objects found", "", HYPERLINK("#'04_Lineage_Explorer'!B6", "➔ Trace Lineage"))) | H30: =IF(A30="","", IF(A30="No intelligence objects found", "", HYPERLINK("#'07_Human_Decision_Log'!A1", "➔ Record Decision")))
A31: {=IFERROR(INDEX(DATA_KO!B:B, MATCH(6, DATA_KO!K:K, 0)), IF(6=1, "No intelligence objects found", ""))} | B31: {=IFERROR(INDEX(DATA_KO!A:A, MATCH(6, DATA_KO!K:K, 0)) & " | " & INDEX(DATA_KO!C:C, MATCH(6, DATA_KO!K:K, 0)), "")} | C31: {=IFERROR(INDEX(DATA_KO!O:O, MATCH(6, DATA_KO!K:K, 0)), "")} | D31: {=IFERROR(INDEX(DATA_KO!P:P, MATCH(6, DATA_KO!K:K, 0)), "")} | E31: {=IFERROR(INDEX(DATA_KO!T:T, MATCH(6, DATA_KO!K:K, 0)), "")} | F31: =IF(A31="","", IF(A31="No intelligence objects found", "", "LINKED")) | G31: =IF(A31="","", IF(A31="No intelligence objects found", "", HYPERLINK("#'04_Lineage_Explorer'!B6", "➔ Trace Lineage"))) | H31: =IF(A31="","", IF(A31="No intelligence objects found", "", HYPERLINK("#'07_Human_Decision_Log'!A1", "➔ Record Decision")))
A32: {=IFERROR(INDEX(DATA_KO!B:B, MATCH(7, DATA_KO!K:K, 0)), IF(7=1, "No intelligence objects found", ""))} | B32: {=IFERROR(INDEX(DATA_KO!A:A, MATCH(7, DATA_KO!K:K, 0)) & " | " & INDEX(DATA_KO!C:C, MATCH(7, DATA_KO!K:K, 0)), "")} | C32: {=IFERROR(INDEX(DATA_KO!O:O, MATCH(7, DATA_KO!K:K, 0)), "")} | D32: {=IFERROR(INDEX(DATA_KO!P:P, MATCH(7, DATA_KO!K:K, 0)), "")} | E32: {=IFERROR(INDEX(DATA_KO!T:T, MATCH(7, DATA_KO!K:K, 0)), "")} | F32: =IF(A32="","", IF(A32="No intelligence objects found", "", "LINKED")) | G32: =IF(A32="","", IF(A32="No intelligence objects found", "", HYPERLINK("#'04_Lineage_Explorer'!B6", "➔ Trace Lineage"))) | H32: =IF(A32="","", IF(A32="No intelligence objects found", "", HYPERLINK("#'07_Human_Decision_Log'!A1", "➔ Record Decision")))
A33: {=IFERROR(INDEX(DATA_KO!B:B, MATCH(8, DATA_KO!K:K, 0)), IF(8=1, "No intelligence objects found", ""))} | B33: {=IFERROR(INDEX(DATA_KO!A:A, MATCH(8, DATA_KO!K:K, 0)) & " | " & INDEX(DATA_KO!C:C, MATCH(8, DATA_KO!K:K, 0)), "")} | C33: {=IFERROR(INDEX(DATA_KO!O:O, MATCH(8, DATA_KO!K:K, 0)), "")} | D33: {=IFERROR(INDEX(DATA_KO!P:P, MATCH(8, DATA_KO!K:K, 0)), "")} | E33: {=IFERROR(INDEX(DATA_KO!T:T, MATCH(8, DATA_KO!K:K, 0)), "")} | F33: =IF(A33="","", IF(A33="No intelligence objects found", "", "LINKED")) | G33: =IF(A33="","", IF(A33="No intelligence objects found", "", HYPERLINK("#'04_Lineage_Explorer'!B6", "➔ Trace Lineage"))) | H33: =IF(A33="","", IF(A33="No intelligence objects found", "", HYPERLINK("#'07_Human_Decision_Log'!A1", "➔ Record Decision")))
A34: {=IFERROR(INDEX(DATA_KO!B:B, MATCH(9, DATA_KO!K:K, 0)), IF(9=1, "No intelligence objects found", ""))} | B34: {=IFERROR(INDEX(DATA_KO!A:A, MATCH(9, DATA_KO!K:K, 0)) & " | " & INDEX(DATA_KO!C:C, MATCH(9, DATA_KO!K:K, 0)), "")} | C34: {=IFERROR(INDEX(DATA_KO!O:O, MATCH(9, DATA_KO!K:K, 0)), "")} | D34: {=IFERROR(INDEX(DATA_KO!P:P, MATCH(9, DATA_KO!K:K, 0)), "")} | E34: {=IFERROR(INDEX(DATA_KO!T:T, MATCH(9, DATA_KO!K:K, 0)), "")} | F34: =IF(A34="","", IF(A34="No intelligence objects found", "", "LINKED")) | G34: =IF(A34="","", IF(A34="No intelligence objects found", "", HYPERLINK("#'04_Lineage_Explorer'!B6", "➔ Trace Lineage"))) | H34: =IF(A34="","", IF(A34="No intelligence objects found", "", HYPERLINK("#'07_Human_Decision_Log'!A1", "➔ Record Decision")))
A35: {=IFERROR(INDEX(DATA_KO!B:B, MATCH(10, DATA_KO!K:K, 0)), IF(10=1, "No intelligence objects found", ""))} | B35: {=IFERROR(INDEX(DATA_KO!A:A, MATCH(10, DATA_KO!K:K, 0)) & " | " & INDEX(DATA_KO!C:C, MATCH(10, DATA_KO!K:K, 0)), "")} | C35: {=IFERROR(INDEX(DATA_KO!O:O, MATCH(10, DATA_KO!K:K, 0)), "")} | D35: {=IFERROR(INDEX(DATA_KO!P:P, MATCH(10, DATA_KO!K:K, 0)), "")} | E35: {=IFERROR(INDEX(DATA_KO!T:T, MATCH(10, DATA_KO!K:K, 0)), "")} | F35: =IF(A35="","", IF(A35="No intelligence objects found", "", "LINKED")) | G35: =IF(A35="","", IF(A35="No intelligence objects found", "", HYPERLINK("#'04_Lineage_Explorer'!B6", "➔ Trace Lineage"))) | H35: =IF(A35="","", IF(A35="No intelligence objects found", "", HYPERLINK("#'07_Human_Decision_Log'!A1", "➔ Record Decision")))
A36: Hierarchical Discovery Tree (Collapsed by Default — Click [+] on Left Margin to Expand Supporting Interpretations & Evidence)
A37: 6. DYNAMIC INTELLIGENCE TREE EXPLORER (MULTI-KO TOPIC DISCOVERY & EXPANSION)
A38: Hierarchical Discovery Tree (Collapsed by Default — Click [+] on Left Margin to Expand Supporting Interpretations & Evidence)
A39: EXPLORATION LENS: | B39: ="Search Topic: " & UPPER($C$20) & " | Retrieved Knowledge Clusters: " & MAX(DATA_KO!K:K) | G39: =HYPERLINK("#'01_Executive_Dashboard'!A20", "➔ [Refresh Tree / New Search]")
A41: {=IFERROR(IF(INDEX(DATA_KO!A:A, MATCH(1, DATA_KO!K:K, 0))="","", "▼ Concept:"), "")} | B41: {=IFERROR(IF(INDEX(DATA_KO!A:A, MATCH(1, DATA_KO!K:K, 0))="","", INDEX(DATA_KO!B:B, MATCH(1, DATA_KO!K:K, 0))), "")} | E41: {=IFERROR(IF(INDEX(DATA_KO!A:A, MATCH(1, DATA_KO!K:K, 0))="","", "[[" & INDEX(DATA_KO!A:A, MATCH(1, DATA_KO!K:K, 0)) & "]]"), "")} | F41: {=IFERROR(IF(INDEX(DATA_KO!A:A, MATCH(1, DATA_KO!K:K, 0))="","", "IO: " & INDEX(DATA_KO!R:R, MATCH(1, DATA_KO!K:K, 0)) & " | EO: " & INDEX(DATA_KO!Q:Q, MATCH(1, DATA_KO!K:K, 0)) & " | Conf: " & TEXT(INDEX(DATA_KO!G:G, MATCH(1, DATA_KO!K:K, 0)), "0.00")), "")} | G41: {=IFERROR(IF(INDEX(DATA_KO!A:A, MATCH(1, DATA_KO!K:K, 0))="","", "Domain: " & INDEX(DATA_KO!C:C, MATCH(1, DATA_KO!K:K, 0))), "")} | H41: {=IFERROR(IF(INDEX(DATA_KO!A:A, MATCH(1, DATA_KO!K:K, 0))="","", HYPERLINK("#'04_Lineage_Explorer'!B6", "➔ [Inspect Lineage]")), "")}
B42: {=IFERROR(IF(INDEX(DATA_KO!A:A, MATCH(1, DATA_KO!K:K, 0))="","", " ▼ Supporting Interpretations (Layer 2) — " & INDEX(DATA_KO!R:R, MATCH(1, DATA_KO!K:K, 0)) & " Models"), "")}
B43: {=IFERROR(IF(INDEX(DATA_KO!A:A, MATCH(1, DATA_KO!K:K, 0))="","", " • [[" & TRIM(MID(SUBSTITUTE(INDEX(DATA_KO!F:F, MATCH(1, DATA_KO!K:K, 0)), ",", REPT(" ", 500)), 1, 500)) & "]] — " & INDEX(DATA_IO!B:B, MATCH(TRIM(MID(SUBSTITUTE(INDEX(DATA_KO!F:F, MATCH(1, DATA_KO!K:K, 0)), ",", REPT(" ", 500)), 1, 500)), DATA_IO!A:A, 0))), "")}
B44: {=IFERROR(IF(INDEX(DATA_KO!A:A, MATCH(1, DATA_KO!K:K, 0))="","", IF(ISERROR(FIND(",", INDEX(DATA_KO!F:F, MATCH(1, DATA_KO!K:K, 0)))), "", " • [[" & TRIM(MID(SUBSTITUTE(INDEX(DATA_KO!F:F, MATCH(1, DATA_KO!K:K, 0)), ",", REPT(" ", 500)), 501, 500)) & "]] — " & INDEX(DATA_IO!B:B, MATCH(TRIM(MID(SUBSTITUTE(INDEX(DATA_KO!F:F, MATCH(1, DATA_KO!K:K, 0)), ",", REPT(" ", 500)), 501, 500)), DATA_IO!A:A, 0)))), "")}
B45: {=IFERROR(IF(INDEX(DATA_KO!A:A, MATCH(1, DATA_KO!K:K, 0))="","", " ▼ Grounding Evidence (Layer 1) — " & INDEX(DATA_KO!Q:Q, MATCH(1, DATA_KO!K:K, 0)) & " Empirical Anchors"), "")}
B46: {=IFERROR(IF(INDEX(DATA_KO!A:A, MATCH(1, DATA_KO!K:K, 0))="","", " • [[" & TRIM(MID(SUBSTITUTE(INDEX(DATA_KO!E:E, MATCH(1, DATA_KO!K:K, 0)), ",", REPT(" ", 500)), 1, 500)) & "]] — " & INDEX(DATA_EO!L:L, MATCH(TRIM(MID(SUBSTITUTE(INDEX(DATA_KO!E:E, MATCH(1, DATA_KO!K:K, 0)), ",", REPT(" ", 500)), 1, 500)), DATA_EO!A:A, 0)) & " (Source: " & INDEX(DATA_EO!B:B, MATCH(TRIM(MID(SUBSTITUTE(INDEX(DATA_KO!E:E, MATCH(1, DATA_KO!K:K, 0)), ",", REPT(" ", 500)), 1, 500)), DATA_EO!A:A, 0)) & ", " & INDEX(DATA_EO!J:J, MATCH(TRIM(MID(SUBSTITUTE(INDEX(DATA_KO!E:E, MATCH(1, DATA_KO!K:K, 0)), ",", REPT(" ", 500)), 1, 500)), DATA_EO!A:A, 0)) & ")"), "")}
B47: {=IFERROR(IF(INDEX(DATA_KO!A:A, MATCH(1, DATA_KO!K:K, 0))="","", IF(ISERROR(FIND(",", INDEX(DATA_KO!E:E, MATCH(1, DATA_KO!K:K, 0)))), "", " • [[" & TRIM(MID(SUBSTITUTE(INDEX(DATA_KO!E:E, MATCH(1, DATA_KO!K:K, 0)), ",", REPT(" ", 500)), 501, 500)) & "]] — " & INDEX(DATA_EO!L:L, MATCH(TRIM(MID(SUBSTITUTE(INDEX(DATA_KO!E:E, MATCH(1, DATA_KO!K:K, 0)), ",", REPT(" ", 500)), 501, 500)), DATA_EO!A:A, 0)) & " (Source: " & INDEX(DATA_EO!B:B, MATCH(TRIM(MID(SUBSTITUTE(INDEX(DATA_KO!E:E, MATCH(1, DATA_KO!K:K, 0)), ",", REPT(" ", 500)), 501, 500)), DATA_EO!A:A, 0)) & ", " & INDEX(DATA_EO!J:J, MATCH(TRIM(MID(SUBSTITUTE(INDEX(DATA_KO!E:E, MATCH(1, DATA_KO!K:K, 0)), ",", REPT(" ", 500)), 501, 500)), DATA_EO!A:A, 0)) & ")")), "")}
B48: {=IFERROR(IF(INDEX(DATA_KO!A:A, MATCH(1, DATA_KO!K:K, 0))="","", IF(LEN(INDEX(DATA_KO!E:E, MATCH(1, DATA_KO!K:K, 0)))-LEN(SUBSTITUTE(INDEX(DATA_KO!E:E, MATCH(1, DATA_KO!K:K, 0)), ",", "" ))<2, "", " • [[" & TRIM(MID(SUBSTITUTE(INDEX(DATA_KO!E:E, MATCH(1, DATA_KO!K:K, 0)), ",", REPT(" ", 500)), 1001, 500)) & "]] — " & INDEX(DATA_EO!L:L, MATCH(TRIM(MID(SUBSTITUTE(INDEX(DATA_KO!E:E, MATCH(1, DATA_KO!K:K, 0)), ",", REPT(" ", 500)), 1001, 500)), DATA_EO!A:A, 0)) & " (Source: " & INDEX(DATA_EO!B:B, MATCH(TRIM(MID(SUBSTITUTE(INDEX(DATA_KO!E:E, MATCH(1, DATA_KO!K:K, 0)), ",", REPT(" ", 500)), 1001, 500)), DATA_EO!A:A, 0)) & ", " & INDEX(DATA_EO!J:J, MATCH(TRIM(MID(SUBSTITUTE(INDEX(DATA_KO!E:E, MATCH(1, DATA_KO!K:K, 0)), ",", REPT(" ", 500)), 1001, 500)), DATA_EO!A:A, 0)) & ")")), "")}
A50: {=IFERROR(IF(INDEX(DATA_KO!A:A, MATCH(2, DATA_KO!K:K, 0))="","", "▼ Concept:"), "")} | B50: {=IFERROR(IF(INDEX(DATA_KO!A:A, MATCH(2, DATA_KO!K:K, 0))="","", INDEX(DATA_KO!B:B, MATCH(2, DATA_KO!K:K, 0))), "")} | E50: {=IFERROR(IF(INDEX(DATA_KO!A:A, MATCH(2, DATA_KO!K:K, 0))="","", "[[" & INDEX(DATA_KO!A:A, MATCH(2, DATA_KO!K:K, 0)) & "]]"), "")} | F50: {=IFERROR(IF(INDEX(DATA_KO!A:A, MATCH(2, DATA_KO!K:K, 0))="","", "IO: " & INDEX(DATA_KO!R:R, MATCH(2, DATA_KO!K:K, 0)) & " | EO: " & INDEX(DATA_KO!Q:Q, MATCH(2, DATA_KO!K:K, 0)) & " | Conf: " & TEXT(INDEX(DATA_KO!G:G, MATCH(2, DATA_KO!K:K, 0)), "0.00")), "")} | G50: {=IFERROR(IF(INDEX(DATA_KO!A:A, MATCH(2, DATA_KO!K:K, 0))="","", "Domain: " & INDEX(DATA_KO!C:C, MATCH(2, DATA_KO!K:K, 0))), "")} | H50: {=IFERROR(IF(INDEX(DATA_KO!A:A, MATCH(2, DATA_KO!K:K, 0))="","", HYPERLINK("#'04_Lineage_Explorer'!B6", "➔ [Inspect Lineage]")), "")}
B51: {=IFERROR(IF(INDEX(DATA_KO!A:A, MATCH(2, DATA_KO!K:K, 0))="","", " ▼ Supporting Interpretations (Layer 2) — " & INDEX(DATA_KO!R:R, MATCH(2, DATA_KO!K:K, 0)) & " Models"), "")}
B52: {=IFERROR(IF(INDEX(DATA_KO!A:A, MATCH(2, DATA_KO!K:K, 0))="","", " • [[" & TRIM(MID(SUBSTITUTE(INDEX(DATA_KO!F:F, MATCH(2, DATA_KO!K:K, 0)), ",", REPT(" ", 500)), 1, 500)) & "]] — " & INDEX(DATA_IO!B:B, MATCH(TRIM(MID(SUBSTITUTE(INDEX(DATA_KO!F:F, MATCH(2, DATA_KO!K:K, 0)), ",", REPT(" ", 500)), 1, 500)), DATA_IO!A:A, 0))), "")}
B53: {=IFERROR(IF(INDEX(DATA_KO!A:A, MATCH(2, DATA_KO!K:K, 0))="","", IF(ISERROR(FIND(",", INDEX(DATA_KO!F:F, MATCH(2, DATA_KO!K:K, 0)))), "", " • [[" & TRIM(MID(SUBSTITUTE(INDEX(DATA_KO!F:F, MATCH(2, DATA_KO!K:K, 0)), ",", REPT(" ", 500)), 501, 500)) & "]] — " & INDEX(DATA_IO!B:B, MATCH(TRIM(MID(SUBSTITUTE(INDEX(DATA_KO!F:F, MATCH(2, DATA_KO!K:K, 0)), ",", REPT(" ", 500)), 501, 500)), DATA_IO!A:A, 0)))), "")}
B54: {=IFERROR(IF(INDEX(DATA_KO!A:A, MATCH(2, DATA_KO!K:K, 0))="","", " ▼ Grounding Evidence (Layer 1) — " & INDEX(DATA_KO!Q:Q, MATCH(2, DATA_KO!K:K, 0)) & " Empirical Anchors"), "")}
B55: {=IFERROR(IF(INDEX(DATA_KO!A:A, MATCH(2, DATA_KO!K:K, 0))="","", " • [[" & TRIM(MID(SUBSTITUTE(INDEX(DATA_KO!E:E, MATCH(2, DATA_KO!K:K, 0)), ",", REPT(" ", 500)), 1, 500)) & "]] — " & INDEX(DATA_EO!L:L, MATCH(TRIM(MID(SUBSTITUTE(INDEX(DATA_KO!E:E, MATCH(2, DATA_KO!K:K, 0)), ",", REPT(" ", 500)), 1, 500)), DATA_EO!A:A, 0)) & " (Source: " & INDEX(DATA_EO!B:B, MATCH(TRIM(MID(SUBSTITUTE(INDEX(DATA_KO!E:E, MATCH(2, DATA_KO!K:K, 0)), ",", REPT(" ", 500)), 1, 500)), DATA_EO!A:A, 0)) & ", " & INDEX(DATA_EO!J:J, MATCH(TRIM(MID(SUBSTITUTE(INDEX(DATA_KO!E:E, MATCH(2, DATA_KO!K:K, 0)), ",", REPT(" ", 500)), 1, 500)), DATA_EO!A:A, 0)) & ")"), "")}
B56: {=IFERROR(IF(INDEX(DATA_KO!A:A, MATCH(2, DATA_KO!K:K, 0))="","", IF(ISERROR(FIND(",", INDEX(DATA_KO!E:E, MATCH(2, DATA_KO!K:K, 0)))), "", " • [[" & TRIM(MID(SUBSTITUTE(INDEX(DATA_KO!E:E, MATCH(2, DATA_KO!K:K, 0)), ",", REPT(" ", 500)), 501, 500)) & "]] — " & INDEX(DATA_EO!L:L, MATCH(TRIM(MID(SUBSTITUTE(INDEX(DATA_KO!E:E, MATCH(2, DATA_KO!K:K, 0)), ",", REPT(" ", 500)), 501, 500)), DATA_EO!A:A, 0)) & " (Source: " & INDEX(DATA_EO!B:B, MATCH(TRIM(MID(SUBSTITUTE(INDEX(DATA_KO!E:E, MATCH(2, DATA_KO!K:K, 0)), ",", REPT(" ", 500)), 501, 500)), DATA_EO!A:A, 0)) & ", " & INDEX(DATA_EO!J:J, MATCH(TRIM(MID(SUBSTITUTE(INDEX(DATA_KO!E:E, MATCH(2, DATA_KO!K:K, 0)), ",", REPT(" ", 500)), 501, 500)), DATA_EO!A:A, 0)) & ")")), "")}
B57: {=IFERROR(IF(INDEX(DATA_KO!A:A, MATCH(2, DATA_KO!K:K, 0))="","", IF(LEN(INDEX(DATA_KO!E:E, MATCH(2, DATA_KO!K:K, 0)))-LEN(SUBSTITUTE(INDEX(DATA_KO!E:E, MATCH(2, DATA_KO!K:K, 0)), ",", "" ))<2, "", " • [[" & TRIM(MID(SUBSTITUTE(INDEX(DATA_KO!E:E, MATCH(2, DATA_KO!K:K, 0)), ",", REPT(" ", 500)), 1001, 500)) & "]] — " & INDEX(DATA_EO!L:L, MATCH(TRIM(MID(SUBSTITUTE(INDEX(DATA_KO!E:E, MATCH(2, DATA_KO!K:K, 0)), ",", REPT(" ", 500)), 1001, 500)), DATA_EO!A:A, 0)) & " (Source: " & INDEX(DATA_EO!B:B, MATCH(TRIM(MID(SUBSTITUTE(INDEX(DATA_KO!E:E, MATCH(2, DATA_KO!K:K, 0)), ",", REPT(" ", 500)), 1001, 500)), DATA_EO!A:A, 0)) & ", " & INDEX(DATA_EO!J:J, MATCH(TRIM(MID(SUBSTITUTE(INDEX(DATA_KO!E:E, MATCH(2, DATA_KO!K:K, 0)), ",", REPT(" ", 500)), 1001, 500)), DATA_EO!A:A, 0)) & ")")), "")}
A59: {=IFERROR(IF(INDEX(DATA_KO!A:A, MATCH(3, DATA_KO!K:K, 0))="","", "▼ Concept:"), "")} | B59: {=IFERROR(IF(INDEX(DATA_KO!A:A, MATCH(3, DATA_KO!K:K, 0))="","", INDEX(DATA_KO!B:B, MATCH(3, DATA_KO!K:K, 0))), "")} | E59: {=IFERROR(IF(INDEX(DATA_KO!A:A, MATCH(3, DATA_KO!K:K, 0))="","", "[[" & INDEX(DATA_KO!A:A, MATCH(3, DATA_KO!K:K, 0)) & "]]"), "")} | F59: {=IFERROR(IF(INDEX(DATA_KO!A:A, MATCH(3, DATA_KO!K:K, 0))="","", "IO: " & INDEX(DATA_KO!R:R, MATCH(3, DATA_KO!K:K, 0)) & " | EO: " & INDEX(DATA_KO!Q:Q, MATCH(3, DATA_KO!K:K, 0)) & " | Conf: " & TEXT(INDEX(DATA_KO!G:G, MATCH(3, DATA_KO!K:K, 0)), "0.00")), "")} | G59: {=IFERROR(IF(INDEX(DATA_KO!A:A, MATCH(3, DATA_KO!K:K, 0))="","", "Domain: " & INDEX(DATA_KO!C:C, MATCH(3, DATA_KO!K:K, 0))), "")} | H59: {=IFERROR(IF(INDEX(DATA_KO!A:A, MATCH(3, DATA_KO!K:K, 0))="","", HYPERLINK("#'04_Lineage_Explorer'!B6", "➔ [Inspect Lineage]")), "")}
B60: {=IFERROR(IF(INDEX(DATA_KO!A:A, MATCH(3, DATA_KO!K:K, 0))="","", " ▼ Supporting Interpretations (Layer 2) — " & INDEX(DATA_KO!R:R, MATCH(3, DATA_KO!K:K, 0)) & " Models"), "")}
B61: {=IFERROR(IF(INDEX(DATA_KO!A:A, MATCH(3, DATA_KO!K:K, 0))="","", " • [[" & TRIM(MID(SUBSTITUTE(INDEX(DATA_KO!F:F, MATCH(3, DATA_KO!K:K, 0)), ",", REPT(" ", 500)), 1, 500)) & "]] — " & INDEX(DATA_IO!B:B, MATCH(TRIM(MID(SUBSTITUTE(INDEX(DATA_KO!F:F, MATCH(3, DATA_KO!K:K, 0)), ",", REPT(" ", 500)), 1, 500)), DATA_IO!A:A, 0))), "")}
B62: {=IFERROR(IF(INDEX(DATA_KO!A:A, MATCH(3, DATA_KO!K:K, 0))="","", IF(ISERROR(FIND(",", INDEX(DATA_KO!F:F, MATCH(3, DATA_KO!K:K, 0)))), "", " • [[" & TRIM(MID(SUBSTITUTE(INDEX(DATA_KO!F:F, MATCH(3, DATA_KO!K:K, 0)), ",", REPT(" ", 500)), 501, 500)) & "]] — " & INDEX(DATA_IO!B:B, MATCH(TRIM(MID(SUBSTITUTE(INDEX(DATA_KO!F:F, MATCH(3, DATA_KO!K:K, 0)), ",", REPT(" ", 500)), 501, 500)), DATA_IO!A:A, 0)))), "")}
B63: {=IFERROR(IF(INDEX(DATA_KO!A:A, MATCH(3, DATA_KO!K:K, 0))="","", " ▼ Grounding Evidence (Layer 1) — " & INDEX(DATA_KO!Q:Q, MATCH(3, DATA_KO!K:K, 0)) & " Empirical Anchors"), "")}
B64: {=IFERROR(IF(INDEX(DATA_KO!A:A, MATCH(3, DATA_KO!K:K, 0))="","", " • [[" & TRIM(MID(SUBSTITUTE(INDEX(DATA_KO!E:E, MATCH(3, DATA_KO!K:K, 0)), ",", REPT(" ", 500)), 1, 500)) & "]] — " & INDEX(DATA_EO!L:L, MATCH(TRIM(MID(SUBSTITUTE(INDEX(DATA_KO!E:E, MATCH(3, DATA_KO!K:K, 0)), ",", REPT(" ", 500)), 1, 500)), DATA_EO!A:A, 0)) & " (Source: " & INDEX(DATA_EO!B:B, MATCH(TRIM(MID(SUBSTITUTE(INDEX(DATA_KO!E:E, MATCH(3, DATA_KO!K:K, 0)), ",", REPT(" ", 500)), 1, 500)), DATA_EO!A:A, 0)) & ", " & INDEX(DATA_EO!J:J, MATCH(TRIM(MID(SUBSTITUTE(INDEX(DATA_KO!E:E, MATCH(3, DATA_KO!K:K, 0)), ",", REPT(" ", 500)), 1, 500)), DATA_EO!A:A, 0)) & ")"), "")}
B65: {=IFERROR(IF(INDEX(DATA_KO!A:A, MATCH(3, DATA_KO!K:K, 0))="","", IF(ISERROR(FIND(",", INDEX(DATA_KO!E:E, MATCH(3, DATA_KO!K:K, 0)))), "", " • [[" & TRIM(MID(SUBSTITUTE(INDEX(DATA_KO!E:E, MATCH(3, DATA_KO!K:K, 0)), ",", REPT(" ", 500)), 501, 500)) & "]] — " & INDEX(DATA_EO!L:L, MATCH(TRIM(MID(SUBSTITUTE(INDEX(DATA_KO!E:E, MATCH(3, DATA_KO!K:K, 0)), ",", REPT(" ", 500)), 501, 500)), DATA_EO!A:A, 0)) & " (Source: " & INDEX(DATA_EO!B:B, MATCH(TRIM(MID(SUBSTITUTE(INDEX(DATA_KO!E:E, MATCH(3, DATA_KO!K:K, 0)), ",", REPT(" ", 500)), 501, 500)), DATA_EO!A:A, 0)) & ", " & INDEX(DATA_EO!J:J, MATCH(TRIM(MID(SUBSTITUTE(INDEX(DATA_KO!E:E, MATCH(3, DATA_KO!K:K, 0)), ",", REPT(" ", 500)), 501, 500)), DATA_EO!A:A, 0)) & ")")), "")}
B66: {=IFERROR(IF(INDEX(DATA_KO!A:A, MATCH(3, DATA_KO!K:K, 0))="","", IF(LEN(INDEX(DATA_KO!E:E, MATCH(3, DATA_KO!K:K, 0)))-LEN(SUBSTITUTE(INDEX(DATA_KO!E:E, MATCH(3, DATA_KO!K:K, 0)), ",", "" ))<2, "", " • [[" & TRIM(MID(SUBSTITUTE(INDEX(DATA_KO!E:E, MATCH(3, DATA_KO!K:K, 0)), ",", REPT(" ", 500)), 1001, 500)) & "]] — " & INDEX(DATA_EO!L:L, MATCH(TRIM(MID(SUBSTITUTE(INDEX(DATA_KO!E:E, MATCH(3, DATA_KO!K:K, 0)), ",", REPT(" ", 500)), 1001, 500)), DATA_EO!A:A, 0)) & " (Source: " & INDEX(DATA_EO!B:B, MATCH(TRIM(MID(SUBSTITUTE(INDEX(DATA_KO!E:E, MATCH(3, DATA_KO!K:K, 0)), ",", REPT(" ", 500)), 1001, 500)), DATA_EO!A:A, 0)) & ", " & INDEX(DATA_EO!J:J, MATCH(TRIM(MID(SUBSTITUTE(INDEX(DATA_KO!E:E, MATCH(3, DATA_KO!K:K, 0)), ",", REPT(" ", 500)), 1001, 500)), DATA_EO!A:A, 0)) & ")")), "")}
A68: {=IFERROR(IF(INDEX(DATA_KO!A:A, MATCH(4, DATA_KO!K:K, 0))="","", "▼ Concept:"), "")} | B68: {=IFERROR(IF(INDEX(DATA_KO!A:A, MATCH(4, DATA_KO!K:K, 0))="","", INDEX(DATA_KO!B:B, MATCH(4, DATA_KO!K:K, 0))), "")} | E68: {=IFERROR(IF(INDEX(DATA_KO!A:A, MATCH(4, DATA_KO!K:K, 0))="","", "[[" & INDEX(DATA_KO!A:A, MATCH(4, DATA_KO!K:K, 0)) & "]]"), "")} | F68: {=IFERROR(IF(INDEX(DATA_KO!A:A, MATCH(4, DATA_KO!K:K, 0))="","", "IO: " & INDEX(DATA_KO!R:R, MATCH(4, DATA_KO!K:K, 0)) & " | EO: " & INDEX(DATA_KO!Q:Q, MATCH(4, DATA_KO!K:K, 0)) & " | Conf: " & TEXT(INDEX(DATA_KO!G:G, MATCH(4, DATA_KO!K:K, 0)), "0.00")), "")} | G68: {=IFERROR(IF(INDEX(DATA_KO!A:A, MATCH(4, DATA_KO!K:K, 0))="","", "Domain: " & INDEX(DATA_KO!C:C, MATCH(4, DATA_KO!K:K, 0))), "")} | H68: {=IFERROR(IF(INDEX(DATA_KO!A:A, MATCH(4, DATA_KO!K:K, 0))="","", HYPERLINK("#'04_Lineage_Explorer'!B6", "➔ [Inspect Lineage]")), "")}
B69: {=IFERROR(IF(INDEX(DATA_KO!A:A, MATCH(4, DATA_KO!K:K, 0))="","", " ▼ Supporting Interpretations (Layer 2) — " & INDEX(DATA_KO!R:R, MATCH(4, DATA_KO!K:K, 0)) & " Models"), "")}
B70: {=IFERROR(IF(INDEX(DATA_KO!A:A, MATCH(4, DATA_KO!K:K, 0))="","", " • [[" & TRIM(MID(SUBSTITUTE(INDEX(DATA_KO!F:F, MATCH(4, DATA_KO!K:K, 0)), ",", REPT(" ", 500)), 1, 500)) & "]] — " & INDEX(DATA_IO!B:B, MATCH(TRIM(MID(SUBSTITUTE(INDEX(DATA_KO!F:F, MATCH(4, DATA_KO!K:K, 0)), ",", REPT(" ", 500)), 1, 500)), DATA_IO!A:A, 0))), "")}
B71: {=IFERROR(IF(INDEX(DATA_KO!A:A, MATCH(4, DATA_KO!K:K, 0))="","", IF(ISERROR(FIND(",", INDEX(DATA_KO!F:F, MATCH(4, DATA_KO!K:K, 0)))), "", " • [[" & TRIM(MID(SUBSTITUTE(INDEX(DATA_KO!F:F, MATCH(4, DATA_KO!K:K, 0)), ",", REPT(" ", 500)), 501, 500)) & "]] — " & INDEX(DATA_IO!B:B, MATCH(TRIM(MID(SUBSTITUTE(INDEX(DATA_KO!F:F, MATCH(4, DATA_KO!K:K, 0)), ",", REPT(" ", 500)), 501, 500)), DATA_IO!A:A, 0)))), "")}
B72: {=IFERROR(IF(INDEX(DATA_KO!A:A, MATCH(4, DATA_KO!K:K, 0))="","", " ▼ Grounding Evidence (Layer 1) — " & INDEX(DATA_KO!Q:Q, MATCH(4, DATA_KO!K:K, 0)) & " Empirical Anchors"), "")}
B73: {=IFERROR(IF(INDEX(DATA_KO!A:A, MATCH(4, DATA_KO!K:K, 0))="","", " • [[" & TRIM(MID(SUBSTITUTE(INDEX(DATA_KO!E:E, MATCH(4, DATA_KO!K:K, 0)), ",", REPT(" ", 500)), 1, 500)) & "]] — " & INDEX(DATA_EO!L:L, MATCH(TRIM(MID(SUBSTITUTE(INDEX(DATA_KO!E:E, MATCH(4, DATA_KO!K:K, 0)), ",", REPT(" ", 500)), 1, 500)), DATA_EO!A:A, 0)) & " (Source: " & INDEX(DATA_EO!B:B, MATCH(TRIM(MID(SUBSTITUTE(INDEX(DATA_KO!E:E, MATCH(4, DATA_KO!K:K, 0)), ",", REPT(" ", 500)), 1, 500)), DATA_EO!A:A, 0)) & ", " & INDEX(DATA_EO!J:J, MATCH(TRIM(MID(SUBSTITUTE(INDEX(DATA_KO!E:E, MATCH(4, DATA_KO!K:K, 0)), ",", REPT(" ", 500)), 1, 500)), DATA_EO!A:A, 0)) & ")"), "")}
B74: {=IFERROR(IF(INDEX(DATA_KO!A:A, MATCH(4, DATA_KO!K:K, 0))="","", IF(ISERROR(FIND(",", INDEX(DATA_KO!E:E, MATCH(4, DATA_KO!K:K, 0)))), "", " • [[" & TRIM(MID(SUBSTITUTE(INDEX(DATA_KO!E:E, MATCH(4, DATA_KO!K:K, 0)), ",", REPT(" ", 500)), 501, 500)) & "]] — " & INDEX(DATA_EO!L:L, MATCH(TRIM(MID(SUBSTITUTE(INDEX(DATA_KO!E:E, MATCH(4, DATA_KO!K:K, 0)), ",", REPT(" ", 500)), 501, 500)), DATA_EO!A:A, 0)) & " (Source: " & INDEX(DATA_EO!B:B, MATCH(TRIM(MID(SUBSTITUTE(INDEX(DATA_KO!E:E, MATCH(4, DATA_KO!K:K, 0)), ",", REPT(" ", 500)), 501, 500)), DATA_EO!A:A, 0)) & ", " & INDEX(DATA_EO!J:J, MATCH(TRIM(MID(SUBSTITUTE(INDEX(DATA_KO!E:E, MATCH(4, DATA_KO!K:K, 0)), ",", REPT(" ", 500)), 501, 500)), DATA_EO!A:A, 0)) & ")")), "")}
B75: {=IFERROR(IF(INDEX(DATA_KO!A:A, MATCH(4, DATA_KO!K:K, 0))="","", IF(LEN(INDEX(DATA_KO!E:E, MATCH(4, DATA_KO!K:K, 0)))-LEN(SUBSTITUTE(INDEX(DATA_KO!E:E, MATCH(4, DATA_KO!K:K, 0)), ",", "" ))<2, "", " • [[" & TRIM(MID(SUBSTITUTE(INDEX(DATA_KO!E:E, MATCH(4, DATA_KO!K:K, 0)), ",", REPT(" ", 500)), 1001, 500)) & "]] — " & INDEX(DATA_EO!L:L, MATCH(TRIM(MID(SUBSTITUTE(INDEX(DATA_KO!E:E, MATCH(4, DATA_KO!K:K, 0)), ",", REPT(" ", 500)), 1001, 500)), DATA_EO!A:A, 0)) & " (Source: " & INDEX(DATA_EO!B:B, MATCH(TRIM(MID(SUBSTITUTE(INDEX(DATA_KO!E:E, MATCH(4, DATA_KO!K:K, 0)), ",", REPT(" ", 500)), 1001, 500)), DATA_EO!A:A, 0)) & ", " & INDEX(DATA_EO!J:J, MATCH(TRIM(MID(SUBSTITUTE(INDEX(DATA_KO!E:E, MATCH(4, DATA_KO!K:K, 0)), ",", REPT(" ", 500)), 1001, 500)), DATA_EO!A:A, 0)) & ")")), "")}
A77: {=IFERROR(IF(INDEX(DATA_KO!A:A, MATCH(5, DATA_KO!K:K, 0))="","", "▼ Concept:"), "")} | B77: {=IFERROR(IF(INDEX(DATA_KO!A:A, MATCH(5, DATA_KO!K:K, 0))="","", INDEX(DATA_KO!B:B, MATCH(5, DATA_KO!K:K, 0))), "")} | E77: {=IFERROR(IF(INDEX(DATA_KO!A:A, MATCH(5, DATA_KO!K:K, 0))="","", "[[" & INDEX(DATA_KO!A:A, MATCH(5, DATA_KO!K:K, 0)) & "]]"), "")} | F77: {=IFERROR(IF(INDEX(DATA_KO!A:A, MATCH(5, DATA_KO!K:K, 0))="","", "IO: " & INDEX(DATA_KO!R:R, MATCH(5, DATA_KO!K:K, 0)) & " | EO: " & INDEX(DATA_KO!Q:Q, MATCH(5, DATA_KO!K:K, 0)) & " | Conf: " & TEXT(INDEX(DATA_KO!G:G, MATCH(5, DATA_KO!K:K, 0)), "0.00")), "")} | G77: {=IFERROR(IF(INDEX(DATA_KO!A:A, MATCH(5, DATA_KO!K:K, 0))="","", "Domain: " & INDEX(DATA_KO!C:C, MATCH(5, DATA_KO!K:K, 0))), "")} | H77: {=IFERROR(IF(INDEX(DATA_KO!A:A, MATCH(5, DATA_KO!K:K, 0))="","", HYPERLINK("#'04_Lineage_Explorer'!B6", "➔ [Inspect Lineage]")), "")}
B78: {=IFERROR(IF(INDEX(DATA_KO!A:A, MATCH(5, DATA_KO!K:K, 0))="","", " ▼ Supporting Interpretations (Layer 2) — " & INDEX(DATA_KO!R:R, MATCH(5, DATA_KO!K:K, 0)) & " Models"), "")}
B79: {=IFERROR(IF(INDEX(DATA_KO!A:A, MATCH(5, DATA_KO!K:K, 0))="","", " • [[" & TRIM(MID(SUBSTITUTE(INDEX(DATA_KO!F:F, MATCH(5, DATA_KO!K:K, 0)), ",", REPT(" ", 500)), 1, 500)) & "]] — " & INDEX(DATA_IO!B:B, MATCH(TRIM(MID(SUBSTITUTE(INDEX(DATA_KO!F:F, MATCH(5, DATA_KO!K:K, 0)), ",", REPT(" ", 500)), 1, 500)), DATA_IO!A:A, 0))), "")}
B80: {=IFERROR(IF(INDEX(DATA_KO!A:A, MATCH(5, DATA_KO!K:K, 0))="","", IF(ISERROR(FIND(",", INDEX(DATA_KO!F:F, MATCH(5, DATA_KO!K:K, 0)))), "", " • [[" & TRIM(MID(SUBSTITUTE(INDEX(DATA_KO!F:F, MATCH(5, DATA_KO!K:K, 0)), ",", REPT(" ", 500)), 501, 500)) & "]] — " & INDEX(DATA_IO!B:B, MATCH(TRIM(MID(SUBSTITUTE(INDEX(DATA_KO!F:F, MATCH(5, DATA_KO!K:K, 0)), ",", REPT(" ", 500)), 501, 500)), DATA_IO!A:A, 0)))), "")}
B81: {=IFERROR(IF(INDEX(DATA_KO!A:A, MATCH(5, DATA_KO!K:K, 0))="","", " ▼ Grounding Evidence (Layer 1) — " & INDEX(DATA_KO!Q:Q, MATCH(5, DATA_KO!K:K, 0)) & " Empirical Anchors"), "")}
B82: {=IFERROR(IF(INDEX(DATA_KO!A:A, MATCH(5, DATA_KO!K:K, 0))="","", " • [[" & TRIM(MID(SUBSTITUTE(INDEX(DATA_KO!E:E, MATCH(5, DATA_KO!K:K, 0)), ",", REPT(" ", 500)), 1, 500)) & "]] — " & INDEX(DATA_EO!L:L, MATCH(TRIM(MID(SUBSTITUTE(INDEX(DATA_KO!E:E, MATCH(5, DATA_KO!K:K, 0)), ",", REPT(" ", 500)), 1, 500)), DATA_EO!A:A, 0)) & " (Source: " & INDEX(DATA_EO!B:B, MATCH(TRIM(MID(SUBSTITUTE(INDEX(DATA_KO!E:E, MATCH(5, DATA_KO!K:K, 0)), ",", REPT(" ", 500)), 1, 500)), DATA_EO!A:A, 0)) & ", " & INDEX(DATA_EO!J:J, MATCH(TRIM(MID(SUBSTITUTE(INDEX(DATA_KO!E:E, MATCH(5, DATA_KO!K:K, 0)), ",", REPT(" ", 500)), 1, 500)), DATA_EO!A:A, 0)) & ")"), "")}
B83: {=IFERROR(IF(INDEX(DATA_KO!A:A, MATCH(5, DATA_KO!K:K, 0))="","", IF(ISERROR(FIND(",", INDEX(DATA_KO!E:E, MATCH(5, DATA_KO!K:K, 0)))), "", " • [[" & TRIM(MID(SUBSTITUTE(INDEX(DATA_KO!E:E, MATCH(5, DATA_KO!K:K, 0)), ",", REPT(" ", 500)), 501, 500)) & "]] — " & INDEX(DATA_EO!L:L, MATCH(TRIM(MID(SUBSTITUTE(INDEX(DATA_KO!E:E, MATCH(5, DATA_KO!K:K, 0)), ",", REPT(" ", 500)), 501, 500)), DATA_EO!A:A, 0)) & " (Source: " & INDEX(DATA_EO!B:B, MATCH(TRIM(MID(SUBSTITUTE(INDEX(DATA_KO!E:E, MATCH(5, DATA_KO!K:K, 0)), ",", REPT(" ", 500)), 501, 500)), DATA_EO!A:A, 0)) & ", " & INDEX(DATA_EO!J:J, MATCH(TRIM(MID(SUBSTITUTE(INDEX(DATA_KO!E:E, MATCH(5, DATA_KO!K:K, 0)), ",", REPT(" ", 500)), 501, 500)), DATA_EO!A:A, 0)) & ")")), "")}
B84: {=IFERROR(IF(INDEX(DATA_KO!A:A, MATCH(5, DATA_KO!K:K, 0))="","", IF(LEN(INDEX(DATA_KO!E:E, MATCH(5, DATA_KO!K:K, 0)))-LEN(SUBSTITUTE(INDEX(DATA_KO!E:E, MATCH(5, DATA_KO!K:K, 0)), ",", "" ))<2, "", " • [[" & TRIM(MID(SUBSTITUTE(INDEX(DATA_KO!E:E, MATCH(5, DATA_KO!K:K, 0)), ",", REPT(" ", 500)), 1001, 500)) & "]] — " & INDEX(DATA_EO!L:L, MATCH(TRIM(MID(SUBSTITUTE(INDEX(DATA_KO!E:E, MATCH(5, DATA_KO!K:K, 0)), ",", REPT(" ", 500)), 1001, 500)), DATA_EO!A:A, 0)) & " (Source: " & INDEX(DATA_EO!B:B, MATCH(TRIM(MID(SUBSTITUTE(INDEX(DATA_KO!E:E, MATCH(5, DATA_KO!K:K, 0)), ",", REPT(" ", 500)), 1001, 500)), DATA_EO!A:A, 0)) & ", " & INDEX(DATA_EO!J:J, MATCH(TRIM(MID(SUBSTITUTE(INDEX(DATA_KO!E:E, MATCH(5, DATA_KO!K:K, 0)), ",", REPT(" ", 500)), 1001, 500)), DATA_EO!A:A, 0)) & ")")), "")}
A86: {=IFERROR(IF(INDEX(DATA_KO!A:A, MATCH(6, DATA_KO!K:K, 0))="","", "▼ Concept:"), "")} | B86: {=IFERROR(IF(INDEX(DATA_KO!A:A, MATCH(6, DATA_KO!K:K, 0))="","", INDEX(DATA_KO!B:B, MATCH(6, DATA_KO!K:K, 0))), "")} | E86: {=IFERROR(IF(INDEX(DATA_KO!A:A, MATCH(6, DATA_KO!K:K, 0))="","", "[[" & INDEX(DATA_KO!A:A, MATCH(6, DATA_KO!K:K, 0)) & "]]"), "")} | F86: {=IFERROR(IF(INDEX(DATA_KO!A:A, MATCH(6, DATA_KO!K:K, 0))="","", "IO: " & INDEX(DATA_KO!R:R, MATCH(6, DATA_KO!K:K, 0)) & " | EO: " & INDEX(DATA_KO!Q:Q, MATCH(6, DATA_KO!K:K, 0)) & " | Conf: " & TEXT(INDEX(DATA_KO!G:G, MATCH(6, DATA_KO!K:K, 0)), "0.00")), "")} | G86: {=IFERROR(IF(INDEX(DATA_KO!A:A, MATCH(6, DATA_KO!K:K, 0))="","", "Domain: " & INDEX(DATA_KO!C:C, MATCH(6, DATA_KO!K:K, 0))), "")} | H86: {=IFERROR(IF(INDEX(DATA_KO!A:A, MATCH(6, DATA_KO!K:K, 0))="","", HYPERLINK("#'04_Lineage_Explorer'!B6", "➔ [Inspect Lineage]")), "")}
B87: {=IFERROR(IF(INDEX(DATA_KO!A:A, MATCH(6, DATA_KO!K:K, 0))="","", " ▼ Supporting Interpretations (Layer 2) — " & INDEX(DATA_KO!R:R, MATCH(6, DATA_KO!K:K, 0)) & " Models"), "")}
B88: {=IFERROR(IF(INDEX(DATA_KO!A:A, MATCH(6, DATA_KO!K:K, 0))="","", " • [[" & TRIM(MID(SUBSTITUTE(INDEX(DATA_KO!F:F, MATCH(6, DATA_KO!K:K, 0)), ",", REPT(" ", 500)), 1, 500)) & "]] — " & INDEX(DATA_IO!B:B, MATCH(TRIM(MID(SUBSTITUTE(INDEX(DATA_KO!F:F, MATCH(6, DATA_KO!K:K, 0)), ",", REPT(" ", 500)), 1, 500)), DATA_IO!A:A, 0))), "")}
B89: {=IFERROR(IF(INDEX(DATA_KO!A:A, MATCH(6, DATA_KO!K:K, 0))="","", IF(ISERROR(FIND(",", INDEX(DATA_KO!F:F, MATCH(6, DATA_KO!K:K, 0)))), "", " • [[" & TRIM(MID(SUBSTITUTE(INDEX(DATA_KO!F:F, MATCH(6, DATA_KO!K:K, 0)), ",", REPT(" ", 500)), 501, 500)) & "]] — " & INDEX(DATA_IO!B:B, MATCH(TRIM(MID(SUBSTITUTE(INDEX(DATA_KO!F:F, MATCH(6, DATA_KO!K:K, 0)), ",", REPT(" ", 500)), 501, 500)), DATA_IO!A:A, 0)))), "")}
B90: {=IFERROR(IF(INDEX(DATA_KO!A:A, MATCH(6, DATA_KO!K:K, 0))="","", " ▼ Grounding Evidence (Layer 1) — " & INDEX(DATA_KO!Q:Q, MATCH(6, DATA_KO!K:K, 0)) & " Empirical Anchors"), "")}
B91: {=IFERROR(IF(INDEX(DATA_KO!A:A, MATCH(6, DATA_KO!K:K, 0))="","", " • [[" & TRIM(MID(SUBSTITUTE(INDEX(DATA_KO!E:E, MATCH(6, DATA_KO!K:K, 0)), ",", REPT(" ", 500)), 1, 500)) & "]] — " & INDEX(DATA_EO!L:L, MATCH(TRIM(MID(SUBSTITUTE(INDEX(DATA_KO!E:E, MATCH(6, DATA_KO!K:K, 0)), ",", REPT(" ", 500)), 1, 500)), DATA_EO!A:A, 0)) & " (Source: " & INDEX(DATA_EO!B:B, MATCH(TRIM(MID(SUBSTITUTE(INDEX(DATA_KO!E:E, MATCH(6, DATA_KO!K:K, 0)), ",", REPT(" ", 500)), 1, 500)), DATA_EO!A:A, 0)) & ", " & INDEX(DATA_EO!J:J, MATCH(TRIM(MID(SUBSTITUTE(INDEX(DATA_KO!E:E, MATCH(6, DATA_KO!K:K, 0)), ",", REPT(" ", 500)), 1, 500)), DATA_EO!A:A, 0)) & ")"), "")}
B92: {=IFERROR(IF(INDEX(DATA_KO!A:A, MATCH(6, DATA_KO!K:K, 0))="","", IF(ISERROR(FIND(",", INDEX(DATA_KO!E:E, MATCH(6, DATA_KO!K:K, 0)))), "", " • [[" & TRIM(MID(SUBSTITUTE(INDEX(DATA_KO!E:E, MATCH(6, DATA_KO!K:K, 0)), ",", REPT(" ", 500)), 501, 500)) & "]] — " & INDEX(DATA_EO!L:L, MATCH(TRIM(MID(SUBSTITUTE(INDEX(DATA_KO!E:E, MATCH(6, DATA_KO!K:K, 0)), ",", REPT(" ", 500)), 501, 500)), DATA_EO!A:A, 0)) & " (Source: " & INDEX(DATA_EO!B:B, MATCH(TRIM(MID(SUBSTITUTE(INDEX(DATA_KO!E:E, MATCH(6, DATA_KO!K:K, 0)), ",", REPT(" ", 500)), 501, 500)), DATA_EO!A:A, 0)) & ", " & INDEX(DATA_EO!J:J, MATCH(TRIM(MID(SUBSTITUTE(INDEX(DATA_KO!E:E, MATCH(6, DATA_KO!K:K, 0)), ",", REPT(" ", 500)), 501, 500)), DATA_EO!A:A, 0)) & ")")), "")}
B93: {=IFERROR(IF(INDEX(DATA_KO!A:A, MATCH(6, DATA_KO!K:K, 0))="","", IF(LEN(INDEX(DATA_KO!E:E, MATCH(6, DATA_KO!K:K, 0)))-LEN(SUBSTITUTE(INDEX(DATA_KO!E:E, MATCH(6, DATA_KO!K:K, 0)), ",", "" ))<2, "", " • [[" & TRIM(MID(SUBSTITUTE(INDEX(DATA_KO!E:E, MATCH(6, DATA_KO!K:K, 0)), ",", REPT(" ", 500)), 1001, 500)) & "]] — " & INDEX(DATA_EO!L:L, MATCH(TRIM(MID(SUBSTITUTE(INDEX(DATA_KO!E:E, MATCH(6, DATA_KO!K:K, 0)), ",", REPT(" ", 500)), 1001, 500)), DATA_EO!A:A, 0)) & " (Source: " & INDEX(DATA_EO!B:B, MATCH(TRIM(MID(SUBSTITUTE(INDEX(DATA_KO!E:E, MATCH(6, DATA_KO!K:K, 0)), ",", REPT(" ", 500)), 1001, 500)), DATA_EO!A:A, 0)) & ", " & INDEX(DATA_EO!J:J, MATCH(TRIM(MID(SUBSTITUTE(INDEX(DATA_KO!E:E, MATCH(6, DATA_KO!K:K, 0)), ",", REPT(" ", 500)), 1001, 500)), DATA_EO!A:A, 0)) & ")")), "")}
A95: {=IFERROR(IF(INDEX(DATA_KO!A:A, MATCH(7, DATA_KO!K:K, 0))="","", "▼ Concept:"), "")} | B95: {=IFERROR(IF(INDEX(DATA_KO!A:A, MATCH(7, DATA_KO!K:K, 0))="","", INDEX(DATA_KO!B:B, MATCH(7, DATA_KO!K:K, 0))), "")} | E95: {=IFERROR(IF(INDEX(DATA_KO!A:A, MATCH(7, DATA_KO!K:K, 0))="","", "[[" & INDEX(DATA_KO!A:A, MATCH(7, DATA_KO!K:K, 0)) & "]]"), "")} | F95: {=IFERROR(IF(INDEX(DATA_KO!A:A, MATCH(7, DATA_KO!K:K, 0))="","", "IO: " & INDEX(DATA_KO!R:R, MATCH(7, DATA_KO!K:K, 0)) & " | EO: " & INDEX(DATA_KO!Q:Q, MATCH(7, DATA_KO!K:K, 0)) & " | Conf: " & TEXT(INDEX(DATA_KO!G:G, MATCH(7, DATA_KO!K:K, 0)), "0.00")), "")} | G95: {=IFERROR(IF(INDEX(DATA_KO!A:A, MATCH(7, DATA_KO!K:K, 0))="","", "Domain: " & INDEX(DATA_KO!C:C, MATCH(7, DATA_KO!K:K, 0))), "")} | H95: {=IFERROR(IF(INDEX(DATA_KO!A:A, MATCH(7, DATA_KO!K:K, 0))="","", HYPERLINK("#'04_Lineage_Explorer'!B6", "➔ [Inspect Lineage]")), "")}
B96: {=IFERROR(IF(INDEX(DATA_KO!A:A, MATCH(7, DATA_KO!K:K, 0))="","", " ▼ Supporting Interpretations (Layer 2) — " & INDEX(DATA_KO!R:R, MATCH(7, DATA_KO!K:K, 0)) & " Models"), "")}
B97: {=IFERROR(IF(INDEX(DATA_KO!A:A, MATCH(7, DATA_KO!K:K, 0))="","", " • [[" & TRIM(MID(SUBSTITUTE(INDEX(DATA_KO!F:F, MATCH(7, DATA_KO!K:K, 0)), ",", REPT(" ", 500)), 1, 500)) & "]] — " & INDEX(DATA_IO!B:B, MATCH(TRIM(MID(SUBSTITUTE(INDEX(DATA_KO!F:F, MATCH(7, DATA_KO!K:K, 0)), ",", REPT(" ", 500)), 1, 500)), DATA_IO!A:A, 0))), "")}
B98: {=IFERROR(IF(INDEX(DATA_KO!A:A, MATCH(7, DATA_KO!K:K, 0))="","", IF(ISERROR(FIND(",", INDEX(DATA_KO!F:F, MATCH(7, DATA_KO!K:K, 0)))), "", " • [[" & TRIM(MID(SUBSTITUTE(INDEX(DATA_KO!F:F, MATCH(7, DATA_KO!K:K, 0)), ",", REPT(" ", 500)), 501, 500)) & "]] — " & INDEX(DATA_IO!B:B, MATCH(TRIM(MID(SUBSTITUTE(INDEX(DATA_KO!F:F, MATCH(7, DATA_KO!K:K, 0)), ",", REPT(" ", 500)), 501, 500)), DATA_IO!A:A, 0)))), "")}
B99: {=IFERROR(IF(INDEX(DATA_KO!A:A, MATCH(7, DATA_KO!K:K, 0))="","", " ▼ Grounding Evidence (Layer 1) — " & INDEX(DATA_KO!Q:Q, MATCH(7, DATA_KO!K:K, 0)) & " Empirical Anchors"), "")}
B100: {=IFERROR(IF(INDEX(DATA_KO!A:A, MATCH(7, DATA_KO!K:K, 0))="","", " • [[" & TRIM(MID(SUBSTITUTE(INDEX(DATA_KO!E:E, MATCH(7, DATA_KO!K:K, 0)), ",", REPT(" ", 500)), 1, 500)) & "]] — " & INDEX(DATA_EO!L:L, MATCH(TRIM(MID(SUBSTITUTE(INDEX(DATA_KO!E:E, MATCH(7, DATA_KO!K:K, 0)), ",", REPT(" ", 500)), 1, 500)), DATA_EO!A:A, 0)) & " (Source: " & INDEX(DATA_EO!B:B, MATCH(TRIM(MID(SUBSTITUTE(INDEX(DATA_KO!E:E, MATCH(7, DATA_KO!K:K, 0)), ",", REPT(" ", 500)), 1, 500)), DATA_EO!A:A, 0)) & ", " & INDEX(DATA_EO!J:J, MATCH(TRIM(MID(SUBSTITUTE(INDEX(DATA_KO!E:E, MATCH(7, DATA_KO!K:K, 0)), ",", REPT(" ", 500)), 1, 500)), DATA_EO!A:A, 0)) & ")"), "")}
B101: {=IFERROR(IF(INDEX(DATA_KO!A:A, MATCH(7, DATA_KO!K:K, 0))="","", IF(ISERROR(FIND(",", INDEX(DATA_KO!E:E, MATCH(7, DATA_KO!K:K, 0)))), "", " • [[" & TRIM(MID(SUBSTITUTE(INDEX(DATA_KO!E:E, MATCH(7, DATA_KO!K:K, 0)), ",", REPT(" ", 500)), 501, 500)) & "]] — " & INDEX(DATA_EO!L:L, MATCH(TRIM(MID(SUBSTITUTE(INDEX(DATA_KO!E:E, MATCH(7, DATA_KO!K:K, 0)), ",", REPT(" ", 500)), 501, 500)), DATA_EO!A:A, 0)) & " (Source: " & INDEX(DATA_EO!B:B, MATCH(TRIM(MID(SUBSTITUTE(INDEX(DATA_KO!E:E, MATCH(7, DATA_KO!K:K, 0)), ",", REPT(" ", 500)), 501, 500)), DATA_EO!A:A, 0)) & ", " & INDEX(DATA_EO!J:J, MATCH(TRIM(MID(SUBSTITUTE(INDEX(DATA_KO!E:E, MATCH(7, DATA_KO!K:K, 0)), ",", REPT(" ", 500)), 501, 500)), DATA_EO!A:A, 0)) & ")")), "")}
B102: {=IFERROR(IF(INDEX(DATA_KO!A:A, MATCH(7, DATA_KO!K:K, 0))="","", IF(LEN(INDEX(DATA_KO!E:E, MATCH(7, DATA_KO!K:K, 0)))-LEN(SUBSTITUTE(INDEX(DATA_KO!E:E, MATCH(7, DATA_KO!K:K, 0)), ",", "" ))<2, "", " • [[" & TRIM(MID(SUBSTITUTE(INDEX(DATA_KO!E:E, MATCH(7, DATA_KO!K:K, 0)), ",", REPT(" ", 500)), 1001, 500)) & "]] — " & INDEX(DATA_EO!L:L, MATCH(TRIM(MID(SUBSTITUTE(INDEX(DATA_KO!E:E, MATCH(7, DATA_KO!K:K, 0)), ",", REPT(" ", 500)), 1001, 500)), DATA_EO!A:A, 0)) & " (Source: " & INDEX(DATA_EO!B:B, MATCH(TRIM(MID(SUBSTITUTE(INDEX(DATA_KO!E:E, MATCH(7, DATA_KO!K:K, 0)), ",", REPT(" ", 500)), 1001, 500)), DATA_EO!A:A, 0)) & ", " & INDEX(DATA_EO!J:J, MATCH(TRIM(MID(SUBSTITUTE(INDEX(DATA_KO!E:E, MATCH(7, DATA_KO!K:K, 0)), ",", REPT(" ", 500)), 1001, 500)), DATA_EO!A:A, 0)) & ")")), "")}
A104: {=IFERROR(IF(INDEX(DATA_KO!A:A, MATCH(8, DATA_KO!K:K, 0))="","", "▼ Concept:"), "")} | B104: {=IFERROR(IF(INDEX(DATA_KO!A:A, MATCH(8, DATA_KO!K:K, 0))="","", INDEX(DATA_KO!B:B, MATCH(8, DATA_KO!K:K, 0))), "")} | E104: {=IFERROR(IF(INDEX(DATA_KO!A:A, MATCH(8, DATA_KO!K:K, 0))="","", "[[" & INDEX(DATA_KO!A:A, MATCH(8, DATA_KO!K:K, 0)) & "]]"), "")} | F104: {=IFERROR(IF(INDEX(DATA_KO!A:A, MATCH(8, DATA_KO!K:K, 0))="","", "IO: " & INDEX(DATA_KO!R:R, MATCH(8, DATA_KO!K:K, 0)) & " | EO: " & INDEX(DATA_KO!Q:Q, MATCH(8, DATA_KO!K:K, 0)) & " | Conf: " & TEXT(INDEX(DATA_KO!G:G, MATCH(8, DATA_KO!K:K, 0)), "0.00")), "")} | G104: {=IFERROR(IF(INDEX(DATA_KO!A:A, MATCH(8, DATA_KO!K:K, 0))="","", "Domain: " & INDEX(DATA_KO!C:C, MATCH(8, DATA_KO!K:K, 0))), "")} | H104: {=IFERROR(IF(INDEX(DATA_KO!A:A, MATCH(8, DATA_KO!K:K, 0))="","", HYPERLINK("#'04_Lineage_Explorer'!B6", "➔ [Inspect Lineage]")), "")}
B105: {=IFERROR(IF(INDEX(DATA_KO!A:A, MATCH(8, DATA_KO!K:K, 0))="","", " ▼ Supporting Interpretations (Layer 2) — " & INDEX(DATA_KO!R:R, MATCH(8, DATA_KO!K:K, 0)) & " Models"), "")}
B106: {=IFERROR(IF(INDEX(DATA_KO!A:A, MATCH(8, DATA_KO!K:K, 0))="","", " • [[" & TRIM(MID(SUBSTITUTE(INDEX(DATA_KO!F:F, MATCH(8, DATA_KO!K:K, 0)), ",", REPT(" ", 500)), 1, 500)) & "]] — " & INDEX(DATA_IO!B:B, MATCH(TRIM(MID(SUBSTITUTE(INDEX(DATA_KO!F:F, MATCH(8, DATA_KO!K:K, 0)), ",", REPT(" ", 500)), 1, 500)), DATA_IO!A:A, 0))), "")}
B107: {=IFERROR(IF(INDEX(DATA_KO!A:A, MATCH(8, DATA_KO!K:K, 0))="","", IF(ISERROR(FIND(",", INDEX(DATA_KO!F:F, MATCH(8, DATA_KO!K:K, 0)))), "", " • [[" & TRIM(MID(SUBSTITUTE(INDEX(DATA_KO!F:F, MATCH(8, DATA_KO!K:K, 0)), ",", REPT(" ", 500)), 501, 500)) & "]] — " & INDEX(DATA_IO!B:B, MATCH(TRIM(MID(SUBSTITUTE(INDEX(DATA_KO!F:F, MATCH(8, DATA_KO!K:K, 0)), ",", REPT(" ", 500)), 501, 500)), DATA_IO!A:A, 0)))), "")}
B108: {=IFERROR(IF(INDEX(DATA_KO!A:A, MATCH(8, DATA_KO!K:K, 0))="","", " ▼ Grounding Evidence (Layer 1) — " & INDEX(DATA_KO!Q:Q, MATCH(8, DATA_KO!K:K, 0)) & " Empirical Anchors"), "")}
B109: {=IFERROR(IF(INDEX(DATA_KO!A:A, MATCH(8, DATA_KO!K:K, 0))="","", " • [[" & TRIM(MID(SUBSTITUTE(INDEX(DATA_KO!E:E, MATCH(8, DATA_KO!K:K, 0)), ",", REPT(" ", 500)), 1, 500)) & "]] — " & INDEX(DATA_EO!L:L, MATCH(TRIM(MID(SUBSTITUTE(INDEX(DATA_KO!E:E, MATCH(8, DATA_KO!K:K, 0)), ",", REPT(" ", 500)), 1, 500)), DATA_EO!A:A, 0)) & " (Source: " & INDEX(DATA_EO!B:B, MATCH(TRIM(MID(SUBSTITUTE(INDEX(DATA_KO!E:E, MATCH(8, DATA_KO!K:K, 0)), ",", REPT(" ", 500)), 1, 500)), DATA_EO!A:A, 0)) & ", " & INDEX(DATA_EO!J:J, MATCH(TRIM(MID(SUBSTITUTE(INDEX(DATA_KO!E:E, MATCH(8, DATA_KO!K:K, 0)), ",", REPT(" ", 500)), 1, 500)), DATA_EO!A:A, 0)) & ")"), "")}
B110: {=IFERROR(IF(INDEX(DATA_KO!A:A, MATCH(8, DATA_KO!K:K, 0))="","", IF(ISERROR(FIND(",", INDEX(DATA_KO!E:E, MATCH(8, DATA_KO!K:K, 0)))), "", " • [[" & TRIM(MID(SUBSTITUTE(INDEX(DATA_KO!E:E, MATCH(8, DATA_KO!K:K, 0)), ",", REPT(" ", 500)), 501, 500)) & "]] — " & INDEX(DATA_EO!L:L, MATCH(TRIM(MID(SUBSTITUTE(INDEX(DATA_KO!E:E, MATCH(8, DATA_KO!K:K, 0)), ",", REPT(" ", 500)), 501, 500)), DATA_EO!A:A, 0)) & " (Source: " & INDEX(DATA_EO!B:B, MATCH(TRIM(MID(SUBSTITUTE(INDEX(DATA_KO!E:E, MATCH(8, DATA_KO!K:K, 0)), ",", REPT(" ", 500)), 501, 500)), DATA_EO!A:A, 0)) & ", " & INDEX(DATA_EO!J:J, MATCH(TRIM(MID(SUBSTITUTE(INDEX(DATA_KO!E:E, MATCH(8, DATA_KO!K:K, 0)), ",", REPT(" ", 500)), 501, 500)), DATA_EO!A:A, 0)) & ")")), "")}
B111: {=IFERROR(IF(INDEX(DATA_KO!A:A, MATCH(8, DATA_KO!K:K, 0))="","", IF(LEN(INDEX(DATA_KO!E:E, MATCH(8, DATA_KO!K:K, 0)))-LEN(SUBSTITUTE(INDEX(DATA_KO!E:E, MATCH(8, DATA_KO!K:K, 0)), ",", "" ))<2, "", " • [[" & TRIM(MID(SUBSTITUTE(INDEX(DATA_KO!E:E, MATCH(8, DATA_KO!K:K, 0)), ",", REPT(" ", 500)), 1001, 500)) & "]] — " & INDEX(DATA_EO!L:L, MATCH(TRIM(MID(SUBSTITUTE(INDEX(DATA_KO!E:E, MATCH(8, DATA_KO!K:K, 0)), ",", REPT(" ", 500)), 1001, 500)), DATA_EO!A:A, 0)) & " (Source: " & INDEX(DATA_EO!B:B, MATCH(TRIM(MID(SUBSTITUTE(INDEX(DATA_KO!E:E, MATCH(8, DATA_KO!K:K, 0)), ",", REPT(" ", 500)), 1001, 500)), DATA_EO!A:A, 0)) & ", " & INDEX(DATA_EO!J:J, MATCH(TRIM(MID(SUBSTITUTE(INDEX(DATA_KO!E:E, MATCH(8, DATA_KO!K:K, 0)), ",", REPT(" ", 500)), 1001, 500)), DATA_EO!A:A, 0)) & ")")), "")}
...

Sheet 02_Object_Registry
A1: RESEARCH INTELLIGENCE ENGINE (RIE) — UNIFIED OBJECT REGISTRY PORTAL | G1: =HYPERLINK("#'01_Executive_Dashboard'!A1", "⮌ BACK TO DASHBOARD") | H1: =HYPERLINK("#'04_Lineage_Explorer'!A1", "➔ LINEAGE EXPLORER")
A2: ="Authoritative Epistemic Inventory (" & COUNTA(DATA_KO!A2:A1000) & " KOs, " & COUNTA(DATA_IO!A2:A1000) & " IOs, " & COUNTA(DATA_EO!A2:A1000) & " EOs = " & (COUNTA(DATA_KO!A2:A1000)+COUNTA(DATA_IO!A2:A1000)+COUNTA(DATA_EO!A2:A1000)) & " Total Objects) | Substrate Dynamic Projection"
A4: Dedicated Object Layer | B4: Count | C4: Layer Definition | D4: Direct Registry Access | E4: Confidence | F4: Workflow / Review Status | G4: Supporting References | H4: Lineage Action
A5: 02A: Knowledge Objects (KO) | B5: =COUNTA(DATA_KO!A2:A1000) | C5: Layer 3 synthesized institutional concepts awaiting Level 5 ratification | D5: =HYPERLINK("#'02A_KO_Registry'!A1", "➔ OPEN KO REGISTRY") | E5: 0.88 | F5: CANDIDATE | G5: CANDIDATE_QUEUE | H5: None
A6: 02B: Interpretation Objects (IO) | B6: =COUNTA(DATA_IO!A2:A1000) | C6: Layer 2 analytical models paired with competing counter-hypotheses | D6: =HYPERLINK("#'02B_IO_Registry'!A1", "➔ OPEN IO REGISTRY") | E6: 0.9 | F6: CANDIDATE | G6: CANDIDATE_QUEUE | H6: None
A7: 02C: Evidence Objects (EO) | B7: =COUNTA(DATA_EO!A2:A1000) | C7: Layer 1 ground truth empirical observations with exact timestamps | D7: =HYPERLINK("#'02C_EO_Registry'!A1", "➔ OPEN EO REGISTRY") | E7: 0.82 | F7: CANDIDATE | G7: CANDIDATE_QUEUE | H7: None
A8: KO-FIN-MINER-RATIO-BREAKOUT-001 | B8: KO | C8: Mining Equity Operating Leverage Base Breakout Dynamics | D8: Equity Technical Analysis / Resource Economics | E8: 0.86 | F8: CANDIDATE | G8: CANDIDATE_QUEUE | H8: None
A9: UNIFIED KNOWLEDGE OBJECT (KO) ACTIVE SUBSTRATE PROJECTION | B9: KO | C9: Pre-emptive Tightening Discounting and Policy Announcement Bottoms | D9: Macro Economics / Monetary Transmission | E9: 0.78 | F9: CANDIDATE | G9: CANDIDATE_QUEUE | H9: None
A10: Object_ID | B10: Object_Type | C10: Title / Concept | D10: Domain / Source Anchor | E10: Confidence | F10: Workflow / Review Status | G10: Supporting References | H10: Lineage Action
A11: =IF(DATA_KO!A2<>"",""&DATA_KO!A2,"") | B11: =IF(A11<>"","KO","") | C11: =IF(A11<>"",""&DATA_KO!B2,"") | D11: =IF(A11<>"",""&DATA_KO!C2,"") | E11: =IF(A11<>"",DATA_KO!G2,"") | F11: =IF(A11<>"",""&DATA_KO!H2,"") | G11: =IF(A11<>"",""&DATA_KO!E2,"") | H11: =IF(A11<>"","➔ Trace Lineage","")
A12: =IF(DATA_KO!A3<>"",""&DATA_KO!A3,"") | B12: =IF(A12<>"","KO","") | C12: =IF(A12<>"",""&DATA_KO!B3,"") | D12: =IF(A12<>"",""&DATA_KO!C3,"") | E12: =IF(A12<>"",DATA_KO!G3,"") | F12: =IF(A12<>"",""&DATA_KO!H3,"") | G12: =IF(A12<>"",""&DATA_KO!E3,"") | H12: =IF(A12<>"","➔ Trace Lineage","")
A13: =IF(DATA_KO!A4<>"",""&DATA_KO!A4,"") | B13: =IF(A13<>"","KO","") | C13: =IF(A13<>"",""&DATA_KO!B4,"") | D13: =IF(A13<>"",""&DATA_KO!C4,"") | E13: =IF(A13<>"",DATA_KO!G4,"") | F13: =IF(A13<>"",""&DATA_KO!H4,"") | G13: =IF(A13<>"",""&DATA_KO!E4,"") | H13: =IF(A13<>"","➔ Trace Lineage","")
A14: =IF(DATA_KO!A5<>"",""&DATA_KO!A5,"") | B14: =IF(A14<>"","KO","") | C14: =IF(A14<>"",""&DATA_KO!B5,"") | D14: =IF(A14<>"",""&DATA_KO!C5,"") | E14: =IF(A14<>"",DATA_KO!G5,"") | F14: =IF(A14<>"",""&DATA_KO!H5,"") | G14: =IF(A14<>"",""&DATA_KO!E5,"") | H14: =IF(A14<>"","➔ Trace Lineage","")
A15: =IF(DATA_KO!A6<>"",""&DATA_KO!A6,"") | B15: =IF(A15<>"","KO","") | C15: =IF(A15<>"",""&DATA_KO!B6,"") | D15: =IF(A15<>"",""&DATA_KO!C6,"") | E15: =IF(A15<>"",DATA_KO!G6,"") | F15: =IF(A15<>"",""&DATA_KO!H6,"") | G15: =IF(A15<>"",""&DATA_KO!E6,"") | H15: =IF(A15<>"","➔ Trace Lineage","")
A16: =IF(DATA_KO!A7<>"",""&DATA_KO!A7,"") | B16: =IF(A16<>"","KO","") | C16: =IF(A16<>"",""&DATA_KO!B7,"") | D16: =IF(A16<>"",""&DATA_KO!C7,"") | E16: =IF(A16<>"",DATA_KO!G7,"") | F16: =IF(A16<>"",""&DATA_KO!H7,"") | G16: =IF(A16<>"",""&DATA_KO!E7,"") | H16: =IF(A16<>"","➔ Trace Lineage","")
A17: =IF(DATA_KO!A8<>"",""&DATA_KO!A8,"") | B17: =IF(A17<>"","KO","") | C17: =IF(A17<>"",""&DATA_KO!B8,"") | D17: =IF(A17<>"",""&DATA_KO!C8,"") | E17: =IF(A17<>"",DATA_KO!G8,"") | F17: =IF(A17<>"",""&DATA_KO!H8,"") | G17: =IF(A17<>"",""&DATA_KO!E8,"") | H17: =IF(A17<>"","➔ Trace Lineage","")
A18: =IF(DATA_KO!A9<>"",""&DATA_KO!A9,"") | B18: =IF(A18<>"","KO","") | C18: =IF(A18<>"",""&DATA_KO!B9,"") | D18: =IF(A18<>"",""&DATA_KO!C9,"") | E18: =IF(A18<>"",DATA_KO!G9,"") | F18: =IF(A18<>"",""&DATA_KO!H9,"") | G18: =IF(A18<>"",""&DATA_KO!E9,"") | H18: =IF(A18<>"","➔ Trace Lineage","")
A19: =IF(DATA_KO!A10<>"",""&DATA_KO!A10,"") | B19: =IF(A19<>"","KO","") | C19: =IF(A19<>"",""&DATA_KO!B10,"") | D19: =IF(A19<>"",""&DATA_KO!C10,"") | E19: =IF(A19<>"",DATA_KO!G10,"") | F19: =IF(A19<>"",""&DATA_KO!H10,"") | G19: =IF(A19<>"",""&DATA_KO!E10,"") | H19: =IF(A19<>"","➔ Trace Lineage","")
A20: =IF(DATA_KO!A11<>"",""&DATA_KO!A11,"") | B20: =IF(A20<>"","KO","") | C20: =IF(A20<>"",""&DATA_KO!B11,"") | D20: =IF(A20<>"",""&DATA_KO!C11,"") | E20: =IF(A20<>"",DATA_KO!G11,"") | F20: =IF(A20<>"",""&DATA_KO!H11,"") | G20: =IF(A20<>"",""&DATA_KO!E11,"") | H20: =IF(A20<>"","➔ Trace Lineage","")
A21: =IF(DATA_KO!A12<>"",""&DATA_KO!A12,"") | B21: =IF(A21<>"","KO","") | C21: =IF(A21<>"",""&DATA_KO!B12,"") | D21: =IF(A21<>"",""&DATA_KO!C12,"") | E21: =IF(A21<>"",DATA_KO!G12,"") | F21: =IF(A21<>"",""&DATA_KO!H12,"") | G21: =IF(A21<>"",""&DATA_KO!E12,"") | H21: =IF(A21<>"","➔ Trace Lineage","")
A22: =IF(DATA_KO!A13<>"",""&DATA_KO!A13,"") | B22: =IF(A22<>"","KO","") | C22: =IF(A22<>"",""&DATA_KO!B13,"") | D22: =IF(A22<>"",""&DATA_KO!C13,"") | E22: =IF(A22<>"",DATA_KO!G13,"") | F22: =IF(A22<>"",""&DATA_KO!H13,"") | G22: =IF(A22<>"",""&DATA_KO!E13,"") | H22: =IF(A22<>"","➔ Trace Lineage","")
... A210: =IF(DATA_KO!A201<>"",""&DATA_KO!A201,"") | B210: =IF(A210<>"","KO","") | C210: =IF(A210<>"",""&DATA_KO!B201,"") | D210: =IF(A210<>"",""&DATA_KO!C201,"") | E210: =IF(A210<>"",DATA_KO!G201,"") | F210: =IF(A210<>"",""&DATA_KO!H201,"") | G210: =IF(A210<>"",""&DATA_KO!E201,"") | H210: =IF(A210<>"","➔ Trace Lineage","")

Sheet 02A_KO_Registry
A1: RESEARCH INTELLIGENCE ENGINE (RIE) — KNOWLEDGE OBJECT (KO) REGISTRY | G1: =HYPERLINK("#'01_Executive_Dashboard'!A1", "⮌ BACK TO DASHBOARD") | H1: =HYPERLINK("#'02B_IO_Registry'!A1", "➔ IO REGISTRY") | I1: =HYPERLINK("#'02C_EO_Registry'!A1", "➔ EO REGISTRY") | J1: =HYPERLINK("#'04_Lineage_Explorer'!A1", "➔ LINEAGE EXPLORER")
A2: ="Authoritative Knowledge Objects (" & COUNTA(DATA_KO!A2:A1000) & " KOs) | Substrate Dynamic Projection"
A4: Object_ID | B4: Object_Type | C4: Concept Title | D4: Domain | E4: Confidence | F4: Review Status | G4: Origin Source | H4: Supporting EOs | I4: Supporting IOs | J4: Lineage Action
A5: =IF(DATA_KO!A2<>"",""&DATA_KO!A2,"") | B5: =IF(A5<>"","KO","") | C5: =IF(A5<>"",""&DATA_KO!B2,"") | D5: =IF(A5<>"",""&DATA_KO!C2,"") | E5: =IF(A5<>"",DATA_KO!G2,"") | F5: =IF(A5<>"",""&DATA_KO!H2,"") | G5: =IF(A5<>"",""&DATA_KO!D2,"") | H5: =IF(A5<>"",""&DATA_KO!E2,"") | I5: =IF(A5<>"",""&DATA_KO!F2,"") | J5: =IF(A5<>"","➔ Inspect Lineage","")
A6: =IF(DATA_KO!A3<>"",""&DATA_KO!A3,"") | B6: =IF(A6<>"","KO","") | C6: =IF(A6<>"",""&DATA_KO!B3,"") | D6: =IF(A6<>"",""&DATA_KO!C3,"") | E6: =IF(A6<>"",DATA_KO!G3,"") | F6: =IF(A6<>"",""&DATA_KO!H3,"") | G6: =IF(A6<>"",""&DATA_KO!D3,"") | H6: =IF(A6<>"",""&DATA_KO!E3,"") | I6: =IF(A6<>"",""&DATA_KO!F3,"") | J6: =IF(A6<>"","➔ Inspect Lineage","")
A7: =IF(DATA_KO!A4<>"",""&DATA_KO!A4,"") | B7: =IF(A7<>"","KO","") | C7: =IF(A7<>"",""&DATA_KO!B4,"") | D7: =IF(A7<>"",""&DATA_KO!C4,"") | E7: =IF(A7<>"",DATA_KO!G4,"") | F7: =IF(A7<>"",""&DATA_KO!H4,"") | G7: =IF(A7<>"",""&DATA_KO!D4,"") | H7: =IF(A7<>"",""&DATA_KO!E4,"") | I7: =IF(A7<>"",""&DATA_KO!F4,"") | J7: =IF(A7<>"","➔ Inspect Lineage","")
A8: =IF(DATA_KO!A5<>"",""&DATA_KO!A5,"") | B8: =IF(A8<>"","KO","") | C8: =IF(A8<>"",""&DATA_KO!B5,"") | D8: =IF(A8<>"",""&DATA_KO!C5,"") | E8: =IF(A8<>"",DATA_KO!G5,"") | F8: =IF(A8<>"",""&DATA_KO!H5,"") | G8: =IF(A8<>"",""&DATA_KO!D5,"") | H8: =IF(A8<>"",""&DATA_KO!E5,"") | I8: =IF(A8<>"",""&DATA_KO!F5,"") | J8: =IF(A8<>"","➔ Inspect Lineage","")
A9: =IF(DATA_KO!A6<>"",""&DATA_KO!A6,"") | B9: =IF(A9<>"","KO","") | C9: =IF(A9<>"",""&DATA_KO!B6,"") | D9: =IF(A9<>"",""&DATA_KO!C6,"") | E9: =IF(A9<>"",DATA_KO!G6,"") | F9: =IF(A9<>"",""&DATA_KO!H6,"") | G9: =IF(A9<>"",""&DATA_KO!D6,"") | H9: =IF(A9<>"",""&DATA_KO!E6,"") | I9: =IF(A9<>"",""&DATA_KO!F6,"") | J9: =IF(A9<>"","➔ Inspect Lineage","")
A10: =IF(DATA_KO!A7<>"",""&DATA_KO!A7,"") | B10: =IF(A10<>"","KO","") | C10: =IF(A10<>"",""&DATA_KO!B7,"") | D10: =IF(A10<>"",""&DATA_KO!C7,"") | E10: =IF(A10<>"",DATA_KO!G7,"") | F10: =IF(A10<>"",""&DATA_KO!H7,"") | G10: =IF(A10<>"",""&DATA_KO!D7,"") | H10: =IF(A10<>"",""&DATA_KO!E7,"") | I10: =IF(A10<>"",""&DATA_KO!F7,"") | J10: =IF(A10<>"","➔ Inspect Lineage","")
A11: =IF(DATA_KO!A8<>"",""&DATA_KO!A8,"") | B11: =IF(A11<>"","KO","") | C11: =IF(A11<>"",""&DATA_KO!B8,"") | D11: =IF(A11<>"",""&DATA_KO!C8,"") | E11: =IF(A11<>"",DATA_KO!G8,"") | F11: =IF(A11<>"",""&DATA_KO!H8,"") | G11: =IF(A11<>"",""&DATA_KO!D8,"") | H11: =IF(A11<>"",""&DATA_KO!E8,"") | I11: =IF(A11<>"",""&DATA_KO!F8,"") | J11: =IF(A11<>"","➔ Inspect Lineage","")
A12: =IF(DATA_KO!A9<>"",""&DATA_KO!A9,"") | B12: =IF(A12<>"","KO","") | C12: =IF(A12<>"",""&DATA_KO!B9,"") | D12: =IF(A12<>"",""&DATA_KO!C9,"") | E12: =IF(A12<>"",DATA_KO!G9,"") | F12: =IF(A12<>"",""&DATA_KO!H9,"") | G12: =IF(A12<>"",""&DATA_KO!D9,"") | H12: =IF(A12<>"",""&DATA_KO!E9,"") | I12: =IF(A12<>"",""&DATA_KO!F9,"") | J12: =IF(A12<>"","➔ Inspect Lineage","")
A13: =IF(DATA_KO!A10<>"",""&DATA_KO!A10,"") | B13: =IF(A13<>"","KO","") | C13: =IF(A13<>"",""&DATA_KO!B10,"") | D13: =IF(A13<>"",""&DATA_KO!C10,"") | E13: =IF(A13<>"",DATA_KO!G10,"") | F13: =IF(A13<>"",""&DATA_KO!H10,"") | G13: =IF(A13<>"",""&DATA_KO!D10,"") | H13: =IF(A13<>"",""&DATA_KO!E10,"") | I13: =IF(A13<>"",""&DATA_KO!F10,"") | J13: =IF(A13<>"","➔ Inspect Lineage","")
A14: =IF(DATA_KO!A11<>"",""&DATA_KO!A11,"") | B14: =IF(A14<>"","KO","") | C14: =IF(A14<>"",""&DATA_KO!B11,"") | D14: =IF(A14<>"",""&DATA_KO!C11,"") | E14: =IF(A14<>"",DATA_KO!G11,"") | F14: =IF(A14<>"",""&DATA_KO!H11,"") | G14: =IF(A14<>"",""&DATA_KO!D11,"") | H14: =IF(A14<>"",""&DATA_KO!E11,"") | I14: =IF(A14<>"",""&DATA_KO!F11,"") | J14: =IF(A14<>"","➔ Inspect Lineage","")
A15: =IF(DATA_KO!A12<>"",""&DATA_KO!A12,"") | B15: =IF(A15<>"","KO","") | C15: =IF(A15<>"",""&DATA_KO!B12,"") | D15: =IF(A15<>"",""&DATA_KO!C12,"") | E15: =IF(A15<>"",DATA_KO!G12,"") | F15: =IF(A15<>"",""&DATA_KO!H12,"") | G15: =IF(A15<>"",""&DATA_KO!D12,"") | H15: =IF(A15<>"",""&DATA_KO!E12,"") | I15: =IF(A15<>"",""&DATA_KO!F12,"") | J15: =IF(A15<>"","➔ Inspect Lineage","")
A16: =IF(DATA_KO!A13<>"",""&DATA_KO!A13,"") | B16: =IF(A16<>"","KO","") | C16: =IF(A16<>"",""&DATA_KO!B13,"") | D16: =IF(A16<>"",""&DATA_KO!C13,"") | E16: =IF(A16<>"",DATA_KO!G13,"") | F16: =IF(A16<>"",""&DATA_KO!H13,"") | G16: =IF(A16<>"",""&DATA_KO!D13,"") | H16: =IF(A16<>"",""&DATA_KO!E13,"") | I16: =IF(A16<>"",""&DATA_KO!F13,"") | J16: =IF(A16<>"","➔ Inspect Lineage","")
... A254: =IF(DATA_KO!A251<>"",""&DATA_KO!A251,"") | B254: =IF(A254<>"","KO","") | C254: =IF(A254<>"",""&DATA_KO!B251,"") | D254: =IF(A254<>"",""&DATA_KO!C251,"") | E254: =IF(A254<>"",DATA_KO!G251,"") | F254: =IF(A254<>"",""&DATA_KO!H251,"") | G254: =IF(A254<>"",""&DATA_KO!D251,"") | H254: =IF(A254<>"",""&DATA_KO!E251,"") | I254: =IF(A254<>"",""&DATA_KO!F251,"") | J254: =IF(A254<>"","➔ Inspect Lineage","")

Sheet 02B_IO_Registry
A1: RESEARCH INTELLIGENCE ENGINE (RIE) — INTERPRETATION OBJECT (IO) REGISTRY | F1: =HYPERLINK("#'01_Executive_Dashboard'!A1", "⮌ BACK TO DASHBOARD") | G1: =HYPERLINK("#'02A_KO_Registry'!A1", "➔ KO REGISTRY") | H1: =HYPERLINK("#'02C_EO_Registry'!A1", "➔ EO REGISTRY")
A2: ="Authoritative Interpretation Objects (" & COUNTA(DATA_IO!A2:A1000) & " IOs) | Substrate Dynamic Projection"
A4: Object_ID | B4: Object_Type | C4: Research Question | D4: Primary Interpretation | E4: Alternative Interpretation | F4: Confidence | G4: Supporting EO | H4: Workflow Status
A5: =IF(DATA_IO!A2<>"",""&DATA_IO!A2,"") | B5: =IF(A5<>"","IO","") | C5: =IF(A5<>"",""&DATA_IO!B2,"") | D5: =IF(A5<>"",""&DATA_IO!C2,"") | E5: =IF(A5<>"",""&DATA_IO!D2,"") | F5: =IF(A5<>"",DATA_IO!G2,"") | G5: =IF(A5<>"",""&DATA_IO!E2,"") | H5: =IF(A5<>"","DERIVED","")
A6: =IF(DATA_IO!A3<>"",""&DATA_IO!A3,"") | B6: =IF(A6<>"","IO","") | C6: =IF(A6<>"",""&DATA_IO!B3,"") | D6: =IF(A6<>"",""&DATA_IO!C3,"") | E6: =IF(A6<>"",""&DATA_IO!D3,"") | F6: =IF(A6<>"",DATA_IO!G3,"") | G6: =IF(A6<>"",""&DATA_IO!E3,"") | H6: =IF(A6<>"","DERIVED","")
A7: =IF(DATA_IO!A4<>"",""&DATA_IO!A4,"") | B7: =IF(A7<>"","IO","") | C7: =IF(A7<>"",""&DATA_IO!B4,"") | D7: =IF(A7<>"",""&DATA_IO!C4,"") | E7: =IF(A7<>"",""&DATA_IO!D4,"") | F7: =IF(A7<>"",DATA_IO!G4,"") | G7: =IF(A7<>"",""&DATA_IO!E4,"") | H7: =IF(A7<>"","DERIVED","")
A8: =IF(DATA_IO!A5<>"",""&DATA_IO!A5,"") | B8: =IF(A8<>"","IO","") | C8: =IF(A8<>"",""&DATA_IO!B5,"") | D8: =IF(A8<>"",""&DATA_IO!C5,"") | E8: =IF(A8<>"",""&DATA_IO!D5,"") | F8: =IF(A8<>"",DATA_IO!G5,"") | G8: =IF(A8<>"",""&DATA_IO!E5,"") | H8: =IF(A8<>"","DERIVED","")
A9: =IF(DATA_IO!A6<>"",""&DATA_IO!A6,"") | B9: =IF(A9<>"","IO","") | C9: =IF(A9<>"",""&DATA_IO!B6,"") | D9: =IF(A9<>"",""&DATA_IO!C6,"") | E9: =IF(A9<>"",""&DATA_IO!D6,"") | F9: =IF(A9<>"",DATA_IO!G6,"") | G9: =IF(A9<>"",""&DATA_IO!E6,"") | H9: =IF(A9<>"","DERIVED","")
A10: =IF(DATA_IO!A7<>"",""&DATA_IO!A7,"") | B10: =IF(A10<>"","IO","") | C10: =IF(A10<>"",""&DATA_IO!B7,"") | D10: =IF(A10<>"",""&DATA_IO!C7,"") | E10: =IF(A10<>"",""&DATA_IO!D7,"") | F10: =IF(A10<>"",DATA_IO!G7,"") | G10: =IF(A10<>"",""&DATA_IO!E7,"") | H10: =IF(A10<>"","DERIVED","")
A11: =IF(DATA_IO!A8<>"",""&DATA_IO!A8,"") | B11: =IF(A11<>"","IO","") | C11: =IF(A11<>"",""&DATA_IO!B8,"") | D11: =IF(A11<>"",""&DATA_IO!C8,"") | E11: =IF(A11<>"",""&DATA_IO!D8,"") | F11: =IF(A11<>"",DATA_IO!G8,"") | G11: =IF(A11<>"",""&DATA_IO!E8,"") | H11: =IF(A11<>"","DERIVED","")
A12: =IF(DATA_IO!A9<>"",""&DATA_IO!A9,"") | B12: =IF(A12<>"","IO","") | C12: =IF(A12<>"",""&DATA_IO!B9,"") | D12: =IF(A12<>"",""&DATA_IO!C9,"") | E12: =IF(A12<>"",""&DATA_IO!D9,"") | F12: =IF(A12<>"",DATA_IO!G9,"") | G12: =IF(A12<>"",""&DATA_IO!E9,"") | H12: =IF(A12<>"","DERIVED","")
A13: =IF(DATA_IO!A10<>"",""&DATA_IO!A10,"") | B13: =IF(A13<>"","IO","") | C13: =IF(A13<>"",""&DATA_IO!B10,"") | D13: =IF(A13<>"",""&DATA_IO!C10,"") | E13: =IF(A13<>"",""&DATA_IO!D10,"") | F13: =IF(A13<>"",DATA_IO!G10,"") | G13: =IF(A13<>"",""&DATA_IO!E10,"") | H13: =IF(A13<>"","DERIVED","")
A14: =IF(DATA_IO!A11<>"",""&DATA_IO!A11,"") | B14: =IF(A14<>"","IO","") | C14: =IF(A14<>"",""&DATA_IO!B11,"") | D14: =IF(A14<>"",""&DATA_IO!C11,"") | E14: =IF(A14<>"",""&DATA_IO!D11,"") | F14: =IF(A14<>"",DATA_IO!G11,"") | G14: =IF(A14<>"",""&DATA_IO!E11,"") | H14: =IF(A14<>"","DERIVED","")
A15: =IF(DATA_IO!A12<>"",""&DATA_IO!A12,"") | B15: =IF(A15<>"","IO","") | C15: =IF(A15<>"",""&DATA_IO!B12,"") | D15: =IF(A15<>"",""&DATA_IO!C12,"") | E15: =IF(A15<>"",""&DATA_IO!D12,"") | F15: =IF(A15<>"",DATA_IO!G12,"") | G15: =IF(A15<>"",""&DATA_IO!E12,"") | H15: =IF(A15<>"","DERIVED","")
A16: =IF(DATA_IO!A13<>"",""&DATA_IO!A13,"") | B16: =IF(A16<>"","IO","") | C16: =IF(A16<>"",""&DATA_IO!B13,"") | D16: =IF(A16<>"",""&DATA_IO!C13,"") | E16: =IF(A16<>"",""&DATA_IO!D13,"") | F16: =IF(A16<>"",DATA_IO!G13,"") | G16: =IF(A16<>"",""&DATA_IO!E13,"") | H16: =IF(A16<>"","DERIVED","")
... A254: =IF(DATA_IO!A251<>"",""&DATA_IO!A251,"") | B254: =IF(A254<>"","IO","") | C254: =IF(A254<>"",""&DATA_IO!B251,"") | D254: =IF(A254<>"",""&DATA_IO!C251,"") | E254: =IF(A254<>"",""&DATA_IO!D251,"") | F254: =IF(A254<>"",DATA_IO!G251,"") | G254: =IF(A254<>"",""&DATA_IO!E251,"") | H254: =IF(A254<>"","DERIVED","")

Sheet 02C_EO_Registry
A1: RESEARCH INTELLIGENCE ENGINE (RIE) — EVIDENCE OBJECT (EO) REGISTRY | F1: =HYPERLINK("#'01_Executive_Dashboard'!A1", "⮌ BACK TO DASHBOARD") | G1: =HYPERLINK("#'02A_KO_Registry'!A1", "➔ KO REGISTRY") | H1: =HYPERLINK("#'02B_IO_Registry'!A1", "➔ IO REGISTRY")
A2: ="Authoritative Evidence Objects (" & COUNTA(DATA_EO!A2:A1000) & " EOs) | Substrate Dynamic Projection"
A4: Object_ID | B4: Object_Type | C4: Direct Empirical Observation | D4: Source_ID | E4: RIE_Domain | F4: Evidence_Type | G4: Timestamp / Page | H4: Linked_IO
A5: =IF(DATA_EO!A2<>"",""&DATA_EO!A2,"") | B5: =IF(A5<>"","EO","") | C5: =IF(A5<>"",""&DATA_EO!L2,"") | D5: =IF(A5<>"",""&DATA_EO!B2,"") | E5: =IF(A5<>"",""&DATA_EO!G2,"") | F5: =IF(A5<>"",""&DATA_EO!K2,"") | G5: =IF(A5<>"",""&DATA_EO!J2,"") | H5: =IF(A5<>"",""&DATA_EO!M2,"")
A6: =IF(DATA_EO!A3<>"",""&DATA_EO!A3,"") | B6: =IF(A6<>"","EO","") | C6: =IF(A6<>"",""&DATA_EO!L3,"") | D6: =IF(A6<>"",""&DATA_EO!B3,"") | E6: =IF(A6<>"",""&DATA_EO!G3,"") | F6: =IF(A6<>"",""&DATA_EO!K3,"") | G6: =IF(A6<>"",""&DATA_EO!J3,"") | H6: =IF(A6<>"",""&DATA_EO!M3,"")
A7: =IF(DATA_EO!A4<>"",""&DATA_EO!A4,"") | B7: =IF(A7<>"","EO","") | C7: =IF(A7<>"",""&DATA_EO!L4,"") | D7: =IF(A7<>"",""&DATA_EO!B4,"") | E7: =IF(A7<>"",""&DATA_EO!G4,"") | F7: =IF(A7<>"",""&DATA_EO!K4,"") | G7: =IF(A7<>"",""&DATA_EO!J4,"") | H7: =IF(A7<>"",""&DATA_EO!M4,"")
A8: =IF(DATA_EO!A5<>"",""&DATA_EO!A5,"") | B8: =IF(A8<>"","EO","") | C8: =IF(A8<>"",""&DATA_EO!L5,"") | D8: =IF(A8<>"",""&DATA_EO!B5,"") | E8: =IF(A8<>"",""&DATA_EO!G5,"") | F8: =IF(A8<>"",""&DATA_EO!K5,"") | G8: =IF(A8<>"",""&DATA_EO!J5,"") | H8: =IF(A8<>"",""&DATA_EO!M5,"")
A9: =IF(DATA_EO!A6<>"",""&DATA_EO!A6,"") | B9: =IF(A9<>"","EO","") | C9: =IF(A9<>"",""&DATA_EO!L6,"") | D9: =IF(A9<>"",""&DATA_EO!B6,"") | E9: =IF(A9<>"",""&DATA_EO!G6,"") | F9: =IF(A9<>"",""&DATA_EO!K6,"") | G9: =IF(A9<>"",""&DATA_EO!J6,"") | H9: =IF(A9<>"",""&DATA_EO!M6,"")
A10: =IF(DATA_EO!A7<>"",""&DATA_EO!A7,"") | B10: =IF(A10<>"","EO","") | C10: =IF(A10<>"",""&DATA_EO!L7,"") | D10: =IF(A10<>"",""&DATA_EO!B7,"") | E10: =IF(A10<>"",""&DATA_EO!G7,"") | F10: =IF(A10<>"",""&DATA_EO!K7,"") | G10: =IF(A10<>"",""&DATA_EO!J7,"") | H10: =IF(A10<>"",""&DATA_EO!M7,"")
A11: =IF(DATA_EO!A8<>"",""&DATA_EO!A8,"") | B11: =IF(A11<>"","EO","") | C11: =IF(A11<>"",""&DATA_EO!L8,"") | D11: =IF(A11<>"",""&DATA_EO!B8,"") | E11: =IF(A11<>"",""&DATA_EO!G8,"") | F11: =IF(A11<>"",""&DATA_EO!K8,"") | G11: =IF(A11<>"",""&DATA_EO!J8,"") | H11: =IF(A11<>"",""&DATA_EO!M8,"")
A12: =IF(DATA_EO!A9<>"",""&DATA_EO!A9,"") | B12: =IF(A12<>"","EO","") | C12: =IF(A12<>"",""&DATA_EO!L9,"") | D12: =IF(A12<>"",""&DATA_EO!B9,"") | E12: =IF(A12<>"",""&DATA_EO!G9,"") | F12: =IF(A12<>"",""&DATA_EO!K9,"") | G12: =IF(A12<>"",""&DATA_EO!J9,"") | H12: =IF(A12<>"",""&DATA_EO!M9,"")
A13: =IF(DATA_EO!A10<>"",""&DATA_EO!A10,"") | B13: =IF(A13<>"","EO","") | C13: =IF(A13<>"",""&DATA_EO!L10,"") | D13: =IF(A13<>"",""&DATA_EO!B10,"") | E13: =IF(A13<>"",""&DATA_EO!G10,"") | F13: =IF(A13<>"",""&DATA_EO!K10,"") | G13: =IF(A13<>"",""&DATA_EO!J10,"") | H13: =IF(A13<>"",""&DATA_EO!M10,"")
A14: =IF(DATA_EO!A11<>"",""&DATA_EO!A11,"") | B14: =IF(A14<>"","EO","") | C14: =IF(A14<>"",""&DATA_EO!L11,"") | D14: =IF(A14<>"",""&DATA_EO!B11,"") | E14: =IF(A14<>"",""&DATA_EO!G11,"") | F14: =IF(A14<>"",""&DATA_EO!K11,"") | G14: =IF(A14<>"",""&DATA_EO!J11,"") | H14: =IF(A14<>"",""&DATA_EO!M11,"")
A15: =IF(DATA_EO!A12<>"",""&DATA_EO!A12,"") | B15: =IF(A15<>"","EO","") | C15: =IF(A15<>"",""&DATA_EO!L12,"") | D15: =IF(A15<>"",""&DATA_EO!B12,"") | E15: =IF(A15<>"",""&DATA_EO!G12,"") | F15: =IF(A15<>"",""&DATA_EO!K12,"") | G15: =IF(A15<>"",""&DATA_EO!J12,"") | H15: =IF(A15<>"",""&DATA_EO!M12,"")
A16: =IF(DATA_EO!A13<>"",""&DATA_EO!A13,"") | B16: =IF(A16<>"","EO","") | C16: =IF(A16<>"",""&DATA_EO!L13,"") | D16: =IF(A16<>"",""&DATA_EO!B13,"") | E16: =IF(A16<>"",""&DATA_EO!G13,"") | F16: =IF(A16<>"",""&DATA_EO!K13,"") | G16: =IF(A16<>"",""&DATA_EO!J13,"") | H16: =IF(A16<>"",""&DATA_EO!M13,"")
... A304: =IF(DATA_EO!A301<>"",""&DATA_EO!A301,"") | B304: =IF(A304<>"","EO","") | C304: =IF(A304<>"",""&DATA_EO!L301,"") | D304: =IF(A304<>"",""&DATA_EO!B301,"") | E304: =IF(A304<>"",""&DATA_EO!G301,"") | F304: =IF(A304<>"",""&DATA_EO!K301,"") | G304: =IF(A304<>"",""&DATA_EO!J301,"") | H304: =IF(A304<>"",""&DATA_EO!M301,"")

Sheet 03_Relationship_Registry
A1: RESEARCH INTELLIGENCE ENGINE (RIE) — RELATIONSHIP REGISTRY | J1: =HYPERLINK("#'01_Executive_Dashboard'!A1", "⮌ BACK TO DASHBOARD")
A2: ="Multi-Layer Semantic Relational Matrix (" & COUNTA(DATA_RELATIONSHIPS!A2:A1000) & " Relationships) | Dynamic Projection"
A4: Relationship_ID | B4: Source_ID | C4: Source_Type | D4: Target_ID | E4: Target_Type | F4: Relationship_Vector | G4: Rel_Strength | H4: CMS_v1_Score | I4: Surfacing_Status | J4: Cluster_ID | K4: Provenance_Source | L4: Lineage_Inspection
A5: =IF(DATA_RELATIONSHIPS!B2<>"",""&DATA_RELATIONSHIPS!B2,"") | B5: =IF(A5<>"",""&DATA_RELATIONSHIPS!C2,"") | C5: =IF(A5<>"","KO","") | D5: =IF(A5<>"",""&DATA_RELATIONSHIPS!D2,"") | E5: =IF(A5<>"","KO","") | F5: =IF(A5<>"",""&DATA_RELATIONSHIPS!F2,"") | G5: =IF(A5<>"",DATA_RELATIONSHIPS!G2,"") | H5: =IF(A5<>"",DATA_RELATIONSHIPS!G2,"") | I5: =IF(A5<>"",""&DATA_RELATIONSHIPS!H2,"") | J5: =IF(A5<>"",""&DATA_RELATIONSHIPS!I2,"") | K5: DATA_RELATIONSHIPS (Interest Rate Expectation) | L5: =HYPERLINK("#'04_Lineage_Explorer'!A1", "➔ Trace Lineage")
A6: =IF(DATA_RELATIONSHIPS!B3<>"",""&DATA_RELATIONSHIPS!B3,"") | B6: =IF(A6<>"",""&DATA_RELATIONSHIPS!C3,"") | C6: =IF(A6<>"","KO","") | D6: =IF(A6<>"",""&DATA_RELATIONSHIPS!D3,"") | E6: =IF(A6<>"","KO","") | F6: =IF(A6<>"",""&DATA_RELATIONSHIPS!F3,"") | G6: =IF(A6<>"",DATA_RELATIONSHIPS!G3,"") | H6: =IF(A6<>"",DATA_RELATIONSHIPS!G3,"") | I6: =IF(A6<>"",""&DATA_RELATIONSHIPS!H3,"") | J6: =IF(A6<>"",""&DATA_RELATIONSHIPS!I3,"") | K6: DATA_RELATIONSHIPS (Yield Curve Transmission) | L6: =HYPERLINK("#'04_Lineage_Explorer'!A1", "➔ Trace Lineage")
A7: =IF(DATA_RELATIONSHIPS!B4<>"",""&DATA_RELATIONSHIPS!B4,"") | B7: =IF(A7<>"",""&DATA_RELATIONSHIPS!C4,"") | C7: =IF(A7<>"","KO","") | D7: =IF(A7<>"",""&DATA_RELATIONSHIPS!D4,"") | E7: =IF(A7<>"","KO","") | F7: =IF(A7<>"",""&DATA_RELATIONSHIPS!F4,"") | G7: =IF(A7<>"",DATA_RELATIONSHIPS!G4,"") | H7: =IF(A7<>"",DATA_RELATIONSHIPS!G4,"") | I7: =IF(A7<>"",""&DATA_RELATIONSHIPS!H4,"") | J7: =IF(A7<>"",""&DATA_RELATIONSHIPS!I4,"") | K7: DATA_RELATIONSHIPS (Institutional Capital Rotation) | L7: =HYPERLINK("#'04_Lineage_Explorer'!A1", "➔ Trace Lineage")
A8: =IF(DATA_RELATIONSHIPS!B5<>"",""&DATA_RELATIONSHIPS!B5,"") | B8: =IF(A8<>"",""&DATA_RELATIONSHIPS!C5,"") | C8: =IF(A8<>"","KO","") | D8: =IF(A8<>"",""&DATA_RELATIONSHIPS!D5,"") | E8: =IF(A8<>"","KO","") | F8: =IF(A8<>"",""&DATA_RELATIONSHIPS!F5,"") | G8: =IF(A8<>"",DATA_RELATIONSHIPS!G5,"") | H8: =IF(A8<>"",DATA_RELATIONSHIPS!G5,"") | I8: =IF(A8<>"",""&DATA_RELATIONSHIPS!H5,"") | J8: =IF(A8<>"",""&DATA_RELATIONSHIPS!I5,"") | K8: DATA_RELATIONSHIPS (Secular Valuation Benchmark) | L8: =HYPERLINK("#'04_Lineage_Explorer'!A1", "➔ Trace Lineage")
A9: =IF(DATA_RELATIONSHIPS!B6<>"",""&DATA_RELATIONSHIPS!B6,"") | B9: =IF(A9<>"",""&DATA_RELATIONSHIPS!C6,"") | C9: =IF(A9<>"","KO","") | D9: =IF(A9<>"",""&DATA_RELATIONSHIPS!D6,"") | E9: =IF(A9<>"","KO","") | F9: =IF(A9<>"",""&DATA_RELATIONSHIPS!F6,"") | G9: =IF(A9<>"",DATA_RELATIONSHIPS!G6,"") | H9: =IF(A9<>"",DATA_RELATIONSHIPS!G6,"") | I9: =IF(A9<>"",""&DATA_RELATIONSHIPS!H6,"") | J9: =IF(A9<>"",""&DATA_RELATIONSHIPS!I6,"") | K9: DATA_RELATIONSHIPS (Central Bank Signaling Arbitrage) | L9: =HYPERLINK("#'04_Lineage_Explorer'!A1", "➔ Trace Lineage")
A10: =IF(DATA_RELATIONSHIPS!B7<>"",""&DATA_RELATIONSHIPS!B7,"") | B10: =IF(A10<>"",""&DATA_RELATIONSHIPS!C7,"") | C10: =IF(A10<>"","KO","") | D10: =IF(A10<>"",""&DATA_RELATIONSHIPS!D7,"") | E10: =IF(A10<>"","KO","") | F10: =IF(A10<>"",""&DATA_RELATIONSHIPS!F7,"") | G10: =IF(A10<>"",DATA_RELATIONSHIPS!G7,"") | H10: =IF(A10<>"",DATA_RELATIONSHIPS!G7,"") | I10: =IF(A10<>"",""&DATA_RELATIONSHIPS!H7,"") | J10: =IF(A10<>"",""&DATA_RELATIONSHIPS!I7,"") | K10: DATA_RELATIONSHIPS (Debt Refinancing Term Premium) | L10: =HYPERLINK("#'04_Lineage_Explorer'!A1", "➔ Trace Lineage")
A11: =IF(DATA_RELATIONSHIPS!B8<>"",""&DATA_RELATIONSHIPS!B8,"") | B11: =IF(A11<>"",""&DATA_RELATIONSHIPS!C8,"") | C11: =IF(A11<>"","KO","") | D11: =IF(A11<>"",""&DATA_RELATIONSHIPS!D8,"") | E11: =IF(A11<>"","KO","") | F11: =IF(A11<>"",""&DATA_RELATIONSHIPS!F8,"") | G11: =IF(A11<>"",DATA_RELATIONSHIPS!G8,"") | H11: =IF(A11<>"",DATA_RELATIONSHIPS!G8,"") | I11: =IF(A11<>"",""&DATA_RELATIONSHIPS!H8,"") | J11: =IF(A11<>"",""&DATA_RELATIONSHIPS!I8,"") | K11: DATA_RELATIONSHIPS (Treasury Market Liquidity Vulnerability) | L11: =HYPERLINK("#'04_Lineage_Explorer'!A1", "➔ Trace Lineage")
A12: =IF(DATA_RELATIONSHIPS!B9<>"",""&DATA_RELATIONSHIPS!B9,"") | B12: =IF(A12<>"",""&DATA_RELATIONSHIPS!C9,"") | C12: =IF(A12<>"","KO","") | D12: =IF(A12<>"",""&DATA_RELATIONSHIPS!D9,"") | E12: =IF(A12<>"","KO","") | F12: =IF(A12<>"",""&DATA_RELATIONSHIPS!F9,"") | G12: =IF(A12<>"",DATA_RELATIONSHIPS!G9,"") | H12: =IF(A12<>"",DATA_RELATIONSHIPS!G9,"") | I12: =IF(A12<>"",""&DATA_RELATIONSHIPS!H9,"") | J12: =IF(A12<>"",""&DATA_RELATIONSHIPS!I9,"") | K12: DATA_RELATIONSHIPS (Fiscal Dominance Cost-Push Feedback) | L12: =HYPERLINK("#'04_Lineage_Explorer'!A1", "➔ Trace Lineage")
A13: =IF(DATA_RELATIONSHIPS!B10<>"",""&DATA_RELATIONSHIPS!B10,"") | B13: =IF(A13<>"",""&DATA_RELATIONSHIPS!C10,"") | C13: =IF(A13<>"","KO","") | D13: =IF(A13<>"",""&DATA_RELATIONSHIPS!D10,"") | E13: =IF(A13<>"","KO","") | F13: =IF(A13<>"",""&DATA_RELATIONSHIPS!F10,"") | G13: =IF(A13<>"",DATA_RELATIONSHIPS!G10,"") | H13: =IF(A13<>"",DATA_RELATIONSHIPS!G10,"") | I13: =IF(A13<>"",""&DATA_RELATIONSHIPS!H10,"") | J13: =IF(A13<>"",""&DATA_RELATIONSHIPS!I10,"") | K13: DATA_RELATIONSHIPS (Token Revenue-to-Debt Mismatch) | L13: =HYPERLINK("#'04_Lineage_Explorer'!A1", "➔ Trace Lineage")
A14: =IF(DATA_RELATIONSHIPS!B11<>"",""&DATA_RELATIONSHIPS!B11,"") | B14: =IF(A14<>"",""&DATA_RELATIONSHIPS!C11,"") | C14: =IF(A14<>"","KO","") | D14: =IF(A14<>"",""&DATA_RELATIONSHIPS!D11,"") | E14: =IF(A14<>"","KO","") | F14: =IF(A14<>"",""&DATA_RELATIONSHIPS!F11,"") | G14: =IF(A14<>"",DATA_RELATIONSHIPS!G11,"") | H14: =IF(A14<>"",DATA_RELATIONSHIPS!G11,"") | I14: =IF(A14<>"",""&DATA_RELATIONSHIPS!H11,"") | J14: =IF(A14<>"",""&DATA_RELATIONSHIPS!I11,"") | K14: DATA_RELATIONSHIPS (Off-Balance Sheet Refinancing Cliff) | L14: =HYPERLINK("#'04_Lineage_Explorer'!A1", "➔ Trace Lineage")
A15: =IF(DATA_RELATIONSHIPS!B12<>"",""&DATA_RELATIONSHIPS!B12,"") | B15: =IF(A15<>"",""&DATA_RELATIONSHIPS!C12,"") | C15: =IF(A15<>"","KO","") | D15: =IF(A15<>"",""&DATA_RELATIONSHIPS!D12,"") | E15: =IF(A15<>"","KO","") | F15: =IF(A15<>"",""&DATA_RELATIONSHIPS!F12,"") | G15: =IF(A15<>"",DATA_RELATIONSHIPS!G12,"") | H15: =IF(A15<>"",DATA_RELATIONSHIPS!G12,"") | I15: =IF(A15<>"",""&DATA_RELATIONSHIPS!H12,"") | J15: =IF(A15<>"",""&DATA_RELATIONSHIPS!I12,"") | K15: DATA_RELATIONSHIPS (Leveraged Liquidity Contagion) | L15: =HYPERLINK("#'04_Lineage_Explorer'!A1", "➔ Trace Lineage")
A16: =IF(DATA_RELATIONSHIPS!B13<>"",""&DATA_RELATIONSHIPS!B13,"") | B16: =IF(A16<>"",""&DATA_RELATIONSHIPS!C13,"") | C16: =IF(A16<>"","KO","") | D16: =IF(A16<>"",""&DATA_RELATIONSHIPS!D13,"") | E16: =IF(A16<>"","KO","") | F16: =IF(A16<>"",""&DATA_RELATIONSHIPS!F13,"") | G16: =IF(A16<>"",DATA_RELATIONSHIPS!G13,"") | H16: =IF(A16<>"",DATA_RELATIONSHIPS!G13,"") | I16: =IF(A16<>"",""&DATA_RELATIONSHIPS!H13,"") | J16: =IF(A16<>"",""&DATA_RELATIONSHIPS!I13,"") | K16: DATA_RELATIONSHIPS (Inverted Heuristic Trigger) | L16: =HYPERLINK("#'04_Lineage_Explorer'!A1", "➔ Trace Lineage")
... A21: =IF(DATA_RELATIONSHIPS!B18<>"",""&DATA_RELATIONSHIPS!B18,"") | B21: =IF(A21<>"",""&DATA_RELATIONSHIPS!C18,"") | C21: =IF(A21<>"","KO","") | D21: =IF(A21<>"",""&DATA_RELATIONSHIPS!D18,"") | E21: =IF(A21<>"","KO","") | F21: =IF(A21<>"",""&DATA_RELATIONSHIPS!F18,"") | G21: =IF(A21<>"",DATA_RELATIONSHIPS!G18,"") | H21: =IF(A21<>"",DATA_RELATIONSHIPS!G18,"") | I21: =IF(A21<>"",""&DATA_RELATIONSHIPS!H18,"") | J21: =IF(A21<>"",""&DATA_RELATIONSHIPS!I18,"") | K21: DATA_RELATIONSHIPS (Operating Margin Bull Confirmation) | L21: =HYPERLINK("#'04_Lineage_Explorer'!A1", "➔ Trace Lineage")
A22: =IF(DATA_RELATIONSHIPS!B19<>"",""&DATA_RELATIONSHIPS!B19,"") | B22: =IF(A22<>"",""&DATA_RELATIONSHIPS!C19,"") | C22: =IF(A22<>"","KO","") | D22: =IF(A22<>"",""&DATA_RELATIONSHIPS!D19,"") | E22: =IF(A22<>"","KO","") | F22: =IF(A22<>"",""&DATA_RELATIONSHIPS!F19,"") | G22: =IF(A22<>"",DATA_RELATIONSHIPS!G19,"") | H22: =IF(A22<>"",DATA_RELATIONSHIPS!G19,"") | I22: =IF(A22<>"",""&DATA_RELATIONSHIPS!H19,"") | J22: =IF(A22<>"",""&DATA_RELATIONSHIPS!I19,"") | K22: DATA_RELATIONSHIPS (Fiscal Vulnerability Weaponization)
A23: =IF(DATA_RELATIONSHIPS!B20<>"",""&DATA_RELATIONSHIPS!B20,"") | B23: =IF(A23<>"",""&DATA_RELATIONSHIPS!C20,"") | C23: =IF(A23<>"","KO","") | D23: =IF(A23<>"",""&DATA_RELATIONSHIPS!D20,"") | E23: =IF(A23<>"","KO","") | F23: =IF(A23<>"",""&DATA_RELATIONSHIPS!F20,"") | G23: =IF(A23<>"",DATA_RELATIONSHIPS!G20,"") | H23: =IF(A23<>"",DATA_RELATIONSHIPS!G20,"") | I23: =IF(A23<>"",""&DATA_RELATIONSHIPS!H20,"") | J23: =IF(A23<>"",""&DATA_RELATIONSHIPS!I20,"") | K23: DATA_RELATIONSHIPS (Cost-Push Policy Asymmetry Transmission)
A24: =IF(DATA_RELATIONSHIPS!B21<>"",""&DATA_RELATIONSHIPS!B21,"") | B24: =IF(A24<>"",""&DATA_RELATIONSHIPS!C21,"") | C24: =IF(A24<>"","KO","") | D24: =IF(A24<>"",""&DATA_RELATIONSHIPS!D21,"") | E24: =IF(A24<>"","KO","") | F24: =IF(A24<>"",""&DATA_RELATIONSHIPS!F21,"") | G24: =IF(A24<>"",DATA_RELATIONSHIPS!G21,"") | H24: =IF(A24<>"",DATA_RELATIONSHIPS!G21,"") | I24: =IF(A24<>"",""&DATA_RELATIONSHIPS!H21,"") | J24: =IF(A24<>"",""&DATA_RELATIONSHIPS!I21,"") | K24: DATA_RELATIONSHIPS (Reserve Divestment Countermeasure)
A25: =IF(DATA_RELATIONSHIPS!B22<>"",""&DATA_RELATIONSHIPS!B22,"") | B25: =IF(A25<>"",""&DATA_RELATIONSHIPS!C22,"") | C25: =IF(A25<>"","KO","") | D25: =IF(A25<>"",""&DATA_RELATIONSHIPS!D22,"") | E25: =IF(A25<>"","KO","") | F25: =IF(A25<>"",""&DATA_RELATIONSHIPS!F22,"") | G25: =IF(A25<>"",DATA_RELATIONSHIPS!G22,"") | H25: =IF(A25<>"",DATA_RELATIONSHIPS!G22,"") | I25: =IF(A25<>"",""&DATA_RELATIONSHIPS!H22,"") | J25: =IF(A25<>"",""&DATA_RELATIONSHIPS!I22,"") | K25: DATA_RELATIONSHIPS (Petrodollar Re-Anchoring Flow)
A26: =IF(DATA_RELATIONSHIPS!B23<>"",""&DATA_RELATIONSHIPS!B23,"") | B26: =IF(A26<>"",""&DATA_RELATIONSHIPS!C23,"") | C26: =IF(A26<>"","KO","") | D26: =IF(A26<>"",""&DATA_RELATIONSHIPS!D23,"") | E26: =IF(A26<>"","KO","") | F26: =IF(A26<>"",""&DATA_RELATIONSHIPS!F23,"") | G26: =IF(A26<>"",DATA_RELATIONSHIPS!G23,"") | H26: =IF(A26<>"",DATA_RELATIONSHIPS!G23,"") | I26: =IF(A26<>"",""&DATA_RELATIONSHIPS!H23,"") | J26: =IF(A26<>"",""&DATA_RELATIONSHIPS!I23,"") | K26: DATA_RELATIONSHIPS (Theological Perception Divergence)
A27: =IF(DATA_RELATIONSHIPS!B24<>"",""&DATA_RELATIONSHIPS!B24,"") | B27: =IF(A27<>"",""&DATA_RELATIONSHIPS!C24,"") | C27: =IF(A27<>"","KO","") | D27: =IF(A27<>"",""&DATA_RELATIONSHIPS!D24,"") | E27: =IF(A27<>"","KO","") | F27: =IF(A27<>"",""&DATA_RELATIONSHIPS!F24,"") | G27: =IF(A27<>"",DATA_RELATIONSHIPS!G24,"") | H27: =IF(A27<>"",DATA_RELATIONSHIPS!G24,"") | I27: =IF(A27<>"",""&DATA_RELATIONSHIPS!H24,"") | J27: =IF(A27<>"",""&DATA_RELATIONSHIPS!I24,"") | K27: DATA_RELATIONSHIPS (Macro Tail-Risk Tactical Hedging)
A28: =IF(DATA_RELATIONSHIPS!B25<>"",""&DATA_RELATIONSHIPS!B25,"") | B28: =IF(A28<>"",""&DATA_RELATIONSHIPS!C25,"") | C28: =IF(A28<>"","KO","") | D28: =IF(A28<>"",""&DATA_RELATIONSHIPS!D25,"") | E28: =IF(A28<>"","KO","") | F28: =IF(A28<>"",""&DATA_RELATIONSHIPS!F25,"") | G28: =IF(A28<>"",DATA_RELATIONSHIPS!G25,"") | H28: =IF(A28<>"",DATA_RELATIONSHIPS!G25,"") | I28: =IF(A28<>"",""&DATA_RELATIONSHIPS!H25,"") | J28: =IF(A28<>"",""&DATA_RELATIONSHIPS!I25,"")
A29: =IF(DATA_RELATIONSHIPS!B26<>"",""&DATA_RELATIONSHIPS!B26,"") | B29: =IF(A29<>"",""&DATA_RELATIONSHIPS!C26,"") | C29: =IF(A29<>"","KO","") | D29: =IF(A29<>"",""&DATA_RELATIONSHIPS!D26,"") | E29: =IF(A29<>"","KO","") | F29: =IF(A29<>"",""&DATA_RELATIONSHIPS!F26,"") | G29: =IF(A29<>"",DATA_RELATIONSHIPS!G26,"") | H29: =IF(A29<>"",DATA_RELATIONSHIPS!G26,"") | I29: =IF(A29<>"",""&DATA_RELATIONSHIPS!H26,"") | J29: =IF(A29<>"",""&DATA_RELATIONSHIPS!I26,"")
A30: =IF(DATA_RELATIONSHIPS!B27<>"",""&DATA_RELATIONSHIPS!B27,"") | B30: =IF(A30<>"",""&DATA_RELATIONSHIPS!C27,"") | C30: =IF(A30<>"","KO","") | D30: =IF(A30<>"",""&DATA_RELATIONSHIPS!D27,"") | E30: =IF(A30<>"","KO","") | F30: =IF(A30<>"",""&DATA_RELATIONSHIPS!F27,"") | G30: =IF(A30<>"",DATA_RELATIONSHIPS!G27,"") | H30: =IF(A30<>"",DATA_RELATIONSHIPS!G27,"") | I30: =IF(A30<>"",""&DATA_RELATIONSHIPS!H27,"") | J30: =IF(A30<>"",""&DATA_RELATIONSHIPS!I27,"")
A31: =IF(DATA_RELATIONSHIPS!B28<>"",""&DATA_RELATIONSHIPS!B28,"") | B31: =IF(A31<>"",""&DATA_RELATIONSHIPS!C28,"") | C31: =IF(A31<>"","KO","") | D31: =IF(A31<>"",""&DATA_RELATIONSHIPS!D28,"") | E31: =IF(A31<>"","KO","") | F31: =IF(A31<>"",""&DATA_RELATIONSHIPS!F28,"") | G31: =IF(A31<>"",DATA_RELATIONSHIPS!G28,"") | H31: =IF(A31<>"",DATA_RELATIONSHIPS!G28,"") | I31: =IF(A31<>"",""&DATA_RELATIONSHIPS!H28,"") | J31: =IF(A31<>"",""&DATA_RELATIONSHIPS!I28,"")
A32: =IF(DATA_RELATIONSHIPS!B29<>"",""&DATA_RELATIONSHIPS!B29,"") | B32: =IF(A32<>"",""&DATA_RELATIONSHIPS!C29,"") | C32: =IF(A32<>"","KO","") | D32: =IF(A32<>"",""&DATA_RELATIONSHIPS!D29,"") | E32: =IF(A32<>"","KO","") | F32: =IF(A32<>"",""&DATA_RELATIONSHIPS!F29,"") | G32: =IF(A32<>"",DATA_RELATIONSHIPS!G29,"") | H32: =IF(A32<>"",DATA_RELATIONSHIPS!G29,"") | I32: =IF(A32<>"",""&DATA_RELATIONSHIPS!H29,"") | J32: =IF(A32<>"",""&DATA_RELATIONSHIPS!I29,"")
A33: =IF(DATA_RELATIONSHIPS!B30<>"",""&DATA_RELATIONSHIPS!B30,"") | B33: =IF(A33<>"",""&DATA_RELATIONSHIPS!C30,"") | C33: =IF(A33<>"","KO","") | D33: =IF(A33<>"",""&DATA_RELATIONSHIPS!D30,"") | E33: =IF(A33<>"","KO","") | F33: =IF(A33<>"",""&DATA_RELATIONSHIPS!F30,"") | G33: =IF(A33<>"",DATA_RELATIONSHIPS!G30,"") | H33: =IF(A33<>"",DATA_RELATIONSHIPS!G30,"") | I33: =IF(A33<>"",""&DATA_RELATIONSHIPS!H30,"") | J33: =IF(A33<>"",""&DATA_RELATIONSHIPS!I30,"")
A34: =IF(DATA_RELATIONSHIPS!B31<>"",""&DATA_RELATIONSHIPS!B31,"") | B34: =IF(A34<>"",""&DATA_RELATIONSHIPS!C31,"") | C34: =IF(A34<>"","KO","") | D34: =IF(A34<>"",""&DATA_RELATIONSHIPS!D31,"") | E34: =IF(A34<>"","KO","") | F34: =IF(A34<>"",""&DATA_RELATIONSHIPS!F31,"") | G34: =IF(A34<>"",DATA_RELATIONSHIPS!G31,"") | H34: =IF(A34<>"",DATA_RELATIONSHIPS!G31,"") | I34: =IF(A34<>"",""&DATA_RELATIONSHIPS!H31,"") | J34: =IF(A34<>"",""&DATA_RELATIONSHIPS!I31,"")
A35: =IF(DATA_RELATIONSHIPS!B32<>"",""&DATA_RELATIONSHIPS!B32,"") | B35: =IF(A35<>"",""&DATA_RELATIONSHIPS!C32,"") | C35: =IF(A35<>"","KO","") | D35: =IF(A35<>"",""&DATA_RELATIONSHIPS!D32,"") | E35: =IF(A35<>"","KO","") | F35: =IF(A35<>"",""&DATA_RELATIONSHIPS!F32,"") | G35: =IF(A35<>"",DATA_RELATIONSHIPS!G32,"") | H35: =IF(A35<>"",DATA_RELATIONSHIPS!G32,"") | I35: =IF(A35<>"",""&DATA_RELATIONSHIPS!H32,"") | J35: =IF(A35<>"",""&DATA_RELATIONSHIPS!I32,"")
A36: =IF(DATA_RELATIONSHIPS!B33<>"",""&DATA_RELATIONSHIPS!B33,"") | B36: =IF(A36<>"",""&DATA_RELATIONSHIPS!C33,"") | C36: =IF(A36<>"","KO","") | D36: =IF(A36<>"",""&DATA_RELATIONSHIPS!D33,"") | E36: =IF(A36<>"","KO","") | F36: =IF(A36<>"",""&DATA_RELATIONSHIPS!F33,"") | G36: =IF(A36<>"",DATA_RELATIONSHIPS!G33,"") | H36: =IF(A36<>"",DATA_RELATIONSHIPS!G33,"") | I36: =IF(A36<>"",""&DATA_RELATIONSHIPS!H33,"") | J36: =IF(A36<>"",""&DATA_RELATIONSHIPS!I33,"")
A37: =IF(DATA_RELATIONSHIPS!B34<>"",""&DATA_RELATIONSHIPS!B34,"") | B37: =IF(A37<>"",""&DATA_RELATIONSHIPS!C34,"") | C37: =IF(A37<>"","KO","") | D37: =IF(A37<>"",""&DATA_RELATIONSHIPS!D34,"") | E37: =IF(A37<>"","KO","") | F37: =IF(A37<>"",""&DATA_RELATIONSHIPS!F34,"") | G37: =IF(A37<>"",DATA_RELATIONSHIPS!G34,"") | H37: =IF(A37<>"",DATA_RELATIONSHIPS!G34,"") | I37: =IF(A37<>"",""&DATA_RELATIONSHIPS!H34,"") | J37: =IF(A37<>"",""&DATA_RELATIONSHIPS!I34,"")
A38: =IF(DATA_RELATIONSHIPS!B35<>"",""&DATA_RELATIONSHIPS!B35,"") | B38: =IF(A38<>"",""&DATA_RELATIONSHIPS!C35,"") | C38: =IF(A38<>"","KO","") | D38: =IF(A38<>"",""&DATA_RELATIONSHIPS!D35,"") | E38: =IF(A38<>"","KO","") | F38: =IF(A38<>"",""&DATA_RELATIONSHIPS!F35,"") | G38: =IF(A38<>"",DATA_RELATIONSHIPS!G35,"") | H38: =IF(A38<>"",DATA_RELATIONSHIPS!G35,"") | I38: =IF(A38<>"",""&DATA_RELATIONSHIPS!H35,"") | J38: =IF(A38<>"",""&DATA_RELATIONSHIPS!I35,"")
A39: =IF(DATA_RELATIONSHIPS!B36<>"",""&DATA_RELATIONSHIPS!B36,"") | B39: =IF(A39<>"",""&DATA_RELATIONSHIPS!C36,"") | C39: =IF(A39<>"","KO","") | D39: =IF(A39<>"",""&DATA_RELATIONSHIPS!D36,"") | E39: =IF(A39<>"","KO","") | F39: =IF(A39<>"",""&DATA_RELATIONSHIPS!F36,"") | G39: =IF(A39<>"",DATA_RELATIONSHIPS!G36,"") | H39: =IF(A39<>"",DATA_RELATIONSHIPS!G36,"") | I39: =IF(A39<>"",""&DATA_RELATIONSHIPS!H36,"") | J39: =IF(A39<>"",""&DATA_RELATIONSHIPS!I36,"")
... A154: =IF(DATA_RELATIONSHIPS!B151<>"",""&DATA_RELATIONSHIPS!B151,"") | B154: =IF(A154<>"",""&DATA_RELATIONSHIPS!C151,"") | C154: =IF(A154<>"","KO","") | D154: =IF(A154<>"",""&DATA_RELATIONSHIPS!D151,"") | E154: =IF(A154<>"","KO","") | F154: =IF(A154<>"",""&DATA_RELATIONSHIPS!F151,"") | G154: =IF(A154<>"",DATA_RELATIONSHIPS!G151,"") | H154: =IF(A154<>"",DATA_RELATIONSHIPS!G151,"") | I154: =IF(A154<>"",""&DATA_RELATIONSHIPS!H151,"") | J154: =IF(A154<>"",""&DATA_RELATIONSHIPS!I151,"")

Sheet 04_Lineage_Explorer
A1: RESEARCH INTELLIGENCE ENGINE (RIE) — EPISTEMIC LINEAGE EXPLORER
A2: 4-Tier Vertical Evidence Tracing (KO ➔ IO ➔ EO ➔ Source) | Automated Lineage Health & Provenance Grounding
A4: NAVIGATION: | B4: =HYPERLINK("#'01_Executive_Dashboard'!A1", "⮌ BACK TO DASHBOARD") | C4: =HYPERLINK("#'02_Object_Registry'!A1", "➔ OBJECT REGISTRY") | D4: =HYPERLINK("#'03_Relationship_Registry'!A1", "➔ RELATIONSHIP REGISTRY") | E4: =HYPERLINK("#'05_Knowledge_Frontier'!A1", "➔ KNOWLEDGE FRONTIER") | F4: =HYPERLINK("#'06_Provenance_Register'!A1", "➔ PROVENANCE REGISTER") | G4: =HYPERLINK("#'07_Human_Decision_Log'!A1", "➔ DECISION LOG") | H4: =HYPERLINK("#'DATA_KO'!A1", "➔ REPOSITORY DATA")
A6: Target Knowledge Object (KO): | B6: =IF(D6<>"", D6, IF('01_Executive_Dashboard'!$C$21<>"", '01_Executive_Dashboard'!$C$21, '01_Executive_Dashboard'!$A$26)) | C6: Direct Override Selector: | E6: =HYPERLINK("#'01_Executive_Dashboard'!C21", "➔ [Select on Dashboard]") | F6: {=IFERROR(INDEX('05_Knowledge_Frontier'!H:H, MATCH($B$6, '05_Knowledge_Frontier'!B:B, 0)), "PENDING_ARCHITECT")} | G6: Review Action Link: | H6: =HYPERLINK("#'05_Knowledge_Frontier'!A" & IFERROR(MATCH($B$6, '05_Knowledge_Frontier'!B:B, 0), 1), "➔ Evaluate in Review Queue")
A7: Calculated Lineage Chain: | B7: {="Origin: " & INDEX(DATA_KO!D:D, MATCH(B6, DATA_KO!A:A, 0)) & " | Confidence: " & TEXT(INDEX(DATA_KO!G:G, MATCH(B6, DATA_KO!A:A, 0)), "0.00") & " | EO Count: " & (LEN(INDEX(DATA_KO!E:E, MATCH(B6, DATA_KO!A:A, 0)))-LEN(SUBSTITUTE(INDEX(DATA_KO!E:E, MATCH(B6, DATA_KO!A:A, 0)), ",", ""))+1) & " | Supporting IOs: " & INDEX(DATA_KO!F:F, MATCH(B6, DATA_KO!A:A, 0))}
A9: 1. KNOWLEDGE CLAIM (SYNTHESIZED THESIS & DOMAIN)
A10: Concept Title: | B10: {=INDEX(DATA_KO!B:B, MATCH($B$6, DATA_KO!A:A, 0))} | F10: Ratification State: | G10: {=INDEX(DATA_KO!I:I, MATCH($B$6, DATA_KO!A:A, 0))}
A11: Domain / Field: | B11: {=INDEX(DATA_KO!C:C, MATCH($B$6, DATA_KO!A:A, 0))} | F11: Epistemic Confidence: | G11: {=TEXT(INDEX(DATA_KO!G:G, MATCH($B$6, DATA_KO!A:A, 0)), "0.00")}
A13: 2. SUPPORTING INTERPRETATIONS (PRIMARY HYPOTHESES & MODELS)
A14: Core Research Inquiry (?): | B14: {=INDEX(DATA_IO!B:B, MATCH(TRIM(MID(SUBSTITUTE(INDEX(DATA_KO!F:F, MATCH($B$6, DATA_KO!A:A, 0)), ",", REPT(" ", 500)), 1, 500)), DATA_IO!A:A, 0))} | F14: Model IO ID: | G14: {=TRIM(MID(SUBSTITUTE(INDEX(DATA_KO!F:F, MATCH($B$6, DATA_KO!A:A, 0)), ",", REPT(" ", 500)), 1, 500))}
A15: Primary Model (Hypothesis A): | B15: {=INDEX(DATA_IO!C:C, MATCH(TRIM(MID(SUBSTITUTE(INDEX(DATA_KO!F:F, MATCH($B$6, DATA_KO!A:A, 0)), ",", REPT(" ", 500)), 1, 500)), DATA_IO!A:A, 0))} | F15: Model Confidence: | G15: {=TEXT(INDEX(DATA_IO!G:G, MATCH(TRIM(MID(SUBSTITUTE(INDEX(DATA_KO!F:F, MATCH($B$6, DATA_KO!A:A, 0)), ",", REPT(" ", 500)), 1, 500)), DATA_IO!A:A, 0)), "0.00")}
A17: 3. COMPETING INTERPRETATIONS (FALSIFICATION & COUNTER-HYPOTHESES)
A18: Competing Counter-Hypothesis B: | B18: {=INDEX(DATA_IO!D:D, MATCH(TRIM(MID(SUBSTITUTE(INDEX(DATA_KO!F:F, MATCH($B$6, DATA_KO!A:A, 0)), ",", REPT(" ", 500)), 1, 500)), DATA_IO!A:A, 0))} | F18: Future Research Trigger: | G18: {=INDEX(DATA_IO!I:I, MATCH(TRIM(MID(SUBSTITUTE(INDEX(DATA_KO!F:F, MATCH($B$6, DATA_KO!A:A, 0)), ",", REPT(" ", 500)), 1, 500)), DATA_IO!A:A, 0))}
A20: 4. EVIDENCE PROFILE (GROUND TRUTH EMPIRICAL OBSERVATIONS)
A21: Evidence_Object_ID | B21: Source_ID | C21: Timestamp / Page | D21: Presenter / Analyst | E21: Evidence Type | F21: Direct Empirical Observation
A22: {=IFERROR(TRIM(MID(SUBSTITUTE(INDEX(DATA_KO!E:E, MATCH($B$6, DATA_KO!A:A, 0)), ",", REPT(" ", 500)), (1-1)*500+1, 500)), "")} | B22: {=IF(A22="","", IFERROR(INDEX(DATA_EO!B:B, MATCH(A22, DATA_EO!A:A, 0)), "SOURCE_GAP"))} | C22: {=IF(A22="","", IFERROR(INDEX(DATA_EO!J:J, MATCH(A22, DATA_EO!A:A, 0)), "N/A"))} | D22: {=IF(A22="","", IFERROR(INDEX(DATA_EO!D:D, MATCH(A22, DATA_EO!A:A, 0)), "N/A"))} | E22: {=IF(A22="","", IFERROR(INDEX(DATA_EO!K:K, MATCH(A22, DATA_EO!A:A, 0)), "N/A"))} | F22: {=IF(A22="","", IFERROR(INDEX(DATA_EO!L:L, MATCH(A22, DATA_EO!A:A, 0)), "N/A"))}
A23: {=IFERROR(TRIM(MID(SUBSTITUTE(INDEX(DATA_KO!E:E, MATCH($B$6, DATA_KO!A:A, 0)), ",", REPT(" ", 500)), (2-1)*500+1, 500)), "")} | B23: {=IF(A23="","", IFERROR(INDEX(DATA_EO!B:B, MATCH(A23, DATA_EO!A:A, 0)), "SOURCE_GAP"))} | C23: {=IF(A23="","", IFERROR(INDEX(DATA_EO!J:J, MATCH(A23, DATA_EO!A:A, 0)), "N/A"))} | D23: {=IF(A23="","", IFERROR(INDEX(DATA_EO!D:D, MATCH(A23, DATA_EO!A:A, 0)), "N/A"))} | E23: {=IF(A23="","", IFERROR(INDEX(DATA_EO!K:K, MATCH(A23, DATA_EO!A:A, 0)), "N/A"))} | F23: {=IF(A23="","", IFERROR(INDEX(DATA_EO!L:L, MATCH(A23, DATA_EO!A:A, 0)), "N/A"))}
A24: {=IFERROR(TRIM(MID(SUBSTITUTE(INDEX(DATA_KO!E:E, MATCH($B$6, DATA_KO!A:A, 0)), ",", REPT(" ", 500)), (3-1)*500+1, 500)), "")} | B24: {=IF(A24="","", IFERROR(INDEX(DATA_EO!B:B, MATCH(A24, DATA_EO!A:A, 0)), "SOURCE_GAP"))} | C24: {=IF(A24="","", IFERROR(INDEX(DATA_EO!J:J, MATCH(A24, DATA_EO!A:A, 0)), "N/A"))} | D24: {=IF(A24="","", IFERROR(INDEX(DATA_EO!D:D, MATCH(A24, DATA_EO!A:A, 0)), "N/A"))} | E24: {=IF(A24="","", IFERROR(INDEX(DATA_EO!K:K, MATCH(A24, DATA_EO!A:A, 0)), "N/A"))} | F24: {=IF(A24="","", IFERROR(INDEX(DATA_EO!L:L, MATCH(A24, DATA_EO!A:A, 0)), "N/A"))}
A26: 5. SOURCE RECORDS & CRYPTOGRAPHIC PROVENANCE
A27: Origin Media Source Anchor: | B27: {=INDEX(DATA_KO!D:D, MATCH($B$6, DATA_KO!A:A, 0))} | D27: Speaker / Channel: | E27: {=INDEX(DATA_EO!D:D, MATCH(A22, DATA_EO!A:A, 0)) & " (" & INDEX(DATA_EO!E:E, MATCH(A22, DATA_EO!A:A, 0)) & ")"} | G27: Obsidian Second-Brain Link: | H27: ="[[" & $B$6 & "]]"
A29: HUMAN GOVERNANCE DECISION: | B29: =HYPERLINK("#'07_Human_Decision_Log'!A1", "➔ [ RECORD FORMAL HUMAN DECISION IN DECISION LOG (ACCEPT / HOLD / REJECT / FURTHER RESEARCH) ]")
A45: =DATA_KO!A18 | B45: =DATA_KO!B18 | C45: =DATA_KO!C18 | D45: =DATA_KO!D18 | E45: =IF(DATA_KO!F18="","", LEN(DATA_KO!F18)-LEN(SUBSTITUTE(DATA_KO!F18, ",", ""))+1) | F45: =IF(DATA_KO!E18="","", LEN(DATA_KO!E18)-LEN(SUBSTITUTE(DATA_KO!E18, ",", ""))+1) | G45: =IF(OR(DATA_KO!E18="", DATA_KO!F18=""), "BROKEN_LINEAGE", IF(DATA_KO!H18="QUARANTINED_SYNTHETIC_FIXTURE", "QUARANTINED_FIXTURE", IF(OR(DATA_KO!H18="CANDIDATE", DATA_KO!G18<0.8), "WARNING_REVIEW_REQUIRED", "VERIFIED_COMPLETE"))) | H45: =IF(G45="BROKEN_LINEAGE", "HALT: RESOLVE DANGLING OBJECT", IF(G45="QUARANTINED_FIXTURE", "EXCLUDED: QUARANTINED SYNTHETIC FIXTURE", IF(G45="WARNING_REVIEW_REQUIRED", "QUEUE FOR LEVEL 5 RATIFICATION", "RATIFIED CANONICAL")))
A46: =DATA_KO!A19 | B46: =DATA_KO!B19 | C46: =DATA_KO!C19 | D46: =DATA_KO!D19 | E46: =IF(DATA_KO!F19="","", LEN(DATA_KO!F19)-LEN(SUBSTITUTE(DATA_KO!F19, ",", ""))+1) | F46: =IF(DATA_KO!E19="","", LEN(DATA_KO!E19)-LEN(SUBSTITUTE(DATA_KO!E19, ",", ""))+1) | G46: =IF(OR(DATA_KO!E19="", DATA_KO!F19=""), "BROKEN_LINEAGE", IF(DATA_KO!H19="QUARANTINED_SYNTHETIC_FIXTURE", "QUARANTINED_FIXTURE", IF(OR(DATA_KO!H19="CANDIDATE", DATA_KO!G19<0.8), "WARNING_REVIEW_REQUIRED", "VERIFIED_COMPLETE"))) | H46: =IF(G46="BROKEN_LINEAGE", "HALT: RESOLVE DANGLING OBJECT", IF(G46="QUARANTINED_FIXTURE", "EXCLUDED: QUARANTINED SYNTHETIC FIXTURE", IF(G46="WARNING_REVIEW_REQUIRED", "QUEUE FOR LEVEL 5 RATIFICATION", "RATIFIED CANONICAL")))

Sheet 05_Knowledge_Frontier
A1: RESEARCH INTELLIGENCE ENGINE (RIE) — HUMAN KNOWLEDGE REVIEW WORKFLOW | J1: =HYPERLINK("#'01_Executive_Dashboard'!A1", "⮌ BACK TO DASHBOARD")
A2: ="Pillar 5: Knowledge Frontier & Epistemic Candidate Queue (" & (COUNTIF(DATA_KO!H:H, "CANDIDATE") + COUNTIF(DATA_KO!H:H, "PENDING_HUMAN_REVIEW")) & " Candidates) | Level 5 Authority"
A4: REVIEW WORKFLOW INVARIANTS: Allowed Review States: PENDING_ARCHITECT | UNDER_REVIEW | ACCEPTED | REJECTED | DEFERRED. Strictly NO automatic transition. NO AI promotion. Human Architect Level 5 decision required.
A6: Queue_ID | B6: Subject_Object | C6: Item_Type | D6: Recommendation | E6: Evidence_Count | F6: Domain | G6: Confidence | H6: Review_Status | I6: Architect_Decision | J6: Review_Link | K6: Architect_Remark
A7: =IF(DATA_KO!A2<>"","Q-"&TEXT(1,"000"),"") | B7: =IF(DATA_KO!A2<>"",""&DATA_KO!A2,"") | C7: =IF(A7<>"",""&DATA_KO!H2&"_KO","") | D7: =IF(A7<>"","Candidate: "&DATA_KO!B2,"") | E7: =IF(A7<>"","EO: "&DATA_KO!Q2&", IO: "&DATA_KO!R2,"") | F7: =IF(A7<>"",""&DATA_KO!C2,"") | G7: =IF(A7<>"",DATA_KO!G2,"") | H7: =IF(A7<>"",""&DATA_KO!H2,"") | I7: =IF(A7<>"",""&DATA_KO!I2,"") | J7: =IF(A7<>"","➔ Inspect Item","") | K7: Queued for Human Architect Level 5 evaluation. No premature acceptance.
A8: =IF(DATA_KO!A3<>"","Q-"&TEXT(2,"000"),"") | B8: =IF(DATA_KO!A3<>"",""&DATA_KO!A3,"") | C8: =IF(A8<>"",""&DATA_KO!H3&"_KO","") | D8: =IF(A8<>"","Candidate: "&DATA_KO!B3,"") | E8: =IF(A8<>"","EO: "&DATA_KO!Q3&", IO: "&DATA_KO!R3,"") | F8: =IF(A8<>"",""&DATA_KO!C3,"") | G8: =IF(A8<>"",DATA_KO!G3,"") | H8: =IF(A8<>"",""&DATA_KO!H3,"") | I8: =IF(A8<>"",""&DATA_KO!I3,"") | J8: =IF(A8<>"","➔ Inspect Item","") | K8: Queued for Human Architect Level 5 evaluation. No premature acceptance.
A9: =IF(DATA_KO!A4<>"","Q-"&TEXT(3,"000"),"") | B9: =IF(DATA_KO!A4<>"",""&DATA_KO!A4,"") | C9: =IF(A9<>"",""&DATA_KO!H4&"_KO","") | D9: =IF(A9<>"","Candidate: "&DATA_KO!B4,"") | E9: =IF(A9<>"","EO: "&DATA_KO!Q4&", IO: "&DATA_KO!R4,"") | F9: =IF(A9<>"",""&DATA_KO!C4,"") | G9: =IF(A9<>"",DATA_KO!G4,"") | H9: =IF(A9<>"",""&DATA_KO!H4,"") | I9: =IF(A9<>"",""&DATA_KO!I4,"") | J9: =IF(A9<>"","➔ Inspect Item","") | K9: Queued for Human Architect Level 5 evaluation. No premature acceptance.
A10: =IF(DATA_KO!A5<>"","Q-"&TEXT(4,"000"),"") | B10: =IF(DATA_KO!A5<>"",""&DATA_KO!A5,"") | C10: =IF(A10<>"",""&DATA_KO!H5&"_KO","") | D10: =IF(A10<>"","Candidate: "&DATA_KO!B5,"") | E10: =IF(A10<>"","EO: "&DATA_KO!Q5&", IO: "&DATA_KO!R5,"") | F10: =IF(A10<>"",""&DATA_KO!C5,"") | G10: =IF(A10<>"",DATA_KO!G5,"") | H10: =IF(A10<>"",""&DATA_KO!H5,"") | I10: =IF(A10<>"",""&DATA_KO!I5,"") | J10: =IF(A10<>"","➔ Inspect Item","") | K10: Queued for Human Architect Level 5 evaluation. No premature acceptance.
A11: =IF(DATA_KO!A6<>"","Q-"&TEXT(5,"000"),"") | B11: =IF(DATA_KO!A6<>"",""&DATA_KO!A6,"") | C11: =IF(A11<>"",""&DATA_KO!H6&"_KO","") | D11: =IF(A11<>"","Candidate: "&DATA_KO!B6,"") | E11: =IF(A11<>"","EO: "&DATA_KO!Q6&", IO: "&DATA_KO!R6,"") | F11: =IF(A11<>"",""&DATA_KO!C6,"") | G11: =IF(A11<>"",DATA_KO!G6,"") | H11: =IF(A11<>"",""&DATA_KO!H6,"") | I11: =IF(A11<>"",""&DATA_KO!I6,"") | J11: =IF(A11<>"","➔ Inspect Item","") | K11: Queued for Human Architect Level 5 evaluation. No premature acceptance.
A12: =IF(DATA_KO!A7<>"","Q-"&TEXT(6,"000"),"") | B12: =IF(DATA_KO!A7<>"",""&DATA_KO!A7,"") | C12: =IF(A12<>"",""&DATA_KO!H7&"_KO","") | D12: =IF(A12<>"","Candidate: "&DATA_KO!B7,"") | E12: =IF(A12<>"","EO: "&DATA_KO!Q7&", IO: "&DATA_KO!R7,"") | F12: =IF(A12<>"",""&DATA_KO!C7,"") | G12: =IF(A12<>"",DATA_KO!G7,"") | H12: =IF(A12<>"",""&DATA_KO!H7,"") | I12: =IF(A12<>"",""&DATA_KO!I7,"") | J12: =IF(A12<>"","➔ Inspect Item","") | K12: Queued for Human Architect Level 5 evaluation. No premature acceptance.
A13: =IF(DATA_KO!A8<>"","Q-"&TEXT(7,"000"),"") | B13: =IF(DATA_KO!A8<>"",""&DATA_KO!A8,"") | C13: =IF(A13<>"",""&DATA_KO!H8&"_KO","") | D13: =IF(A13<>"","Candidate: "&DATA_KO!B8,"") | E13: =IF(A13<>"","EO: "&DATA_KO!Q8&", IO: "&DATA_KO!R8,"") | F13: =IF(A13<>"",""&DATA_KO!C8,"") | G13: =IF(A13<>"",DATA_KO!G8,"") | H13: =IF(A13<>"",""&DATA_KO!H8,"") | I13: =IF(A13<>"",""&DATA_KO!I8,"") | J13: =IF(A13<>"","➔ Inspect Item","") | K13: Queued for Human Architect Level 5 evaluation. No premature acceptance.
A14: =IF(DATA_KO!A9<>"","Q-"&TEXT(8,"000"),"") | B14: =IF(DATA_KO!A9<>"",""&DATA_KO!A9,"") | C14: =IF(A14<>"",""&DATA_KO!H9&"_KO","") | D14: =IF(A14<>"","Candidate: "&DATA_KO!B9,"") | E14: =IF(A14<>"","EO: "&DATA_KO!Q9&", IO: "&DATA_KO!R9,"") | F14: =IF(A14<>"",""&DATA_KO!C9,"") | G14: =IF(A14<>"",DATA_KO!G9,"") | H14: =IF(A14<>"",""&DATA_KO!H9,"") | I14: =IF(A14<>"",""&DATA_KO!I9,"") | J14: =IF(A14<>"","➔ Inspect Item","") | K14: Queued for Human Architect Level 5 evaluation. No premature acceptance.
A15: =IF(DATA_KO!A10<>"","Q-"&TEXT(9,"000"),"") | B15: =IF(DATA_KO!A10<>"",""&DATA_KO!A10,"") | C15: =IF(A15<>"",""&DATA_KO!H10&"_KO","") | D15: =IF(A15<>"","Candidate: "&DATA_KO!B10,"") | E15: =IF(A15<>"","EO: "&DATA_KO!Q10&", IO: "&DATA_KO!R10,"") | F15: =IF(A15<>"",""&DATA_KO!C10,"") | G15: =IF(A15<>"",DATA_KO!G10,"") | H15: =IF(A15<>"",""&DATA_KO!H10,"") | I15: =IF(A15<>"",""&DATA_KO!I10,"") | J15: =IF(A15<>"","➔ Inspect Item","") | K15: Queued for Human Architect Level 5 evaluation. No premature acceptance.
A16: =IF(DATA_KO!A11<>"","Q-"&TEXT(10,"000"),"") | B16: =IF(DATA_KO!A11<>"",""&DATA_KO!A11,"") | C16: =IF(A16<>"",""&DATA_KO!H11&"_KO","") | D16: =IF(A16<>"","Candidate: "&DATA_KO!B11,"") | E16: =IF(A16<>"","EO: "&DATA_KO!Q11&", IO: "&DATA_KO!R11,"") | F16: =IF(A16<>"",""&DATA_KO!C11,"") | G16: =IF(A16<>"",DATA_KO!G11,"") | H16: =IF(A16<>"",""&DATA_KO!H11,"") | I16: =IF(A16<>"",""&DATA_KO!I11,"") | J16: =IF(A16<>"","➔ Inspect Item","") | K16: Queued for Human Architect Level 5 evaluation. No premature acceptance.
A17: =IF(DATA_KO!A12<>"","Q-"&TEXT(11,"000"),"") | B17: =IF(DATA_KO!A12<>"",""&DATA_KO!A12,"") | C17: =IF(A17<>"",""&DATA_KO!H12&"_KO","") | D17: =IF(A17<>"","Candidate: "&DATA_KO!B12,"") | E17: =IF(A17<>"","EO: "&DATA_KO!Q12&", IO: "&DATA_KO!R12,"") | F17: =IF(A17<>"",""&DATA_KO!C12,"") | G17: =IF(A17<>"",DATA_KO!G12,"") | H17: =IF(A17<>"",""&DATA_KO!H12,"") | I17: =IF(A17<>"",""&DATA_KO!I12,"") | J17: =IF(A17<>"","➔ Inspect Item","") | K17: Queued for Human Architect Level 5 evaluation. No premature acceptance.
A18: =IF(DATA_KO!A13<>"","Q-"&TEXT(12,"000"),"") | B18: =IF(DATA_KO!A13<>"",""&DATA_KO!A13,"") | C18: =IF(A18<>"",""&DATA_KO!H13&"_KO","") | D18: =IF(A18<>"","Candidate: "&DATA_KO!B13,"") | E18: =IF(A18<>"","EO: "&DATA_KO!Q13&", IO: "&DATA_KO!R13,"") | F18: =IF(A18<>"",""&DATA_KO!C13,"") | G18: =IF(A18<>"",DATA_KO!G13,"") | H18: =IF(A18<>"",""&DATA_KO!H13,"") | I18: =IF(A18<>"",""&DATA_KO!I13,"") | J18: =IF(A18<>"","➔ Inspect Item","") | K18: Queued for Human Architect Level 5 evaluation. No premature acceptance.
A19: =IF(DATA_KO!A14<>"","Q-"&TEXT(13,"000"),"") | B19: =IF(DATA_KO!A14<>"",""&DATA_KO!A14,"") | C19: =IF(A19<>"",""&DATA_KO!H14&"_KO","") | D19: =IF(A19<>"","Candidate: "&DATA_KO!B14,"") | E19: =IF(A19<>"","EO: "&DATA_KO!Q14&", IO: "&DATA_KO!R14,"") | F19: =IF(A19<>"",""&DATA_KO!C14,"") | G19: =IF(A19<>"",DATA_KO!G14,"") | H19: =IF(A19<>"",""&DATA_KO!H14,"") | I19: =IF(A19<>"",""&DATA_KO!I14,"") | J19: =IF(A19<>"","➔ Inspect Item","") | K19: Queued for Human Architect Level 5 evaluation. No premature acceptance.
A20: =IF(DATA_KO!A15<>"","Q-"&TEXT(14,"000"),"") | B20: =IF(DATA_KO!A15<>"",""&DATA_KO!A15,"") | C20: =IF(A20<>"",""&DATA_KO!H15&"_KO","") | D20: =IF(A20<>"","Candidate: "&DATA_KO!B15,"") | E20: =IF(A20<>"","EO: "&DATA_KO!Q15&", IO: "&DATA_KO!R15,"") | F20: =IF(A20<>"",""&DATA_KO!C15,"") | G20: =IF(A20<>"",DATA_KO!G15,"") | H20: =IF(A20<>"",""&DATA_KO!H15,"") | I20: =IF(A20<>"",""&DATA_KO!I15,"") | J20: =IF(A20<>"","➔ Inspect Item","") | K20: Queued for Human Architect Level 5 evaluation. No premature acceptance.
A21: =IF(DATA_KO!A16<>"","Q-"&TEXT(15,"000"),"") | B21: =IF(DATA_KO!A16<>"",""&DATA_KO!A16,"") | C21: =IF(A21<>"",""&DATA_KO!H16&"_KO","") | D21: =IF(A21<>"","Candidate: "&DATA_KO!B16,"") | E21: =IF(A21<>"","EO: "&DATA_KO!Q16&", IO: "&DATA_KO!R16,"") | F21: =IF(A21<>"",""&DATA_KO!C16,"") | G21: =IF(A21<>"",DATA_KO!G16,"") | H21: =IF(A21<>"",""&DATA_KO!H16,"") | I21: =IF(A21<>"",""&DATA_KO!I16,"") | J21: =IF(A21<>"","➔ Inspect Item","") | K21: Queued for Human Architect Level 5 evaluation. No premature acceptance.
A22: =IF(DATA_KO!A17<>"","Q-"&TEXT(16,"000"),"") | B22: =IF(DATA_KO!A17<>"",""&DATA_KO!A17,"") | C22: =IF(A22<>"",""&DATA_KO!H17&"_KO","") | D22: =IF(A22<>"","Candidate: "&DATA_KO!B17,"") | E22: =IF(A22<>"","EO: "&DATA_KO!Q17&", IO: "&DATA_KO!R17,"") | F22: =IF(A22<>"",""&DATA_KO!C17,"") | G22: =IF(A22<>"",DATA_KO!G17,"") | H22: =IF(A22<>"",""&DATA_KO!H17,"") | I22: =IF(A22<>"",""&DATA_KO!I17,"") | J22: =IF(A22<>"","➔ Inspect Item","") | K22: Queued for Human Architect Level 5 evaluation. No premature acceptance.
A23: =IF(DATA_KO!A18<>"","Q-"&TEXT(17,"000"),"") | B23: =IF(DATA_KO!A18<>"",""&DATA_KO!A18,"") | C23: =IF(A23<>"",""&DATA_KO!H18&"_KO","") | D23: =IF(A23<>"","Candidate: "&DATA_KO!B18,"") | E23: =IF(A23<>"","EO: "&DATA_KO!Q18&", IO: "&DATA_KO!R18,"") | F23: =IF(A23<>"",""&DATA_KO!C18,"") | G23: =IF(A23<>"",DATA_KO!G18,"") | H23: =IF(A23<>"",""&DATA_KO!H18,"") | I23: =IF(A23<>"",""&DATA_KO!I18,"") | J23: =IF(A23<>"","➔ Inspect Item","") | K23: Queued for Human Architect Level 5 evaluation. No premature acceptance.
A24: =IF(DATA_KO!A19<>"","Q-"&TEXT(18,"000"),"") | B24: =IF(DATA_KO!A19<>"",""&DATA_KO!A19,"") | C24: =IF(A24<>"",""&DATA_KO!H19&"_KO","") | D24: =IF(A24<>"","Candidate: "&DATA_KO!B19,"") | E24: =IF(A24<>"","EO: "&DATA_KO!Q19&", IO: "&DATA_KO!R19,"") | F24: =IF(A24<>"",""&DATA_KO!C19,"") | G24: =IF(A24<>"",DATA_KO!G19,"") | H24: =IF(A24<>"",""&DATA_KO!H19,"") | I24: =IF(A24<>"",""&DATA_KO!I19,"") | J24: =IF(A24<>"","➔ Inspect Item","") | K24: Queued for Human Architect Level 5 evaluation. No premature acceptance.
A25: =IF(DATA_KO!A20<>"","Q-"&TEXT(19,"000"),"") | B25: =IF(DATA_KO!A20<>"",""&DATA_KO!A20,"") | C25: =IF(A25<>"",""&DATA_KO!H20&"_KO","") | D25: =IF(A25<>"","Candidate: "&DATA_KO!B20,"") | E25: =IF(A25<>"","EO: "&DATA_KO!Q20&", IO: "&DATA_KO!R20,"") | F25: =IF(A25<>"",""&DATA_KO!C20,"") | G25: =IF(A25<>"",DATA_KO!G20,"") | H25: =IF(A25<>"",""&DATA_KO!H20,"") | I25: =IF(A25<>"",""&DATA_KO!I20,"") | J25: =IF(A25<>"","➔ Inspect Item","") | K25: Queued for Human Architect Level 5 evaluation. No premature acceptance.
A26: =IF(DATA_KO!A21<>"","Q-"&TEXT(20,"000"),"") | B26: =IF(DATA_KO!A21<>"",""&DATA_KO!A21,"") | C26: =IF(A26<>"",""&DATA_KO!H21&"_KO","") | D26: =IF(A26<>"","Candidate: "&DATA_KO!B21,"") | E26: =IF(A26<>"","EO: "&DATA_KO!Q21&", IO: "&DATA_KO!R21,"") | F26: =IF(A26<>"",""&DATA_KO!C21,"") | G26: =IF(A26<>"",DATA_KO!G21,"") | H26: =IF(A26<>"",""&DATA_KO!H21,"") | I26: =IF(A26<>"",""&DATA_KO!I21,"") | J26: =IF(A26<>"","➔ Inspect Item","") | K26: Queued for Human Architect Level 5 evaluation. No premature acceptance.
A27: =IF(DATA_KO!A22<>"","Q-"&TEXT(21,"000"),"") | B27: =IF(DATA_KO!A22<>"",""&DATA_KO!A22,"") | C27: =IF(A27<>"",""&DATA_KO!H22&"_KO","") | D27: =IF(A27<>"","Candidate: "&DATA_KO!B22,"") | E27: =IF(A27<>"","EO: "&DATA_KO!Q22&", IO: "&DATA_KO!R22,"") | F27: =IF(A27<>"",""&DATA_KO!C22,"") | G27: =IF(A27<>"",DATA_KO!G22,"") | H27: =IF(A27<>"",""&DATA_KO!H22,"") | I27: =IF(A27<>"",""&DATA_KO!I22,"") | J27: =IF(A27<>"","➔ Inspect Item","") | K27: Queued for Human Architect Level 5 evaluation. No premature acceptance.
A28: =IF(DATA_KO!A23<>"","Q-"&TEXT(22,"000"),"") | B28: =IF(DATA_KO!A23<>"",""&DATA_KO!A23,"") | C28: =IF(A28<>"",""&DATA_KO!H23&"_KO","") | D28: =IF(A28<>"","Candidate: "&DATA_KO!B23,"") | E28: =IF(A28<>"","EO: "&DATA_KO!Q23&", IO: "&DATA_KO!R23,"") | F28: =IF(A28<>"",""&DATA_KO!C23,"") | G28: =IF(A28<>"",DATA_KO!G23,"") | H28: =IF(A28<>"",""&DATA_KO!H23,"") | I28: =IF(A28<>"",""&DATA_KO!I23,"") | J28: =IF(A28<>"","➔ Inspect Item","") | K28: Queued for Human Architect Level 5 evaluation. No premature acceptance.
A29: =IF(DATA_KO!A24<>"","Q-"&TEXT(23,"000"),"") | B29: =IF(DATA_KO!A24<>"",""&DATA_KO!A24,"") | C29: =IF(A29<>"",""&DATA_KO!H24&"_KO","") | D29: =IF(A29<>"","Candidate: "&DATA_KO!B24,"") | E29: =IF(A29<>"","EO: "&DATA_KO!Q24&", IO: "&DATA_KO!R24,"") | F29: =IF(A29<>"",""&DATA_KO!C24,"") | G29: =IF(A29<>"",DATA_KO!G24,"") | H29: =IF(A29<>"",""&DATA_KO!H24,"") | I29: =IF(A29<>"",""&DATA_KO!I24,"") | J29: =IF(A29<>"","➔ Inspect Item","") | K29: Queued for Human Architect Level 5 evaluation. No premature acceptance.
A30: =IF(DATA_KO!A25<>"","Q-"&TEXT(24,"000"),"") | B30: =IF(DATA_KO!A25<>"",""&DATA_KO!A25,"") | C30: =IF(A30<>"",""&DATA_KO!H25&"_KO","") | D30: =IF(A30<>"","Candidate: "&DATA_KO!B25,"") | E30: =IF(A30<>"","EO: "&DATA_KO!Q25&", IO: "&DATA_KO!R25,"") | F30: =IF(A30<>"",""&DATA_KO!C25,"") | G30: =IF(A30<>"",DATA_KO!G25,"") | H30: =IF(A30<>"",""&DATA_KO!H25,"") | I30: =IF(A30<>"",""&DATA_KO!I25,"") | J30: =IF(A30<>"","➔ Inspect Item","")
A31: =IF(DATA_KO!A26<>"","Q-"&TEXT(25,"000"),"") | B31: =IF(DATA_KO!A26<>"",""&DATA_KO!A26,"") | C31: =IF(A31<>"",""&DATA_KO!H26&"_KO","") | D31: =IF(A31<>"","Candidate: "&DATA_KO!B26,"") | E31: =IF(A31<>"","EO: "&DATA_KO!Q26&", IO: "&DATA_KO!R26,"") | F31: =IF(A31<>"",""&DATA_KO!C26,"") | G31: =IF(A31<>"",DATA_KO!G26,"") | H31: =IF(A31<>"",""&DATA_KO!H26,"") | I31: =IF(A31<>"",""&DATA_KO!I26,"") | J31: =IF(A31<>"","➔ Inspect Item","")
A32: =IF(DATA_KO!A27<>"","Q-"&TEXT(26,"000"),"") | B32: =IF(DATA_KO!A27<>"",""&DATA_KO!A27,"") | C32: =IF(A32<>"",""&DATA_KO!H27&"_KO","") | D32: =IF(A32<>"","Candidate: "&DATA_KO!B27,"") | E32: =IF(A32<>"","EO: "&DATA_KO!Q27&", IO: "&DATA_KO!R27,"") | F32: =IF(A32<>"",""&DATA_KO!C27,"") | G32: =IF(A32<>"",DATA_KO!G27,"") | H32: =IF(A32<>"",""&DATA_KO!H27,"") | I32: =IF(A32<>"",""&DATA_KO!I27,"") | J32: =IF(A32<>"","➔ Inspect Item","")
A33: =IF(DATA_KO!A28<>"","Q-"&TEXT(27,"000"),"") | B33: =IF(DATA_KO!A28<>"",""&DATA_KO!A28,"") | C33: =IF(A33<>"",""&DATA_KO!H28&"_KO","") | D33: =IF(A33<>"","Candidate: "&DATA_KO!B28,"") | E33: =IF(A33<>"","EO: "&DATA_KO!Q28&", IO: "&DATA_KO!R28,"") | F33: =IF(A33<>"",""&DATA_KO!C28,"") | G33: =IF(A33<>"",DATA_KO!G28,"") | H33: =IF(A33<>"",""&DATA_KO!H28,"") | I33: =IF(A33<>"",""&DATA_KO!I28,"") | J33: =IF(A33<>"","➔ Inspect Item","")
A34: =IF(DATA_KO!A29<>"","Q-"&TEXT(28,"000"),"") | B34: =IF(DATA_KO!A29<>"",""&DATA_KO!A29,"") | C34: =IF(A34<>"",""&DATA_KO!H29&"_KO","") | D34: =IF(A34<>"","Candidate: "&DATA_KO!B29,"") | E34: =IF(A34<>"","EO: "&DATA_KO!Q29&", IO: "&DATA_KO!R29,"") | F34: =IF(A34<>"",""&DATA_KO!C29,"") | G34: =IF(A34<>"",DATA_KO!G29,"") | H34: =IF(A34<>"",""&DATA_KO!H29,"") | I34: =IF(A34<>"",""&DATA_KO!I29,"") | J34: =IF(A34<>"","➔ Inspect Item","")
A35: =IF(DATA_KO!A30<>"","Q-"&TEXT(29,"000"),"") | B35: =IF(DATA_KO!A30<>"",""&DATA_KO!A30,"") | C35: =IF(A35<>"",""&DATA_KO!H30&"_KO","") | D35: =IF(A35<>"","Candidate: "&DATA_KO!B30,"") | E35: =IF(A35<>"","EO: "&DATA_KO!Q30&", IO: "&DATA_KO!R30,"") | F35: =IF(A35<>"",""&DATA_KO!C30,"") | G35: =IF(A35<>"",DATA_KO!G30,"") | H35: =IF(A35<>"",""&DATA_KO!H30,"") | I35: =IF(A35<>"",""&DATA_KO!I30,"") | J35: =IF(A35<>"","➔ Inspect Item","")
A36: =IF(DATA_KO!A31<>"","Q-"&TEXT(30,"000"),"") | B36: =IF(DATA_KO!A31<>"",""&DATA_KO!A31,"") | C36: =IF(A36<>"",""&DATA_KO!H31&"_KO","") | D36: =IF(A36<>"","Candidate: "&DATA_KO!B31,"") | E36: =IF(A36<>"","EO: "&DATA_KO!Q31&", IO: "&DATA_KO!R31,"") | F36: =IF(A36<>"",""&DATA_KO!C31,"") | G36: =IF(A36<>"",DATA_KO!G31,"") | H36: =IF(A36<>"",""&DATA_KO!H31,"") | I36: =IF(A36<>"",""&DATA_KO!I31,"") | J36: =IF(A36<>"","➔ Inspect Item","")
A37: =IF(DATA_KO!A32<>"","Q-"&TEXT(31,"000"),"") | B37: =IF(DATA_KO!A32<>"",""&DATA_KO!A32,"") | C37: =IF(A37<>"",""&DATA_KO!H32&"_KO","") | D37: =IF(A37<>"","Candidate: "&DATA_KO!B32,"") | E37: =IF(A37<>"","EO: "&DATA_KO!Q32&", IO: "&DATA_KO!R32,"") | F37: =IF(A37<>"",""&DATA_KO!C32,"") | G37: =IF(A37<>"",DATA_KO!G32,"") | H37: =IF(A37<>"",""&DATA_KO!H32,"") | I37: =IF(A37<>"",""&DATA_KO!I32,"") | J37: =IF(A37<>"","➔ Inspect Item","")
A38: =IF(DATA_KO!A33<>"","Q-"&TEXT(32,"000"),"") | B38: =IF(DATA_KO!A33<>"",""&DATA_KO!A33,"") | C38: =IF(A38<>"",""&DATA_KO!H33&"_KO","") | D38: =IF(A38<>"","Candidate: "&DATA_KO!B33,"") | E38: =IF(A38<>"","EO: "&DATA_KO!Q33&", IO: "&DATA_KO!R33,"") | F38: =IF(A38<>"",""&DATA_KO!C33,"") | G38: =IF(A38<>"",DATA_KO!G33,"") | H38: =IF(A38<>"",""&DATA_KO!H33,"") | I38: =IF(A38<>"",""&DATA_KO!I33,"") | J38: =IF(A38<>"","➔ Inspect Item","")
A39: =IF(DATA_KO!A34<>"","Q-"&TEXT(33,"000"),"") | B39: =IF(DATA_KO!A34<>"",""&DATA_KO!A34,"") | C39: =IF(A39<>"",""&DATA_KO!H34&"_KO","") | D39: =IF(A39<>"","Candidate: "&DATA_KO!B34,"") | E39: =IF(A39<>"","EO: "&DATA_KO!Q34&", IO: "&DATA_KO!R34,"") | F39: =IF(A39<>"",""&DATA_KO!C34,"") | G39: =IF(A39<>"",DATA_KO!G34,"") | H39: =IF(A39<>"",""&DATA_KO!H34,"") | I39: =IF(A39<>"",""&DATA_KO!I34,"") | J39: =IF(A39<>"","➔ Inspect Item","")
A40: =IF(DATA_KO!A35<>"","Q-"&TEXT(34,"000"),"") | B40: =IF(DATA_KO!A35<>"",""&DATA_KO!A35,"") | C40: =IF(A40<>"",""&DATA_KO!H35&"_KO","") | D40: =IF(A40<>"","Candidate: "&DATA_KO!B35,"") | E40: =IF(A40<>"","EO: "&DATA_KO!Q35&", IO: "&DATA_KO!R35,"") | F40: =IF(A40<>"",""&DATA_KO!C35,"") | G40: =IF(A40<>"",DATA_KO!G35,"") | H40: =IF(A40<>"",""&DATA_KO!H35,"") | I40: =IF(A40<>"",""&DATA_KO!I35,"") | J40: =IF(A40<>"","➔ Inspect Item","")
A41: =IF(DATA_KO!A36<>"","Q-"&TEXT(35,"000"),"") | B41: =IF(DATA_KO!A36<>"",""&DATA_KO!A36,"") | C41: =IF(A41<>"",""&DATA_KO!H36&"_KO","") | D41: =IF(A41<>"","Candidate: "&DATA_KO!B36,"") | E41: =IF(A41<>"","EO: "&DATA_KO!Q36&", IO: "&DATA_KO!R36,"") | F41: =IF(A41<>"",""&DATA_KO!C36,"") | G41: =IF(A41<>"",DATA_KO!G36,"") | H41: =IF(A41<>"",""&DATA_KO!H36,"") | I41: =IF(A41<>"",""&DATA_KO!I36,"") | J41: =IF(A41<>"","➔ Inspect Item","")
A42: =IF(DATA_KO!A37<>"","Q-"&TEXT(36,"000"),"") | B42: =IF(DATA_KO!A37<>"",""&DATA_KO!A37,"") | C42: =IF(A42<>"",""&DATA_KO!H37&"_KO","") | D42: =IF(A42<>"","Candidate: "&DATA_KO!B37,"") | E42: =IF(A42<>"","EO: "&DATA_KO!Q37&", IO: "&DATA_KO!R37,"") | F42: =IF(A42<>"",""&DATA_KO!C37,"") | G42: =IF(A42<>"",DATA_KO!G37,"") | H42: =IF(A42<>"",""&DATA_KO!H37,"") | I42: =IF(A42<>"",""&DATA_KO!I37,"") | J42: =IF(A42<>"","➔ Inspect Item","")
A43: =IF(DATA_KO!A38<>"","Q-"&TEXT(37,"000"),"") | B43: =IF(DATA_KO!A38<>"",""&DATA_KO!A38,"") | C43: =IF(A43<>"",""&DATA_KO!H38&"_KO","") | D43: =IF(A43<>"","Candidate: "&DATA_KO!B38,"") | E43: =IF(A43<>"","EO: "&DATA_KO!Q38&", IO: "&DATA_KO!R38,"") | F43: =IF(A43<>"",""&DATA_KO!C38,"") | G43: =IF(A43<>"",DATA_KO!G38,"") | H43: =IF(A43<>"",""&DATA_KO!H38,"") | I43: =IF(A43<>"",""&DATA_KO!I38,"") | J43: =IF(A43<>"","➔ Inspect Item","")
A44: =IF(DATA_KO!A39<>"","Q-"&TEXT(38,"000"),"") | B44: =IF(DATA_KO!A39<>"",""&DATA_KO!A39,"") | C44: =IF(A44<>"",""&DATA_KO!H39&"_KO","") | D44: =IF(A44<>"","Candidate: "&DATA_KO!B39,"") | E44: =IF(A44<>"","EO: "&DATA_KO!Q39&", IO: "&DATA_KO!R39,"") | F44: =IF(A44<>"",""&DATA_KO!C39,"") | G44: =IF(A44<>"",DATA_KO!G39,"") | H44: =IF(A44<>"",""&DATA_KO!H39,"") | I44: =IF(A44<>"",""&DATA_KO!I39,"") | J44: =IF(A44<>"","➔ Inspect Item","")
A45: =IF(DATA_KO!A40<>"","Q-"&TEXT(39,"000"),"") | B45: =IF(DATA_KO!A40<>"",""&DATA_KO!A40,"") | C45: =IF(A45<>"",""&DATA_KO!H40&"_KO","") | D45: =IF(A45<>"","Candidate: "&DATA_KO!B40,"") | E45: =IF(A45<>"","EO: "&DATA_KO!Q40&", IO: "&DATA_KO!R40,"") | F45: =IF(A45<>"",""&DATA_KO!C40,"") | G45: =IF(A45<>"",DATA_KO!G40,"") | H45: =IF(A45<>"",""&DATA_KO!H40,"") | I45: =IF(A45<>"",""&DATA_KO!I40,"") | J45: =IF(A45<>"","➔ Inspect Item","")
A46: =IF(DATA_KO!A41<>"","Q-"&TEXT(40,"000"),"") | B46: =IF(DATA_KO!A41<>"",""&DATA_KO!A41,"") | C46: =IF(A46<>"",""&DATA_KO!H41&"_KO","") | D46: =IF(A46<>"","Candidate: "&DATA_KO!B41,"") | E46: =IF(A46<>"","EO: "&DATA_KO!Q41&", IO: "&DATA_KO!R41,"") | F46: =IF(A46<>"",""&DATA_KO!C41,"") | G46: =IF(A46<>"",DATA_KO!G41,"") | H46: =IF(A46<>"",""&DATA_KO!H41,"") | I46: =IF(A46<>"",""&DATA_KO!I41,"") | J46: =IF(A46<>"","➔ Inspect Item","")
A47: =IF(DATA_KO!A42<>"","Q-"&TEXT(41,"000"),"") | B47: =IF(DATA_KO!A42<>"",""&DATA_KO!A42,"") | C47: =IF(A47<>"",""&DATA_KO!H42&"_KO","") | D47: =IF(A47<>"","Candidate: "&DATA_KO!B42,"") | E47: =IF(A47<>"","EO: "&DATA_KO!Q42&", IO: "&DATA_KO!R42,"") | F47: =IF(A47<>"",""&DATA_KO!C42,"") | G47: =IF(A47<>"",DATA_KO!G42,"") | H47: =IF(A47<>"",""&DATA_KO!H42,"") | I47: =IF(A47<>"",""&DATA_KO!I42,"") | J47: =IF(A47<>"","➔ Inspect Item","")
A48: =IF(DATA_KO!A43<>"","Q-"&TEXT(42,"000"),"") | B48: =IF(DATA_KO!A43<>"",""&DATA_KO!A43,"") | C48: =IF(A48<>"",""&DATA_KO!H43&"_KO","") | D48: =IF(A48<>"","Candidate: "&DATA_KO!B43,"") | E48: =IF(A48<>"","EO: "&DATA_KO!Q43&", IO: "&DATA_KO!R43,"") | F48: =IF(A48<>"",""&DATA_KO!C43,"") | G48: =IF(A48<>"",DATA_KO!G43,"") | H48: =IF(A48<>"",""&DATA_KO!H43,"") | I48: =IF(A48<>"",""&DATA_KO!I43,"") | J48: =IF(A48<>"","➔ Inspect Item","")
A49: =IF(DATA_KO!A44<>"","Q-"&TEXT(43,"000"),"") | B49: =IF(DATA_KO!A44<>"",""&DATA_KO!A44,"") | C49: =IF(A49<>"",""&DATA_KO!H44&"_KO","") | D49: =IF(A49<>"","Candidate: "&DATA_KO!B44,"") | E49: =IF(A49<>"","EO: "&DATA_KO!Q44&", IO: "&DATA_KO!R44,"") | F49: =IF(A49<>"",""&DATA_KO!C44,"") | G49: =IF(A49<>"",DATA_KO!G44,"") | H49: =IF(A49<>"",""&DATA_KO!H44,"") | I49: =IF(A49<>"",""&DATA_KO!I44,"") | J49: =IF(A49<>"","➔ Inspect Item","")
A50: =IF(DATA_KO!A45<>"","Q-"&TEXT(44,"000"),"") | B50: =IF(DATA_KO!A45<>"",""&DATA_KO!A45,"") | C50: =IF(A50<>"",""&DATA_KO!H45&"_KO","") | D50: =IF(A50<>"","Candidate: "&DATA_KO!B45,"") | E50: =IF(A50<>"","EO: "&DATA_KO!Q45&", IO: "&DATA_KO!R45,"") | F50: =IF(A50<>"",""&DATA_KO!C45,"") | G50: =IF(A50<>"",DATA_KO!G45,"") | H50: =IF(A50<>"",""&DATA_KO!H45,"") | I50: =IF(A50<>"",""&DATA_KO!I45,"") | J50: =IF(A50<>"","➔ Inspect Item","")
A51: =IF(DATA_KO!A46<>"","Q-"&TEXT(45,"000"),"") | B51: =IF(DATA_KO!A46<>"",""&DATA_KO!A46,"") | C51: =IF(A51<>"",""&DATA_KO!H46&"_KO","") | D51: =IF(A51<>"","Candidate: "&DATA_KO!B46,"") | E51: =IF(A51<>"","EO: "&DATA_KO!Q46&", IO: "&DATA_KO!R46,"") | F51: =IF(A51<>"",""&DATA_KO!C46,"") | G51: =IF(A51<>"",DATA_KO!G46,"") | H51: =IF(A51<>"",""&DATA_KO!H46,"") | I51: =IF(A51<>"",""&DATA_KO!I46,"") | J51: =IF(A51<>"","➔ Inspect Item","")
A52: =IF(DATA_KO!A47<>"","Q-"&TEXT(46,"000"),"") | B52: =IF(DATA_KO!A47<>"",""&DATA_KO!A47,"") | C52: =IF(A52<>"",""&DATA_KO!H47&"_KO","") | D52: =IF(A52<>"","Candidate: "&DATA_KO!B47,"") | E52: =IF(A52<>"","EO: "&DATA_KO!Q47&", IO: "&DATA_KO!R47,"") | F52: =IF(A52<>"",""&DATA_KO!C47,"") | G52: =IF(A52<>"",DATA_KO!G47,"") | H52: =IF(A52<>"",""&DATA_KO!H47,"") | I52: =IF(A52<>"",""&DATA_KO!I47,"") | J52: =IF(A52<>"","➔ Inspect Item","")
A53: =IF(DATA_KO!A48<>"","Q-"&TEXT(47,"000"),"") | B53: =IF(DATA_KO!A48<>"",""&DATA_KO!A48,"") | C53: =IF(A53<>"",""&DATA_KO!H48&"_KO","") | D53: =IF(A53<>"","Candidate: "&DATA_KO!B48,"") | E53: =IF(A53<>"","EO: "&DATA_KO!Q48&", IO: "&DATA_KO!R48,"") | F53: =IF(A53<>"",""&DATA_KO!C48,"") | G53: =IF(A53<>"",DATA_KO!G48,"") | H53: =IF(A53<>"",""&DATA_KO!H48,"") | I53: =IF(A53<>"",""&DATA_KO!I48,"") | J53: =IF(A53<>"","➔ Inspect Item","")
A54: =IF(DATA_KO!A49<>"","Q-"&TEXT(48,"000"),"") | B54: =IF(DATA_KO!A49<>"",""&DATA_KO!A49,"") | C54: =IF(A54<>"",""&DATA_KO!H49&"_KO","") | D54: =IF(A54<>"","Candidate: "&DATA_KO!B49,"") | E54: =IF(A54<>"","EO: "&DATA_KO!Q49&", IO: "&DATA_KO!R49,"") | F54: =IF(A54<>"",""&DATA_KO!C49,"") | G54: =IF(A54<>"",DATA_KO!G49,"") | H54: =IF(A54<>"",""&DATA_KO!H49,"") | I54: =IF(A54<>"",""&DATA_KO!I49,"") | J54: =IF(A54<>"","➔ Inspect Item","")
A55: =IF(DATA_KO!A50<>"","Q-"&TEXT(49,"000"),"") | B55: =IF(DATA_KO!A50<>"",""&DATA_KO!A50,"") | C55: =IF(A55<>"",""&DATA_KO!H50&"_KO","") | D55: =IF(A55<>"","Candidate: "&DATA_KO!B50,"") | E55: =IF(A55<>"","EO: "&DATA_KO!Q50&", IO: "&DATA_KO!R50,"") | F55: =IF(A55<>"",""&DATA_KO!C50,"") | G55: =IF(A55<>"",DATA_KO!G50,"") | H55: =IF(A55<>"",""&DATA_KO!H50,"") | I55: =IF(A55<>"",""&DATA_KO!I50,"") | J55: =IF(A55<>"","➔ Inspect Item","")
A56: =IF(DATA_KO!A51<>"","Q-"&TEXT(50,"000"),"") | B56: =IF(DATA_KO!A51<>"",""&DATA_KO!A51,"") | C56: =IF(A56<>"",""&DATA_KO!H51&"_KO","") | D56: =IF(A56<>"","Candidate: "&DATA_KO!B51,"") | E56: =IF(A56<>"","EO: "&DATA_KO!Q51&", IO: "&DATA_KO!R51,"") | F56: =IF(A56<>"",""&DATA_KO!C51,"") | G56: =IF(A56<>"",DATA_KO!G51,"") | H56: =IF(A56<>"",""&DATA_KO!H51,"") | I56: =IF(A56<>"",""&DATA_KO!I51,"") | J56: =IF(A56<>"","➔ Inspect Item","")
A57: =IF(DATA_KO!A52<>"","Q-"&TEXT(51,"000"),"") | B57: =IF(DATA_KO!A52<>"",""&DATA_KO!A52,"") | C57: =IF(A57<>"",""&DATA_KO!H52&"_KO","") | D57: =IF(A57<>"","Candidate: "&DATA_KO!B52,"") | E57: =IF(A57<>"","EO: "&DATA_KO!Q52&", IO: "&DATA_KO!R52,"") | F57: =IF(A57<>"",""&DATA_KO!C52,"") | G57: =IF(A57<>"",DATA_KO!G52,"") | H57: =IF(A57<>"",""&DATA_KO!H52,"") | I57: =IF(A57<>"",""&DATA_KO!I52,"") | J57: =IF(A57<>"","➔ Inspect Item","")
A58: =IF(DATA_KO!A53<>"","Q-"&TEXT(52,"000"),"") | B58: =IF(DATA_KO!A53<>"",""&DATA_KO!A53,"") | C58: =IF(A58<>"",""&DATA_KO!H53&"_KO","") | D58: =IF(A58<>"","Candidate: "&DATA_KO!B53,"") | E58: =IF(A58<>"","EO: "&DATA_KO!Q53&", IO: "&DATA_KO!R53,"") | F58: =IF(A58<>"",""&DATA_KO!C53,"") | G58: =IF(A58<>"",DATA_KO!G53,"") | H58: =IF(A58<>"",""&DATA_KO!H53,"") | I58: =IF(A58<>"",""&DATA_KO!I53,"") | J58: =IF(A58<>"","➔ Inspect Item","")
A59: =IF(DATA_KO!A54<>"","Q-"&TEXT(53,"000"),"") | B59: =IF(DATA_KO!A54<>"",""&DATA_KO!A54,"") | C59: =IF(A59<>"",""&DATA_KO!H54&"_KO","") | D59: =IF(A59<>"","Candidate: "&DATA_KO!B54,"") | E59: =IF(A59<>"","EO: "&DATA_KO!Q54&", IO: "&DATA_KO!R54,"") | F59: =IF(A59<>"",""&DATA_KO!C54,"") | G59: =IF(A59<>"",DATA_KO!G54,"") | H59: =IF(A59<>"",""&DATA_KO!H54,"") | I59: =IF(A59<>"",""&DATA_KO!I54,"") | J59: =IF(A59<>"","➔ Inspect Item","")
A60: =IF(DATA_KO!A55<>"","Q-"&TEXT(54,"000"),"") | B60: =IF(DATA_KO!A55<>"",""&DATA_KO!A55,"") | C60: =IF(A60<>"",""&DATA_KO!H55&"_KO","") | D60: =IF(A60<>"","Candidate: "&DATA_KO!B55,"") | E60: =IF(A60<>"","EO: "&DATA_KO!Q55&", IO: "&DATA_KO!R55,"") | F60: =IF(A60<>"",""&DATA_KO!C55,"") | G60: =IF(A60<>"",DATA_KO!G55,"") | H60: =IF(A60<>"",""&DATA_KO!H55,"") | I60: =IF(A60<>"",""&DATA_KO!I55,"") | J60: =IF(A60<>"","➔ Inspect Item","")
A61: =IF(DATA_KO!A56<>"","Q-"&TEXT(55,"000"),"") | B61: =IF(DATA_KO!A56<>"",""&DATA_KO!A56,"") | C61: =IF(A61<>"",""&DATA_KO!H56&"_KO","") | D61: =IF(A61<>"","Candidate: "&DATA_KO!B56,"") | E61: =IF(A61<>"","EO: "&DATA_KO!Q56&", IO: "&DATA_KO!R56,"") | F61: =IF(A61<>"",""&DATA_KO!C56,"") | G61: =IF(A61<>"",DATA_KO!G56,"") | H61: =IF(A61<>"",""&DATA_KO!H56,"") | I61: =IF(A61<>"",""&DATA_KO!I56,"") | J61: =IF(A61<>"","➔ Inspect Item","")
A62: =IF(DATA_KO!A57<>"","Q-"&TEXT(56,"000"),"") | B62: =IF(DATA_KO!A57<>"",""&DATA_KO!A57,"") | C62: =IF(A62<>"",""&DATA_KO!H57&"_KO","") | D62: =IF(A62<>"","Candidate: "&DATA_KO!B57,"") | E62: =IF(A62<>"","EO: "&DATA_KO!Q57&", IO: "&DATA_KO!R57,"") | F62: =IF(A62<>"",""&DATA_KO!C57,"") | G62: =IF(A62<>"",DATA_KO!G57,"") | H62: =IF(A62<>"",""&DATA_KO!H57,"") | I62: =IF(A62<>"",""&DATA_KO!I57,"") | J62: =IF(A62<>"","➔ Inspect Item","")
A63: =IF(DATA_KO!A58<>"","Q-"&TEXT(57,"000"),"") | B63: =IF(DATA_KO!A58<>"",""&DATA_KO!A58,"") | C63: =IF(A63<>"",""&DATA_KO!H58&"_KO","") | D63: =IF(A63<>"","Candidate: "&DATA_KO!B58,"") | E63: =IF(A63<>"","EO: "&DATA_KO!Q58&", IO: "&DATA_KO!R58,"") | F63: =IF(A63<>"",""&DATA_KO!C58,"") | G63: =IF(A63<>"",DATA_KO!G58,"") | H63: =IF(A63<>"",""&DATA_KO!H58,"") | I63: =IF(A63<>"",""&DATA_KO!I58,"") | J63: =IF(A63<>"","➔ Inspect Item","")
A64: =IF(DATA_KO!A59<>"","Q-"&TEXT(58,"000"),"") | B64: =IF(DATA_KO!A59<>"",""&DATA_KO!A59,"") | C64: =IF(A64<>"",""&DATA_KO!H59&"_KO","") | D64: =IF(A64<>"","Candidate: "&DATA_KO!B59,"") | E64: =IF(A64<>"","EO: "&DATA_KO!Q59&", IO: "&DATA_KO!R59,"") | F64: =IF(A64<>"",""&DATA_KO!C59,"") | G64: =IF(A64<>"",DATA_KO!G59,"") | H64: =IF(A64<>"",""&DATA_KO!H59,"") | I64: =IF(A64<>"",""&DATA_KO!I59,"") | J64: =IF(A64<>"","➔ Inspect Item","")
A65: =IF(DATA_KO!A60<>"","Q-"&TEXT(59,"000"),"") | B65: =IF(DATA_KO!A60<>"",""&DATA_KO!A60,"") | C65: =IF(A65<>"",""&DATA_KO!H60&"_KO","") | D65: =IF(A65<>"","Candidate: "&DATA_KO!B60,"") | E65: =IF(A65<>"","EO: "&DATA_KO!Q60&", IO: "&DATA_KO!R60,"") | F65: =IF(A65<>"",""&DATA_KO!C60,"") | G65: =IF(A65<>"",DATA_KO!G60,"") | H65: =IF(A65<>"",""&DATA_KO!H60,"") | I65: =IF(A65<>"",""&DATA_KO!I60,"") | J65: =IF(A65<>"","➔ Inspect Item","")
A66: =IF(DATA_KO!A61<>"","Q-"&TEXT(60,"000"),"") | B66: =IF(DATA_KO!A61<>"",""&DATA_KO!A61,"") | C66: =IF(A66<>"",""&DATA_KO!H61&"_KO","") | D66: =IF(A66<>"","Candidate: "&DATA_KO!B61,"") | E66: =IF(A66<>"","EO: "&DATA_KO!Q61&", IO: "&DATA_KO!R61,"") | F66: =IF(A66<>"",""&DATA_KO!C61,"") | G66: =IF(A66<>"",DATA_KO!G61,"") | H66: =IF(A66<>"",""&DATA_KO!H61,"") | I66: =IF(A66<>"",""&DATA_KO!I61,"") | J66: =IF(A66<>"","➔ Inspect Item","")
A67: =IF(DATA_KO!A62<>"","Q-"&TEXT(61,"000"),"") | B67: =IF(DATA_KO!A62<>"",""&DATA_KO!A62,"") | C67: =IF(A67<>"",""&DATA_KO!H62&"_KO","") | D67: =IF(A67<>"","Candidate: "&DATA_KO!B62,"") | E67: =IF(A67<>"","EO: "&DATA_KO!Q62&", IO: "&DATA_KO!R62,"") | F67: =IF(A67<>"",""&DATA_KO!C62,"") | G67: =IF(A67<>"",DATA_KO!G62,"") | H67: =IF(A67<>"",""&DATA_KO!H62,"") | I67: =IF(A67<>"",""&DATA_KO!I62,"") | J67: =IF(A67<>"","➔ Inspect Item","")
A68: =IF(DATA_KO!A63<>"","Q-"&TEXT(62,"000"),"") | B68: =IF(DATA_KO!A63<>"",""&DATA_KO!A63,"") | C68: =IF(A68<>"",""&DATA_KO!H63&"_KO","") | D68: =IF(A68<>"","Candidate: "&DATA_KO!B63,"") | E68: =IF(A68<>"","EO: "&DATA_KO!Q63&", IO: "&DATA_KO!R63,"") | F68: =IF(A68<>"",""&DATA_KO!C63,"") | G68: =IF(A68<>"",DATA_KO!G63,"") | H68: =IF(A68<>"",""&DATA_KO!H63,"") | I68: =IF(A68<>"",""&DATA_KO!I63,"") | J68: =IF(A68<>"","➔ Inspect Item","")
A69: =IF(DATA_KO!A64<>"","Q-"&TEXT(63,"000"),"") | B69: =IF(DATA_KO!A64<>"",""&DATA_KO!A64,"") | C69: =IF(A69<>"",""&DATA_KO!H64&"_KO","") | D69: =IF(A69<>"","Candidate: "&DATA_KO!B64,"") | E69: =IF(A69<>"","EO: "&DATA_KO!Q64&", IO: "&DATA_KO!R64,"") | F69: =IF(A69<>"",""&DATA_KO!C64,"") | G69: =IF(A69<>"",DATA_KO!G64,"") | H69: =IF(A69<>"",""&DATA_KO!H64,"") | I69: =IF(A69<>"",""&DATA_KO!I64,"") | J69: =IF(A69<>"","➔ Inspect Item","")
A70: =IF(DATA_KO!A65<>"","Q-"&TEXT(64,"000"),"") | B70: =IF(DATA_KO!A65<>"",""&DATA_KO!A65,"") | C70: =IF(A70<>"",""&DATA_KO!H65&"_KO","") | D70: =IF(A70<>"","Candidate: "&DATA_KO!B65,"") | E70: =IF(A70<>"","EO: "&DATA_KO!Q65&", IO: "&DATA_KO!R65,"") | F70: =IF(A70<>"",""&DATA_KO!C65,"") | G70: =IF(A70<>"",DATA_KO!G65,"") | H70: =IF(A70<>"",""&DATA_KO!H65,"") | I70: =IF(A70<>"",""&DATA_KO!I65,"") | J70: =IF(A70<>"","➔ Inspect Item","")
A71: =IF(DATA_KO!A66<>"","Q-"&TEXT(65,"000"),"") | B71: =IF(DATA_KO!A66<>"",""&DATA_KO!A66,"") | C71: =IF(A71<>"",""&DATA_KO!H66&"_KO","") | D71: =IF(A71<>"","Candidate: "&DATA_KO!B66,"") | E71: =IF(A71<>"","EO: "&DATA_KO!Q66&", IO: "&DATA_KO!R66,"") | F71: =IF(A71<>"",""&DATA_KO!C66,"") | G71: =IF(A71<>"",DATA_KO!G66,"") | H71: =IF(A71<>"",""&DATA_KO!H66,"") | I71: =IF(A71<>"",""&DATA_KO!I66,"") | J71: =IF(A71<>"","➔ Inspect Item","")
A72: =IF(DATA_KO!A67<>"","Q-"&TEXT(66,"000"),"") | B72: =IF(DATA_KO!A67<>"",""&DATA_KO!A67,"") | C72: =IF(A72<>"",""&DATA_KO!H67&"_KO","") | D72: =IF(A72<>"","Candidate: "&DATA_KO!B67,"") | E72: =IF(A72<>"","EO: "&DATA_KO!Q67&", IO: "&DATA_KO!R67,"") | F72: =IF(A72<>"",""&DATA_KO!C67,"") | G72: =IF(A72<>"",DATA_KO!G67,"") | H72: =IF(A72<>"",""&DATA_KO!H67,"") | I72: =IF(A72<>"",""&DATA_KO!I67,"") | J72: =IF(A72<>"","➔ Inspect Item","")
A73: =IF(DATA_KO!A68<>"","Q-"&TEXT(67,"000"),"") | B73: =IF(DATA_KO!A68<>"",""&DATA_KO!A68,"") | C73: =IF(A73<>"",""&DATA_KO!H68&"_KO","") | D73: =IF(A73<>"","Candidate: "&DATA_KO!B68,"") | E73: =IF(A73<>"","EO: "&DATA_KO!Q68&", IO: "&DATA_KO!R68,"") | F73: =IF(A73<>"",""&DATA_KO!C68,"") | G73: =IF(A73<>"",DATA_KO!G68,"") | H73: =IF(A73<>"",""&DATA_KO!H68,"") | I73: =IF(A73<>"",""&DATA_KO!I68,"") | J73: =IF(A73<>"","➔ Inspect Item","")
A74: =IF(DATA_KO!A69<>"","Q-"&TEXT(68,"000"),"") | B74: =IF(DATA_KO!A69<>"",""&DATA_KO!A69,"") | C74: =IF(A74<>"",""&DATA_KO!H69&"_KO","") | D74: =IF(A74<>"","Candidate: "&DATA_KO!B69,"") | E74: =IF(A74<>"","EO: "&DATA_KO!Q69&", IO: "&DATA_KO!R69,"") | F74: =IF(A74<>"",""&DATA_KO!C69,"") | G74: =IF(A74<>"",DATA_KO!G69,"") | H74: =IF(A74<>"",""&DATA_KO!H69,"") | I74: =IF(A74<>"",""&DATA_KO!I69,"") | J74: =IF(A74<>"","➔ Inspect Item","")
A75: =IF(DATA_KO!A70<>"","Q-"&TEXT(69,"000"),"") | B75: =IF(DATA_KO!A70<>"",""&DATA_KO!A70,"") | C75: =IF(A75<>"",""&DATA_KO!H70&"_KO","") | D75: =IF(A75<>"","Candidate: "&DATA_KO!B70,"") | E75: =IF(A75<>"","EO: "&DATA_KO!Q70&", IO: "&DATA_KO!R70,"") | F75: =IF(A75<>"",""&DATA_KO!C70,"") | G75: =IF(A75<>"",DATA_KO!G70,"") | H75: =IF(A75<>"",""&DATA_KO!H70,"") | I75: =IF(A75<>"",""&DATA_KO!I70,"") | J75: =IF(A75<>"","➔ Inspect Item","")
A76: =IF(DATA_KO!A71<>"","Q-"&TEXT(70,"000"),"") | B76: =IF(DATA_KO!A71<>"",""&DATA_KO!A71,"") | C76: =IF(A76<>"",""&DATA_KO!H71&"_KO","") | D76: =IF(A76<>"","Candidate: "&DATA_KO!B71,"") | E76: =IF(A76<>"","EO: "&DATA_KO!Q71&", IO: "&DATA_KO!R71,"") | F76: =IF(A76<>"",""&DATA_KO!C71,"") | G76: =IF(A76<>"",DATA_KO!G71,"") | H76: =IF(A76<>"",""&DATA_KO!H71,"") | I76: =IF(A76<>"",""&DATA_KO!I71,"") | J76: =IF(A76<>"","➔ Inspect Item","")
A77: =IF(DATA_KO!A72<>"","Q-"&TEXT(71,"000"),"") | B77: =IF(DATA_KO!A72<>"",""&DATA_KO!A72,"") | C77: =IF(A77<>"",""&DATA_KO!H72&"_KO","") | D77: =IF(A77<>"","Candidate: "&DATA_KO!B72,"") | E77: =IF(A77<>"","EO: "&DATA_KO!Q72&", IO: "&DATA_KO!R72,"") | F77: =IF(A77<>"",""&DATA_KO!C72,"") | G77: =IF(A77<>"",DATA_KO!G72,"") | H77: =IF(A77<>"",""&DATA_KO!H72,"") | I77: =IF(A77<>"",""&DATA_KO!I72,"") | J77: =IF(A77<>"","➔ Inspect Item","")
A78: =IF(DATA_KO!A73<>"","Q-"&TEXT(72,"000"),"") | B78: =IF(DATA_KO!A73<>"",""&DATA_KO!A73,"") | C78: =IF(A78<>"",""&DATA_KO!H73&"_KO","") | D78: =IF(A78<>"","Candidate: "&DATA_KO!B73,"") | E78: =IF(A78<>"","EO: "&DATA_KO!Q73&", IO: "&DATA_KO!R73,"") | F78: =IF(A78<>"",""&DATA_KO!C73,"") | G78: =IF(A78<>"",DATA_KO!G73,"") | H78: =IF(A78<>"",""&DATA_KO!H73,"") | I78: =IF(A78<>"",""&DATA_KO!I73,"") | J78: =IF(A78<>"","➔ Inspect Item","")
A79: =IF(DATA_KO!A74<>"","Q-"&TEXT(73,"000"),"") | B79: =IF(DATA_KO!A74<>"",""&DATA_KO!A74,"") | C79: =IF(A79<>"",""&DATA_KO!H74&"_KO","") | D79: =IF(A79<>"","Candidate: "&DATA_KO!B74,"") | E79: =IF(A79<>"","EO: "&DATA_KO!Q74&", IO: "&DATA_KO!R74,"") | F79: =IF(A79<>"",""&DATA_KO!C74,"") | G79: =IF(A79<>"",DATA_KO!G74,"") | H79: =IF(A79<>"",""&DATA_KO!H74,"") | I79: =IF(A79<>"",""&DATA_KO!I74,"") | J79: =IF(A79<>"","➔ Inspect Item","")
A80: =IF(DATA_KO!A75<>"","Q-"&TEXT(74,"000"),"") | B80: =IF(DATA_KO!A75<>"",""&DATA_KO!A75,"") | C80: =IF(A80<>"",""&DATA_KO!H75&"_KO","") | D80: =IF(A80<>"","Candidate: "&DATA_KO!B75,"") | E80: =IF(A80<>"","EO: "&DATA_KO!Q75&", IO: "&DATA_KO!R75,"") | F80: =IF(A80<>"",""&DATA_KO!C75,"") | G80: =IF(A80<>"",DATA_KO!G75,"") | H80: =IF(A80<>"",""&DATA_KO!H75,"") | I80: =IF(A80<>"",""&DATA_KO!I75,"") | J80: =IF(A80<>"","➔ Inspect Item","")
A81: =IF(DATA_KO!A76<>"","Q-"&TEXT(75,"000"),"") | B81: =IF(DATA_KO!A76<>"",""&DATA_KO!A76,"") | C81: =IF(A81<>"",""&DATA_KO!H76&"_KO","") | D81: =IF(A81<>"","Candidate: "&DATA_KO!B76,"") | E81: =IF(A81<>"","EO: "&DATA_KO!Q76&", IO: "&DATA_KO!R76,"") | F81: =IF(A81<>"",""&DATA_KO!C76,"") | G81: =IF(A81<>"",DATA_KO!G76,"") | H81: =IF(A81<>"",""&DATA_KO!H76,"") | I81: =IF(A81<>"",""&DATA_KO!I76,"") | J81: =IF(A81<>"","➔ Inspect Item","")
A82: =IF(DATA_KO!A77<>"","Q-"&TEXT(76,"000"),"") | B82: =IF(DATA_KO!A77<>"",""&DATA_KO!A77,"") | C82: =IF(A82<>"",""&DATA_KO!H77&"_KO","") | D82: =IF(A82<>"","Candidate: "&DATA_KO!B77,"") | E82: =IF(A82<>"","EO: "&DATA_KO!Q77&", IO: "&DATA_KO!R77,"") | F82: =IF(A82<>"",""&DATA_KO!C77,"") | G82: =IF(A82<>"",DATA_KO!G77,"") | H82: =IF(A82<>"",""&DATA_KO!H77,"") | I82: =IF(A82<>"",""&DATA_KO!I77,"") | J82: =IF(A82<>"","➔ Inspect Item","")
A83: =IF(DATA_KO!A78<>"","Q-"&TEXT(77,"000"),"") | B83: =IF(DATA_KO!A78<>"",""&DATA_KO!A78,"") | C83: =IF(A83<>"",""&DATA_KO!H78&"_KO","") | D83: =IF(A83<>"","Candidate: "&DATA_KO!B78,"") | E83: =IF(A83<>"","EO: "&DATA_KO!Q78&", IO: "&DATA_KO!R78,"") | F83: =IF(A83<>"",""&DATA_KO!C78,"") | G83: =IF(A83<>"",DATA_KO!G78,"") | H83: =IF(A83<>"",""&DATA_KO!H78,"") | I83: =IF(A83<>"",""&DATA_KO!I78,"") | J83: =IF(A83<>"","➔ Inspect Item","")
A84: =IF(DATA_KO!A79<>"","Q-"&TEXT(78,"000"),"") | B84: =IF(DATA_KO!A79<>"",""&DATA_KO!A79,"") | C84: =IF(A84<>"",""&DATA_KO!H79&"_KO","") | D84: =IF(A84<>"","Candidate: "&DATA_KO!B79,"") | E84: =IF(A84<>"","EO: "&DATA_KO!Q79&", IO: "&DATA_KO!R79,"") | F84: =IF(A84<>"",""&DATA_KO!C79,"") | G84: =IF(A84<>"",DATA_KO!G79,"") | H84: =IF(A84<>"",""&DATA_KO!H79,"") | I84: =IF(A84<>"",""&DATA_KO!I79,"") | J84: =IF(A84<>"","➔ Inspect Item","")
A85: =IF(DATA_KO!A80<>"","Q-"&TEXT(79,"000"),"") | B85: =IF(DATA_KO!A80<>"",""&DATA_KO!A80,"") | C85: =IF(A85<>"",""&DATA_KO!H80&"_KO","") | D85: =IF(A85<>"","Candidate: "&DATA_KO!B80,"") | E85: =IF(A85<>"","EO: "&DATA_KO!Q80&", IO: "&DATA_KO!R80,"") | F85: =IF(A85<>"",""&DATA_KO!C80,"") | G85: =IF(A85<>"",DATA_KO!G80,"") | H85: =IF(A85<>"",""&DATA_KO!H80,"") | I85: =IF(A85<>"",""&DATA_KO!I80,"") | J85: =IF(A85<>"","➔ Inspect Item","")
A86: =IF(DATA_KO!A81<>"","Q-"&TEXT(80,"000"),"") | B86: =IF(DATA_KO!A81<>"",""&DATA_KO!A81,"") | C86: =IF(A86<>"",""&DATA_KO!H81&"_KO","") | D86: =IF(A86<>"","Candidate: "&DATA_KO!B81,"") | E86: =IF(A86<>"","EO: "&DATA_KO!Q81&", IO: "&DATA_KO!R81,"") | F86: =IF(A86<>"",""&DATA_KO!C81,"") | G86: =IF(A86<>"",DATA_KO!G81,"") | H86: =IF(A86<>"",""&DATA_KO!H81,"") | I86: =IF(A86<>"",""&DATA_KO!I81,"") | J86: =IF(A86<>"","➔ Inspect Item","")
A87: =IF(DATA_KO!A82<>"","Q-"&TEXT(81,"000"),"") | B87: =IF(DATA_KO!A82<>"",""&DATA_KO!A82,"") | C87: =IF(A87<>"",""&DATA_KO!H82&"_KO","") | D87: =IF(A87<>"","Candidate: "&DATA_KO!B82,"") | E87: =IF(A87<>"","EO: "&DATA_KO!Q82&", IO: "&DATA_KO!R82,"") | F87: =IF(A87<>"",""&DATA_KO!C82,"") | G87: =IF(A87<>"",DATA_KO!G82,"") | H87: =IF(A87<>"",""&DATA_KO!H82,"") | I87: =IF(A87<>"",""&DATA_KO!I82,"") | J87: =IF(A87<>"","➔ Inspect Item","")
A88: =IF(DATA_KO!A83<>"","Q-"&TEXT(82,"000"),"") | B88: =IF(DATA_KO!A83<>"",""&DATA_KO!A83,"") | C88: =IF(A88<>"",""&DATA_KO!H83&"_KO","") | D88: =IF(A88<>"","Candidate: "&DATA_KO!B83,"") | E88: =IF(A88<>"","EO: "&DATA_KO!Q83&", IO: "&DATA_KO!R83,"") | F88: =IF(A88<>"",""&DATA_KO!C83,"") | G88: =IF(A88<>"",DATA_KO!G83,"") | H88: =IF(A88<>"",""&DATA_KO!H83,"") | I88: =IF(A88<>"",""&DATA_KO!I83,"") | J88: =IF(A88<>"","➔ Inspect Item","")
A89: =IF(DATA_KO!A84<>"","Q-"&TEXT(83,"000"),"") | B89: =IF(DATA_KO!A84<>"",""&DATA_KO!A84,"") | C89: =IF(A89<>"",""&DATA_KO!H84&"_KO","") | D89: =IF(A89<>"","Candidate: "&DATA_KO!B84,"") | E89: =IF(A89<>"","EO: "&DATA_KO!Q84&", IO: "&DATA_KO!R84,"") | F89: =IF(A89<>"",""&DATA_KO!C84,"") | G89: =IF(A89<>"",DATA_KO!G84,"") | H89: =IF(A89<>"",""&DATA_KO!H84,"") | I89: =IF(A89<>"",""&DATA_KO!I84,"") | J89: =IF(A89<>"","➔ Inspect Item","")
A90: =IF(DATA_KO!A85<>"","Q-"&TEXT(84,"000"),"") | B90: =IF(DATA_KO!A85<>"",""&DATA_KO!A85,"") | C90: =IF(A90<>"",""&DATA_KO!H85&"_KO","") | D90: =IF(A90<>"","Candidate: "&DATA_KO!B85,"") | E90: =IF(A90<>"","EO: "&DATA_KO!Q85&", IO: "&DATA_KO!R85,"") | F90: =IF(A90<>"",""&DATA_KO!C85,"") | G90: =IF(A90<>"",DATA_KO!G85,"") | H90: =IF(A90<>"",""&DATA_KO!H85,"") | I90: =IF(A90<>"",""&DATA_KO!I85,"") | J90: =IF(A90<>"","➔ Inspect Item","")
A91: =IF(DATA_KO!A86<>"","Q-"&TEXT(85,"000"),"") | B91: =IF(DATA_KO!A86<>"",""&DATA_KO!A86,"") | C91: =IF(A91<>"",""&DATA_KO!H86&"_KO","") | D91: =IF(A91<>"","Candidate: "&DATA_KO!B86,"") | E91: =IF(A91<>"","EO: "&DATA_KO!Q86&", IO: "&DATA_KO!R86,"") | F91: =IF(A91<>"",""&DATA_KO!C86,"") | G91: =IF(A91<>"",DATA_KO!G86,"") | H91: =IF(A91<>"",""&DATA_KO!H86,"") | I91: =IF(A91<>"",""&DATA_KO!I86,"") | J91: =IF(A91<>"","➔ Inspect Item","")
A92: =IF(DATA_KO!A87<>"","Q-"&TEXT(86,"000"),"") | B92: =IF(DATA_KO!A87<>"",""&DATA_KO!A87,"") | C92: =IF(A92<>"",""&DATA_KO!H87&"_KO","") | D92: =IF(A92<>"","Candidate: "&DATA_KO!B87,"") | E92: =IF(A92<>"","EO: "&DATA_KO!Q87&", IO: "&DATA_KO!R87,"") | F92: =IF(A92<>"",""&DATA_KO!C87,"") | G92: =IF(A92<>"",DATA_KO!G87,"") | H92: =IF(A92<>"",""&DATA_KO!H87,"") | I92: =IF(A92<>"",""&DATA_KO!I87,"") | J92: =IF(A92<>"","➔ Inspect Item","")
A93: =IF(DATA_KO!A88<>"","Q-"&TEXT(87,"000"),"") | B93: =IF(DATA_KO!A88<>"",""&DATA_KO!A88,"") | C93: =IF(A93<>"",""&DATA_KO!H88&"_KO","") | D93: =IF(A93<>"","Candidate: "&DATA_KO!B88,"") | E93: =IF(A93<>"","EO: "&DATA_KO!Q88&", IO: "&DATA_KO!R88,"") | F93: =IF(A93<>"",""&DATA_KO!C88,"") | G93: =IF(A93<>"",DATA_KO!G88,"") | H93: =IF(A93<>"",""&DATA_KO!H88,"") | I93: =IF(A93<>"",""&DATA_KO!I88,"") | J93: =IF(A93<>"","➔ Inspect Item","")
A94: =IF(DATA_KO!A89<>"","Q-"&TEXT(88,"000"),"") | B94: =IF(DATA_KO!A89<>"",""&DATA_KO!A89,"") | C94: =IF(A94<>"",""&DATA_KO!H89&"_KO","") | D94: =IF(A94<>"","Candidate: "&DATA_KO!B89,"") | E94: =IF(A94<>"","EO: "&DATA_KO!Q89&", IO: "&DATA_KO!R89,"") | F94: =IF(A94<>"",""&DATA_KO!C89,"") | G94: =IF(A94<>"",DATA_KO!G89,"") | H94: =IF(A94<>"",""&DATA_KO!H89,"") | I94: =IF(A94<>"",""&DATA_KO!I89,"") | J94: =IF(A94<>"","➔ Inspect Item","")
A95: =IF(DATA_KO!A90<>"","Q-"&TEXT(89,"000"),"") | B95: =IF(DATA_KO!A90<>"",""&DATA_KO!A90,"") | C95: =IF(A95<>"",""&DATA_KO!H90&"_KO","") | D95: =IF(A95<>"","Candidate: "&DATA_KO!B90,"") | E95: =IF(A95<>"","EO: "&DATA_KO!Q90&", IO: "&DATA_KO!R90,"") | F95: =IF(A95<>"",""&DATA_KO!C90,"") | G95: =IF(A95<>"",DATA_KO!G90,"") | H95: =IF(A95<>"",""&DATA_KO!H90,"") | I95: =IF(A95<>"",""&DATA_KO!I90,"") | J95: =IF(A95<>"","➔ Inspect Item","")
A96: =IF(DATA_KO!A91<>"","Q-"&TEXT(90,"000"),"") | B96: =IF(DATA_KO!A91<>"",""&DATA_KO!A91,"") | C96: =IF(A96<>"",""&DATA_KO!H91&"_KO","") | D96: =IF(A96<>"","Candidate: "&DATA_KO!B91,"") | E96: =IF(A96<>"","EO: "&DATA_KO!Q91&", IO: "&DATA_KO!R91,"") | F96: =IF(A96<>"",""&DATA_KO!C91,"") | G96: =IF(A96<>"",DATA_KO!G91,"") | H96: =IF(A96<>"",""&DATA_KO!H91,"") | I96: =IF(A96<>"",""&DATA_KO!I91,"") | J96: =IF(A96<>"","➔ Inspect Item","")
A97: =IF(DATA_KO!A92<>"","Q-"&TEXT(91,"000"),"") | B97: =IF(DATA_KO!A92<>"",""&DATA_KO!A92,"") | C97: =IF(A97<>"",""&DATA_KO!H92&"_KO","") | D97: =IF(A97<>"","Candidate: "&DATA_KO!B92,"") | E97: =IF(A97<>"","EO: "&DATA_KO!Q92&", IO: "&DATA_KO!R92,"") | F97: =IF(A97<>"",""&DATA_KO!C92,"") | G97: =IF(A97<>"",DATA_KO!G92,"") | H97: =IF(A97<>"",""&DATA_KO!H92,"") | I97: =IF(A97<>"",""&DATA_KO!I92,"") | J97: =IF(A97<>"","➔ Inspect Item","")
A98: =IF(DATA_KO!A93<>"","Q-"&TEXT(92,"000"),"") | B98: =IF(DATA_KO!A93<>"",""&DATA_KO!A93,"") | C98: =IF(A98<>"",""&DATA_KO!H93&"_KO","") | D98: =IF(A98<>"","Candidate: "&DATA_KO!B93,"") | E98: =IF(A98<>"","EO: "&DATA_KO!Q93&", IO: "&DATA_KO!R93,"") | F98: =IF(A98<>"",""&DATA_KO!C93,"") | G98: =IF(A98<>"",DATA_KO!G93,"") | H98: =IF(A98<>"",""&DATA_KO!H93,"") | I98: =IF(A98<>"",""&DATA_KO!I93,"") | J98: =IF(A98<>"","➔ Inspect Item","")
A99: =IF(DATA_KO!A94<>"","Q-"&TEXT(93,"000"),"") | B99: =IF(DATA_KO!A94<>"",""&DATA_KO!A94,"") | C99: =IF(A99<>"",""&DATA_KO!H94&"_KO","") | D99: =IF(A99<>"","Candidate: "&DATA_KO!B94,"") | E99: =IF(A99<>"","EO: "&DATA_KO!Q94&", IO: "&DATA_KO!R94,"") | F99: =IF(A99<>"",""&DATA_KO!C94,"") | G99: =IF(A99<>"",DATA_KO!G94,"") | H99: =IF(A99<>"",""&DATA_KO!H94,"") | I99: =IF(A99<>"",""&DATA_KO!I94,"") | J99: =IF(A99<>"","➔ Inspect Item","")
A100: =IF(DATA_KO!A95<>"","Q-"&TEXT(94,"000"),"") | B100: =IF(DATA_KO!A95<>"",""&DATA_KO!A95,"") | C100: =IF(A100<>"",""&DATA_KO!H95&"_KO","") | D100: =IF(A100<>"","Candidate: "&DATA_KO!B95,"") | E100: =IF(A100<>"","EO: "&DATA_KO!Q95&", IO: "&DATA_KO!R95,"") | F100: =IF(A100<>"",""&DATA_KO!C95,"") | G100: =IF(A100<>"",DATA_KO!G95,"") | H100: =IF(A100<>"",""&DATA_KO!H95,"") | I100: =IF(A100<>"",""&DATA_KO!I95,"") | J100: =IF(A100<>"","➔ Inspect Item","")
A101: =IF(DATA_KO!A96<>"","Q-"&TEXT(95,"000"),"") | B101: =IF(DATA_KO!A96<>"",""&DATA_KO!A96,"") | C101: =IF(A101<>"",""&DATA_KO!H96&"_KO","") | D101: =IF(A101<>"","Candidate: "&DATA_KO!B96,"") | E101: =IF(A101<>"","EO: "&DATA_KO!Q96&", IO: "&DATA_KO!R96,"") | F101: =IF(A101<>"",""&DATA_KO!C96,"") | G101: =IF(A101<>"",DATA_KO!G96,"") | H101: =IF(A101<>"",""&DATA_KO!H96,"") | I101: =IF(A101<>"",""&DATA_KO!I96,"") | J101: =IF(A101<>"","➔ Inspect Item","")
A102: =IF(DATA_KO!A97<>"","Q-"&TEXT(96,"000"),"") | B102: =IF(DATA_KO!A97<>"",""&DATA_KO!A97,"") | C102: =IF(A102<>"",""&DATA_KO!H97&"_KO","") | D102: =IF(A102<>"","Candidate: "&DATA_KO!B97,"") | E102: =IF(A102<>"","EO: "&DATA_KO!Q97&", IO: "&DATA_KO!R97,"") | F102: =IF(A102<>"",""&DATA_KO!C97,"") | G102: =IF(A102<>"",DATA_KO!G97,"") | H102: =IF(A102<>"",""&DATA_KO!H97,"") | I102: =IF(A102<>"",""&DATA_KO!I97,"") | J102: =IF(A102<>"","➔ Inspect Item","")
...

Sheet 06_Provenance_Register
A1: RESEARCH INTELLIGENCE ENGINE (RIE) — PROVENANCE REGISTER | G1: =HYPERLINK("#'01_Executive_Dashboard'!A1", "⮌ BACK TO DASHBOARD")
A2: ="Cryptographic Provenance, Content Hashes & Immutable Audit Trail (" & COUNTA(DATA_PROVENANCE!A2:A100) & " Assets) | Level 5 Human Custody"
A4: Asset_ID | B4: Asset_Type | C4: Canonical_Path | D4: SHA256_Checksum | E4: Record_Count | F4: Last_Verified_UTC | G4: Integrity_Status
A5: =IF(DATA_PROVENANCE!A2<>"",""&DATA_PROVENANCE!A2,"") | B5: =IF(A5<>"",""&DATA_PROVENANCE!B2,"") | C5: =IF(A5<>"",""&DATA_PROVENANCE!C2,"") | D5: =IF(A5<>"",""&DATA_PROVENANCE!D2,"") | E5: =IF(A5<>"",DATA_PROVENANCE!E2,"") | F5: =IF(A5<>"",""&DATA_PROVENANCE!F2,"") | G5: =IF(A5<>"",""&DATA_PROVENANCE!G2,"")
A6: =IF(DATA_PROVENANCE!A3<>"",""&DATA_PROVENANCE!A3,"") | B6: =IF(A6<>"",""&DATA_PROVENANCE!B3,"") | C6: =IF(A6<>"",""&DATA_PROVENANCE!C3,"") | D6: =IF(A6<>"",""&DATA_PROVENANCE!D3,"") | E6: =IF(A6<>"",DATA_PROVENANCE!E3,"") | F6: =IF(A6<>"",""&DATA_PROVENANCE!F3,"") | G6: =IF(A6<>"",""&DATA_PROVENANCE!G3,"")
A7: =IF(DATA_PROVENANCE!A4<>"",""&DATA_PROVENANCE!A4,"") | B7: =IF(A7<>"",""&DATA_PROVENANCE!B4,"") | C7: =IF(A7<>"",""&DATA_PROVENANCE!C4,"") | D7: =IF(A7<>"",""&DATA_PROVENANCE!D4,"") | E7: =IF(A7<>"",DATA_PROVENANCE!E4,"") | F7: =IF(A7<>"",""&DATA_PROVENANCE!F4,"") | G7: =IF(A7<>"",""&DATA_PROVENANCE!G4,"")
A8: =IF(DATA_PROVENANCE!A5<>"",""&DATA_PROVENANCE!A5,"") | B8: =IF(A8<>"",""&DATA_PROVENANCE!B5,"") | C8: =IF(A8<>"",""&DATA_PROVENANCE!C5,"") | D8: =IF(A8<>"",""&DATA_PROVENANCE!D5,"") | E8: =IF(A8<>"",DATA_PROVENANCE!E5,"") | F8: =IF(A8<>"",""&DATA_PROVENANCE!F5,"") | G8: =IF(A8<>"",""&DATA_PROVENANCE!G5,"")
A9: =IF(DATA_PROVENANCE!A6<>"",""&DATA_PROVENANCE!A6,"") | B9: =IF(A9<>"",""&DATA_PROVENANCE!B6,"") | C9: =IF(A9<>"",""&DATA_PROVENANCE!C6,"") | D9: =IF(A9<>"",""&DATA_PROVENANCE!D6,"") | E9: =IF(A9<>"",DATA_PROVENANCE!E6,"") | F9: =IF(A9<>"",""&DATA_PROVENANCE!F6,"") | G9: =IF(A9<>"",""&DATA_PROVENANCE!G6,"")
A10: =IF(DATA_PROVENANCE!A7<>"",""&DATA_PROVENANCE!A7,"") | B10: =IF(A10<>"",""&DATA_PROVENANCE!B7,"") | C10: =IF(A10<>"",""&DATA_PROVENANCE!C7,"") | D10: =IF(A10<>"",""&DATA_PROVENANCE!D7,"") | E10: =IF(A10<>"",DATA_PROVENANCE!E7,"") | F10: =IF(A10<>"",""&DATA_PROVENANCE!F7,"") | G10: =IF(A10<>"",""&DATA_PROVENANCE!G7,"")
A11: =IF(DATA_PROVENANCE!A8<>"",""&DATA_PROVENANCE!A8,"") | B11: =IF(A11<>"",""&DATA_PROVENANCE!B8,"") | C11: =IF(A11<>"",""&DATA_PROVENANCE!C8,"") | D11: =IF(A11<>"",""&DATA_PROVENANCE!D8,"") | E11: =IF(A11<>"",DATA_PROVENANCE!E8,"") | F11: =IF(A11<>"",""&DATA_PROVENANCE!F8,"") | G11: =IF(A11<>"",""&DATA_PROVENANCE!G8,"")
A12: =IF(DATA_PROVENANCE!A9<>"",""&DATA_PROVENANCE!A9,"") | B12: =IF(A12<>"",""&DATA_PROVENANCE!B9,"") | C12: =IF(A12<>"",""&DATA_PROVENANCE!C9,"") | D12: =IF(A12<>"",""&DATA_PROVENANCE!D9,"") | E12: =IF(A12<>"",DATA_PROVENANCE!E9,"") | F12: =IF(A12<>"",""&DATA_PROVENANCE!F9,"") | G12: =IF(A12<>"",""&DATA_PROVENANCE!G9,"")
A13: =IF(DATA_PROVENANCE!A10<>"",""&DATA_PROVENANCE!A10,"") | B13: =IF(A13<>"",""&DATA_PROVENANCE!B10,"") | C13: =IF(A13<>"",""&DATA_PROVENANCE!C10,"") | D13: =IF(A13<>"",""&DATA_PROVENANCE!D10,"") | E13: =IF(A13<>"",DATA_PROVENANCE!E10,"") | F13: =IF(A13<>"",""&DATA_PROVENANCE!F10,"") | G13: =IF(A13<>"",""&DATA_PROVENANCE!G10,"")
A14: =IF(DATA_PROVENANCE!A11<>"",""&DATA_PROVENANCE!A11,"") | B14: =IF(A14<>"",""&DATA_PROVENANCE!B11,"") | C14: =IF(A14<>"",""&DATA_PROVENANCE!C11,"") | D14: =IF(A14<>"",""&DATA_PROVENANCE!D11,"") | E14: =IF(A14<>"",DATA_PROVENANCE!E11,"") | F14: =IF(A14<>"",""&DATA_PROVENANCE!F11,"") | G14: =IF(A14<>"",""&DATA_PROVENANCE!G11,"")
A15: =IF(DATA_PROVENANCE!A12<>"",""&DATA_PROVENANCE!A12,"") | B15: =IF(A15<>"",""&DATA_PROVENANCE!B12,"") | C15: =IF(A15<>"",""&DATA_PROVENANCE!C12,"") | D15: =IF(A15<>"",""&DATA_PROVENANCE!D12,"") | E15: =IF(A15<>"",DATA_PROVENANCE!E12,"") | F15: =IF(A15<>"",""&DATA_PROVENANCE!F12,"") | G15: =IF(A15<>"",""&DATA_PROVENANCE!G12,"")
A16: =IF(DATA_PROVENANCE!A13<>"",""&DATA_PROVENANCE!A13,"") | B16: =IF(A16<>"",""&DATA_PROVENANCE!B13,"") | C16: =IF(A16<>"",""&DATA_PROVENANCE!C13,"") | D16: =IF(A16<>"",""&DATA_PROVENANCE!D13,"") | E16: =IF(A16<>"",DATA_PROVENANCE!E13,"") | F16: =IF(A16<>"",""&DATA_PROVENANCE!F13,"") | G16: =IF(A16<>"",""&DATA_PROVENANCE!G13,"")
... A54: =IF(DATA_PROVENANCE!A51<>"",""&DATA_PROVENANCE!A51,"") | B54: =IF(A54<>"",""&DATA_PROVENANCE!B51,"") | C54: =IF(A54<>"",""&DATA_PROVENANCE!C51,"") | D54: =IF(A54<>"",""&DATA_PROVENANCE!D51,"") | E54: =IF(A54<>"",DATA_PROVENANCE!E51,"") | F54: =IF(A54<>"",""&DATA_PROVENANCE!F51,"") | G54: =IF(A54<>"",""&DATA_PROVENANCE!G51,"")

Sheet 07_Human_Decision_Log
A1: RESEARCH INTELLIGENCE ENGINE (RIE) — HUMAN DECISION LOG | H1: =HYPERLINK("#'01_Executive_Dashboard'!A1", "⮌ BACK TO DASHBOARD")
A2: ="Pillar 7: Ratified Human Decisions & Sovereign Architecture Decrees (" & COUNTA(DATA_DECISION_LOG!A2:A1000) & " Decisions) | Human Architect Level 5 — Human Architect"
A4: Decision_ID | B4: Queue_ID | C4: Subject_Object | D4: Human_Decision | E4: Ratified_Status | F4: Decision_Date | G4: Architect_Remark | H4: Authority_Ref | I4: Review_Queue_Link
A5: =IF(DATA_DECISION_LOG!A2<>"",""&DATA_DECISION_LOG!A2,"") | B5: =IF(A5<>"",""&DATA_DECISION_LOG!B2,"") | C5: =IF(A5<>"",""&DATA_DECISION_LOG!C2,"") | D5: =IF(A5<>"",""&DATA_DECISION_LOG!D2,"") | E5: =IF(A5<>"",""&DATA_DECISION_LOG!E2,"") | F5: =IF(A5<>"",""&DATA_DECISION_LOG!F2,"") | G5: =IF(A5<>"",""&DATA_DECISION_LOG!G2,"") | H5: =IF(A5<>"",""&DATA_DECISION_LOG!H2,"") | I5: =HYPERLINK("#'05_Knowledge_Frontier'!A" & MATCH("Q-001", '05_Knowledge_Frontier'!A:A, 0), "➔ Inspect Review Item (Q-001)")
A6: =IF(DATA_DECISION_LOG!A3<>"",""&DATA_DECISION_LOG!A3,"") | B6: =IF(A6<>"",""&DATA_DECISION_LOG!B3,"") | C6: =IF(A6<>"",""&DATA_DECISION_LOG!C3,"") | D6: =IF(A6<>"",""&DATA_DECISION_LOG!D3,"") | E6: =IF(A6<>"",""&DATA_DECISION_LOG!E3,"") | F6: =IF(A6<>"",""&DATA_DECISION_LOG!F3,"") | G6: =IF(A6<>"",""&DATA_DECISION_LOG!G3,"") | H6: =IF(A6<>"",""&DATA_DECISION_LOG!H3,"") | I6: =HYPERLINK("#'05_Knowledge_Frontier'!A" & MATCH("Q-002", '05_Knowledge_Frontier'!A:A, 0), "➔ Inspect Review Item (Q-002)")
A7: =IF(DATA_DECISION_LOG!A4<>"",""&DATA_DECISION_LOG!A4,"") | B7: =IF(A7<>"",""&DATA_DECISION_LOG!B4,"") | C7: =IF(A7<>"",""&DATA_DECISION_LOG!C4,"") | D7: =IF(A7<>"",""&DATA_DECISION_LOG!D4,"") | E7: =IF(A7<>"",""&DATA_DECISION_LOG!E4,"") | F7: =IF(A7<>"",""&DATA_DECISION_LOG!F4,"") | G7: =IF(A7<>"",""&DATA_DECISION_LOG!G4,"") | H7: =IF(A7<>"",""&DATA_DECISION_LOG!H4,"") | I7: =HYPERLINK("#'05_Knowledge_Frontier'!A" & MATCH("Q-003", '05_Knowledge_Frontier'!A:A, 0), "➔ Inspect Review Item (Q-003)")
A8: =IF(DATA_DECISION_LOG!A5<>"",""&DATA_DECISION_LOG!A5,"") | B8: =IF(A8<>"",""&DATA_DECISION_LOG!B5,"") | C8: =IF(A8<>"",""&DATA_DECISION_LOG!C5,"") | D8: =IF(A8<>"",""&DATA_DECISION_LOG!D5,"") | E8: =IF(A8<>"",""&DATA_DECISION_LOG!E5,"") | F8: =IF(A8<>"",""&DATA_DECISION_LOG!F5,"") | G8: =IF(A8<>"",""&DATA_DECISION_LOG!G5,"") | H8: =IF(A8<>"",""&DATA_DECISION_LOG!H5,"") | I8: =HYPERLINK("#'05_Knowledge_Frontier'!A" & MATCH("Q-004", '05_Knowledge_Frontier'!A:A, 0), "➔ Inspect Review Item (Q-004)")
A9: =IF(DATA_DECISION_LOG!A6<>"",""&DATA_DECISION_LOG!A6,"") | B9: =IF(A9<>"",""&DATA_DECISION_LOG!B6,"") | C9: =IF(A9<>"",""&DATA_DECISION_LOG!C6,"") | D9: =IF(A9<>"",""&DATA_DECISION_LOG!D6,"") | E9: =IF(A9<>"",""&DATA_DECISION_LOG!E6,"") | F9: =IF(A9<>"",""&DATA_DECISION_LOG!F6,"") | G9: =IF(A9<>"",""&DATA_DECISION_LOG!G6,"") | H9: =IF(A9<>"",""&DATA_DECISION_LOG!H6,"")
A10: =IF(DATA_DECISION_LOG!A7<>"",""&DATA_DECISION_LOG!A7,"") | B10: =IF(A10<>"",""&DATA_DECISION_LOG!B7,"") | C10: =IF(A10<>"",""&DATA_DECISION_LOG!C7,"") | D10: =IF(A10<>"",""&DATA_DECISION_LOG!D7,"") | E10: =IF(A10<>"",""&DATA_DECISION_LOG!E7,"") | F10: =IF(A10<>"",""&DATA_DECISION_LOG!F7,"") | G10: =IF(A10<>"",""&DATA_DECISION_LOG!G7,"") | H10: =IF(A10<>"",""&DATA_DECISION_LOG!H7,"")
A11: =IF(DATA_DECISION_LOG!A8<>"",""&DATA_DECISION_LOG!A8,"") | B11: =IF(A11<>"",""&DATA_DECISION_LOG!B8,"") | C11: =IF(A11<>"",""&DATA_DECISION_LOG!C8,"") | D11: =IF(A11<>"",""&DATA_DECISION_LOG!D8,"") | E11: =IF(A11<>"",""&DATA_DECISION_LOG!E8,"") | F11: =IF(A11<>"",""&DATA_DECISION_LOG!F8,"") | G11: =IF(A11<>"",""&DATA_DECISION_LOG!G8,"") | H11: =IF(A11<>"",""&DATA_DECISION_LOG!H8,"")
A12: =IF(DATA_DECISION_LOG!A9<>"",""&DATA_DECISION_LOG!A9,"") | B12: =IF(A12<>"",""&DATA_DECISION_LOG!B9,"") | C12: =IF(A12<>"",""&DATA_DECISION_LOG!C9,"") | D12: =IF(A12<>"",""&DATA_DECISION_LOG!D9,"") | E12: =IF(A12<>"",""&DATA_DECISION_LOG!E9,"") | F12: =IF(A12<>"",""&DATA_DECISION_LOG!F9,"") | G12: =IF(A12<>"",""&DATA_DECISION_LOG!G9,"") | H12: =IF(A12<>"",""&DATA_DECISION_LOG!H9,"")
A13: =IF(DATA_DECISION_LOG!A10<>"",""&DATA_DECISION_LOG!A10,"") | B13: =IF(A13<>"",""&DATA_DECISION_LOG!B10,"") | C13: =IF(A13<>"",""&DATA_DECISION_LOG!C10,"") | D13: =IF(A13<>"",""&DATA_DECISION_LOG!D10,"") | E13: =IF(A13<>"",""&DATA_DECISION_LOG!E10,"") | F13: =IF(A13<>"",""&DATA_DECISION_LOG!F10,"") | G13: =IF(A13<>"",""&DATA_DECISION_LOG!G10,"") | H13: =IF(A13<>"",""&DATA_DECISION_LOG!H10,"")
A14: =IF(DATA_DECISION_LOG!A11<>"",""&DATA_DECISION_LOG!A11,"") | B14: =IF(A14<>"",""&DATA_DECISION_LOG!B11,"") | C14: =IF(A14<>"",""&DATA_DECISION_LOG!C11,"") | D14: =IF(A14<>"",""&DATA_DECISION_LOG!D11,"") | E14: =IF(A14<>"",""&DATA_DECISION_LOG!E11,"") | F14: =IF(A14<>"",""&DATA_DECISION_LOG!F11,"") | G14: =IF(A14<>"",""&DATA_DECISION_LOG!G11,"") | H14: =IF(A14<>"",""&DATA_DECISION_LOG!H11,"")
A15: =IF(DATA_DECISION_LOG!A12<>"",""&DATA_DECISION_LOG!A12,"") | B15: =IF(A15<>"",""&DATA_DECISION_LOG!B12,"") | C15: =IF(A15<>"",""&DATA_DECISION_LOG!C12,"") | D15: =IF(A15<>"",""&DATA_DECISION_LOG!D12,"") | E15: =IF(A15<>"",""&DATA_DECISION_LOG!E12,"") | F15: =IF(A15<>"",""&DATA_DECISION_LOG!F12,"") | G15: =IF(A15<>"",""&DATA_DECISION_LOG!G12,"") | H15: =IF(A15<>"",""&DATA_DECISION_LOG!H12,"")
A16: =IF(DATA_DECISION_LOG!A13<>"",""&DATA_DECISION_LOG!A13,"") | B16: =IF(A16<>"",""&DATA_DECISION_LOG!B13,"") | C16: =IF(A16<>"",""&DATA_DECISION_LOG!C13,"") | D16: =IF(A16<>"",""&DATA_DECISION_LOG!D13,"") | E16: =IF(A16<>"",""&DATA_DECISION_LOG!E13,"") | F16: =IF(A16<>"",""&DATA_DECISION_LOG!F13,"") | G16: =IF(A16<>"",""&DATA_DECISION_LOG!G13,"") | H16: =IF(A16<>"",""&DATA_DECISION_LOG!H13,"")
A17: =IF(DATA_DECISION_LOG!A14<>"",""&DATA_DECISION_LOG!A14,"") | B17: =IF(A17<>"",""&DATA_DECISION_LOG!B14,"") | C17: =IF(A17<>"",""&DATA_DECISION_LOG!C14,"") | D17: =IF(A17<>"",""&DATA_DECISION_LOG!D14,"") | E17: =IF(A17<>"",""&DATA_DECISION_LOG!E14,"") | F17: =IF(A17<>"",""&DATA_DECISION_LOG!F14,"") | G17: =IF(A17<>"",""&DATA_DECISION_LOG!G14,"") | H17: =IF(A17<>"",""&DATA_DECISION_LOG!H14,"")
A18: =IF(DATA_DECISION_LOG!A15<>"",""&DATA_DECISION_LOG!A15,"") | B18: =IF(A18<>"",""&DATA_DECISION_LOG!B15,"") | C18: =IF(A18<>"",""&DATA_DECISION_LOG!C15,"") | D18: =IF(A18<>"",""&DATA_DECISION_LOG!D15,"") | E18: =IF(A18<>"",""&DATA_DECISION_LOG!E15,"") | F18: =IF(A18<>"",""&DATA_DECISION_LOG!F15,"") | G18: =IF(A18<>"",""&DATA_DECISION_LOG!G15,"") | H18: =IF(A18<>"",""&DATA_DECISION_LOG!H15,"")
A19: =IF(DATA_DECISION_LOG!A16<>"",""&DATA_DECISION_LOG!A16,"") | B19: =IF(A19<>"",""&DATA_DECISION_LOG!B16,"") | C19: =IF(A19<>"",""&DATA_DECISION_LOG!C16,"") | D19: =IF(A19<>"",""&DATA_DECISION_LOG!D16,"") | E19: =IF(A19<>"",""&DATA_DECISION_LOG!E16,"") | F19: =IF(A19<>"",""&DATA_DECISION_LOG!F16,"") | G19: =IF(A19<>"",""&DATA_DECISION_LOG!G16,"") | H19: =IF(A19<>"",""&DATA_DECISION_LOG!H16,"")
A20: =IF(DATA_DECISION_LOG!A17<>"",""&DATA_DECISION_LOG!A17,"") | B20: =IF(A20<>"",""&DATA_DECISION_LOG!B17,"") | C20: =IF(A20<>"",""&DATA_DECISION_LOG!C17,"") | D20: =IF(A20<>"",""&DATA_DECISION_LOG!D17,"") | E20: =IF(A20<>"",""&DATA_DECISION_LOG!E17,"") | F20: =IF(A20<>"",""&DATA_DECISION_LOG!F17,"") | G20: =IF(A20<>"",""&DATA_DECISION_LOG!G17,"") | H20: =IF(A20<>"",""&DATA_DECISION_LOG!H17,"")
... A104: =IF(DATA_DECISION_LOG!A101<>"",""&DATA_DECISION_LOG!A101,"") | B104: =IF(A104<>"",""&DATA_DECISION_LOG!B101,"") | C104: =IF(A104<>"",""&DATA_DECISION_LOG!C101,"") | D104: =IF(A104<>"",""&DATA_DECISION_LOG!D101,"") | E104: =IF(A104<>"",""&DATA_DECISION_LOG!E101,"") | F104: =IF(A104<>"",""&DATA_DECISION_LOG!F101,"") | G104: =IF(A104<>"",""&DATA_DECISION_LOG!G101,"") | H104: =IF(A104<>"",""&DATA_DECISION_LOG!H101,"")

Sheet DATA_SOURCE
A1: Source_ID | B1: Source_Type | C1: Speaker_Author | D1: Organization_Channel | E1: Source_Topic | F1: RIE_Domain | G1: Date_Published | H1: EO_Count | I1: Status

Sheet DATA_EO
A1: EO_ID | B1: Source_ID | C1: Source_Type | D1: Speaker_Author | E1: Organization_Channel | F1: Source_Topic | G1: RIE_Domain | H1: RIE_Subtopic | I1: Date_Published | J1: Timestamp_Page | K1: Evidence_Type | L1: Direct_Observation | M1: Linked_IO | N1: Notes | O1: Search_Match | P1: Match_Rank

Sheet DATA_IO
A1: IO_ID | B1: Research_Question | C1: Primary_Interpretation | D1: Alternative_Interpretation | E1: Supporting_EO | F1: Contradicting_EO | G1: Confidence | H1: Human_Review_Notes | I1: Future_Research_Needed | J1: Search_Match | K1: Match_Rank

Sheet DATA_KO
A1: KO_ID | B1: Concept_Title | C1: Domain | D1: Origin_Source | E1: Supporting_EO | F1: Supporting_IO | G1: Confidence | H1: Status | I1: Human_Approval_State | J1: Search_Match | K1: Match_Rank | L1: Match_KO_Title | M1: Match_IO_Question | N1: Match_EO_Observation | O1: Match_Because | P1: Match_Detail_Snippet | Q1: EO_Count | R1: IO_Count | S1: Counter_IO_Explanation | T1: Substrate_Profile_Summary | U1: Priority_Tier | V1: Composite_Sort_Score

Sheet DATA_RELATIONSHIPS
A1: Lookup_Key | B1: Relationship_ID | C1: From_KO | D1: To_KO | E1: Relationship_Description | F1: Relationship_Type | G1: Confidence | H1: Human_Approval | I1: Cluster_ID | J1: Notes

Sheet DATA_CLUSTERS
A1: Cluster_ID | B1: Cluster_Theme | C1: Primary_KO | D1: Domain | E1: Confidence | F1: Search_Keywords | G1: Related_KO_1 | H1: Related_KO_2 | I1: Related_KO_3 | J1: Related_KO_4 | K1: Related_KO_5 | L1: Related_IOs | M1: Related_EOs | N1: Source_Origins | O1: Human_Approval
A2: CLUSTER_GOLD_MONETARY_SYSTEM | B2: Gold Monetary System Transition | C2: KO-FIN-DE-DOLLARIZATION-SANCTIONS-001 | D2: Monetary Economics | E2: 0.85 | F2: gold, monetary, dollar, sanctions, central bank, de-dollarization, reserve, metals, bullion, rate hike, yield curve | G2: KO-FIN-RATE-HIKE-DISCOUNTING-BOTTOM-001 | H2: KO-FIN-BEAR-STEEPENING-001 | I2: KO-FIN-UNDERALLOCATION-BEAR-ROTATION-001 | J2: KO-FIN-EQUITY-RATIO-VALUATION-001 | K2: KO-MACRO-PERCEPTION-REALITY-ARBITRAGE-001 | L2: IO-FelixPrehn-DollarSanctionsDeDollarization-002, IO-FelixPrehn-CentralBankGoldReserveFloor-004, IO-JordanRoyByrne-PreemptiveRateHikeDiscounting-001, IO-JordanRoyByrne-BearSteepeningTransmission-001, IO-JordanRoyByrne-UnderallocationBearMarketRotation-002, IO-JordanRoyByrne-SecularRatioCapitalRotation-004, IO-BobThompson-PerceptionRealityArbitrage-002 | M2: EO-FelixPrehn-USSanctionsEconomicOutcast-005, EO-FelixPrehn-CentralBankPhysicalGoldAccumulation-007, EO-JordanRoyByrne-YieldCurveDynamics2YSurge-001, EO-JordanRoyByrne-HistoricalRateHikeBottoms-002, EO-JordanRoyByrne-PreemptiveYieldDiscounting2026-004, EO-JordanRoyByrne-BearSteepeningSpread-001, EO-JordanRoyByrne-RealRateDecoupling-002, EO-JordanRoyByrne-Historical1970sAnalog-004, EO-JordanRoyByrne-HistoricalEquityBearRotation-008, EO-JordanRoyByrne-GoldETFAllocationBaseline-009, EO-JordanRoyByrne-GoldSP500SecularRatio-008, EO-JordanRoyByrne-GoldNasdaqRoundingBase-009, EO-BobThompson-PerceptionRealityZone-003, EO-BobThompson-PoliticalPressure1970sRateCut-004, EO-BobThompson-PowellInflationPerceptionDynamics-005 | N2: VIDEO-001, VIDEO-002, VIDEO-003, VIDEO-005 | O2: Approved
A3: CLUSTER_AI_CREDIT_CONTAGION | B3: AI Infrastructure & Syndicated Debt Contagion | C3: KO-FIN-STRUCTURED-SPV-CREDIT-ARBITRAGE-001 | D3: Financial Markets / Structured Finance | E3: 0.82 | F3: ai, compute, token, spv, loans, datacenter, cloud, capex, credit, contagion, syndicated, tech | G3: KO-FIN-COMPUTE-TOKEN-DEFLATION-001 | H3: KO-FIN-SHADOW-CAPEX-COMMITMENT-WALL-001 | I3: KO-FIN-BASIS-TRADE-LEVERAGE-001 | L3: IO-StevenVanMetre-SPVCreditArbitrageContagion-001, IO-StevenVanMetre-ComputeTokenDeflationMarginSqueeze-002, IO-StevenVanMetre-ShadowCapexCommitmentWall-003, IO-FelixPrehn-TreasuryBasisTradeLiquidityRisk-003 | M3: EO-StevenVanMetre-OracleProjectJupiterLoans-001, EO-StevenVanMetre-SPVRatingArbitrage-003, EO-StevenVanMetre-ProjectJupiterDelayTimeline-005, EO-StevenVanMetre-HyperscalerFCFDeficits-006, EO-StevenVanMetre-AIComputeTokenPricingCollapse-008, EO-StevenVanMetre-HyperscalerDebtIssuanceForecast-009, EO-StevenVanMetre-OracleCreditDowngrade-004, EO-StevenVanMetre-MorganStanleyOffBalanceSheetObligations-007, EO-FelixPrehn-HedgeFundTreasuryBasisTrade-006 | N3: VIDEO-003, VIDEO-004 | O3: Approved
A4: CLUSTER_SOVEREIGN_DEBT_SPIRAL | B4: Sovereign Debt & Fiscal Dominance Spiral | C4: KO-FIN-DEBT-INTEREST-SPIRAL-001 | D4: Fiscal Economics / Sovereign Debt | E4: 0.9 | F4: debt, treasury, basis trade, fiscal, interest, refinancing, bond, yield, supply shock, inflation | G4: KO-FIN-BEAR-STEEPENING-001 | H4: KO-FIN-BASIS-TRADE-LEVERAGE-001 | I4: KO-MACRO-SUPPLY-SHOCK-POLICY-FAILURE-001 | L4: IO-JordanRoyByrne-SovereignDebtInterestSpiral-002, IO-JordanRoyByrne-BearSteepeningTransmission-001, IO-FelixPrehn-TreasuryBasisTradeLiquidityRisk-003, IO-FelixPrehn-EnergyFertilizerInflationTransmission-001 | M4: EO-JordanRoyByrne-SovereignDebtRefinancingLoad-005, EO-JordanRoyByrne-NetInterestRevenueRatio-006, EO-JordanRoyByrne-BearSteepeningSpread-001, EO-JordanRoyByrne-RealRateDecoupling-002, EO-FelixPrehn-HedgeFundTreasuryBasisTrade-006, EO-FelixPrehn-USTreasuryCashBuyback-009, EO-FelixPrehn-SulfuricAcidExportBan-001 | N4: VIDEO-001, VIDEO-003 | O4: Approved
A5: CLUSTER_MARKET_PSYCHOLOGY_REGIME | B5: Market Psychology & Reflexive Regime Shifts | C5: KO-FIN-CONSENSUS-SATURATION-001 | D5: Financial Markets / Market Psychology | E5: 0.88 | F5: psychology, consensus, regime, reflexivity, central bank, perception, reality, resilience, failure | G5: KO-STRAT-REGIME-ADAPTIVE-EXECUTION-001 | H5: KO-MACRO-PERCEPTION-REALITY-ARBITRAGE-001 | I5: KO-MACRO-RESOURCE-REFLEXIVITY-LOOP-001 | J5: KO-ARCH-FAILURE-CODIFICATION-RESILIENCE-001 | L5: IO-BobThompson-ConsensusSaturation-001, IO-BobThompson-RegimeAdaptiveExecution-003, IO-BobThompson-PerceptionRealityArbitrage-002, IO-BobThompson-ResourceReflexivityCapitalization-004, IO-BobThompson-GenerationalFailureResilience-005 | M5: EO-BobThompson-ConsensusSaturationDruckenmiller-001, EO-BobThompson-DebtDowngrade2011TopAnalog-002, EO-BobThompson-ParabolicVelocityConsolidationSymmetry-006, EO-BobThompson-PrimaryBullMarketHeuristic-007, EO-BobThompson-PrimaryBearMarketHeuristic-008, EO-BobThompson-PerceptionRealityZone-003, EO-BobThompson-ResourceMarketDecoupling-011, EO-BobThompson-SorosReflexivityResourceLoop-012, EO-BobThompson-GenerationalFailureTransmission-009, EO-BobThompson-RubberBallVsGlassResilience-010 | N5: VIDEO-005 | O5: Approved

Sheet DATA_PROVENANCE
A1: Asset_ID | B1: Asset_Type | C1: Canonical_Path | D1: SHA256_Checksum | E1: Record_Count | F1: Last_Verified_UTC | G1: Integrity_Status
A2: RIE_CANONICAL_DATA_TABLES.xlsx | B2: CANONICAL_SUBSTRATE | C2: 000_RIE_New_Era/INTELLIGENCE/DATA/RIE_CANONICAL_DATA_TABLES.xlsx | D2: e80ed99c0accc5902952927146e44516ecae199d581881186a0db3b7e785130c | E2: 168 | F2: 2026-09-29 05:50:00 | G2: PASS (BIT_LEVEL_PARITY)
A3: EO_MASTER_INDEX.xlsx | B3: MASTER_INDEX | C3: 000_RIE_New_Era/INTELLIGENCE/EO_MASTER_INDEX.xlsx | D3: af1ba7bbc629560427121a563e574fbcf6b847193787950c9a731d304da52553 | E3: 98 | F3: 2026-09-29 05:50:00 | G3: PASS (BIT_LEVEL_PARITY)
A4: IO_MASTER_INDEX.xlsx | B4: MASTER_INDEX | C4: 000_RIE_New_Era/INTELLIGENCE/IO_MASTER_INDEX.xlsx | D4: 797bc2ec415266c37f36845923dbed37f40c9e648ab717ccc650f9bc50f860ac | E4: 41 | F4: 2026-09-29 05:50:00 | G4: PASS (BIT_LEVEL_PARITY)
A5: KO_MASTER_INDEX.xlsx | B5: MASTER_INDEX | C5: 000_RIE_New_Era/INTELLIGENCE/KO_MASTER_INDEX.xlsx | D5: cfb94d29a8c636ff224b479d997023358e1ec680a92dc9220bf0dc80361b33ad | E5: 29 | F5: 2026-09-29 05:50:00 | G5: PASS (BIT_LEVEL_PARITY)
A6: SOURCE_RECORD_VIDEO-001.md | B6: SOURCE_CUSTODY | C6: 000_RIE_New_Era/INTELLIGENCE/SOURCE_RECORDS/SOURCE_RECORD_VIDEO-001.md | D6: 93b357b484e8a7ac55734d89bb13453688e0dd8760bdfb0c37cf8e368ad36df8 | E6: 1 | F6: 2026-09-22 18:45:00 | G6: PASS (CUSTODY_ORIGIN)
A7: SOURCE_RECORD_VIDEO-002.md | B7: SOURCE_CUSTODY | C7: 000_RIE_New_Era/INTELLIGENCE/SOURCE_RECORDS/SOURCE_RECORD_VIDEO-002.md | D7: 331a80ea4ba2c715c3af659d339e96132772c059ee15e8f9f60f701bf991408b | E7: 1 | F7: 2026-09-22 18:45:00 | G7: PASS (CUSTODY_ORIGIN)
A8: SOURCE_RECORD_VIDEO-003.md | B8: SOURCE_CUSTODY | C8: 000_RIE_New_Era/INTELLIGENCE/SOURCE_RECORDS/SOURCE_RECORD_VIDEO-003.md | D8: 5175c9821073bb48aa740c303bf64db69cfa82675a41a773a445d27a6bb2394f | E8: 1 | F8: 2026-09-22 18:45:00 | G8: PASS (CUSTODY_ORIGIN)
A9: SOURCE_RECORD_VIDEO-004.md | B9: SOURCE_CUSTODY | C9: 000_RIE_New_Era/INTELLIGENCE/SOURCE_RECORDS/SOURCE_RECORD_VIDEO-004.md | D9: 34cfa670972b602f46172716d1bf74b5341be046eb253d6705af687ece0a71f9 | E9: 1 | F9: 2026-09-22 18:45:00 | G9: PASS (CUSTODY_ORIGIN)
A10: SOURCE_RECORD_VIDEO-005.md | B10: SOURCE_CUSTODY | C10: 000_RIE_New_Era/INTELLIGENCE/SOURCE_RECORDS/SOURCE_RECORD_VIDEO-005.md | D10: fc9d080193a7d203f002a743b29e0619430161e465142d6f3d56e9a31412d531 | E10: 1 | F10: 2026-09-22 18:45:00 | G10: PASS (CUSTODY_ORIGIN)
A11: RIE_v1.4.0_SEMANTIC_CERTIFIED_RC1 | B11: DEVELOPMENT_CANDIDATE | C11: 006_ENGINE/REMEDIATION_V3_DEV/ | D11: 204ab63ffcb17fe6094b4649e512bed4b94931f8653b8858711ad32bf0ef2f9d | E11: 30 | F11: 2026-10-05 03:22:00 | G11: PASS (18/18 Unit Tests, 3/3 Benchmarks, 36/36 Semantic Gates)
A12: RIE_PHASE6B_RC1_SEAL_DECLARATION.md | B12: CUSTODY_SEAL | C12: 000_RIE_New_Era/RIE_PHASE6B_RC1_SEAL_DECLARATION.md | D12: ceae0887cf76ef1d126eb1bc5290b20c9cccdbfee8c0e831c3ce32af8501ff56 | E12: 1 | F12: 2026-10-05 03:26:00 | G12: SEALED (CUSTODY_ANCHOR)

Sheet DATA_DECISION_LOG
A1: Decision_ID | B1: Queue_ID | C1: Subject_Object | D1: Human_Decision | E1: Ratified_Status | F1: Decision_Date | G1: Architect_Remark | H1: Authority_Ref

Sheet DATA_EVOLUTION
A1: Evolution_ID | B1: KO_ID | C1: Concept_Title | D1: Version | E1: Event_Date | F1: Trigger_Source | G1: Prior_Understanding | H1: Evolved_Understanding | I1: Confidence_Change | J1: Research_Notes
A2: EVO-001 | B2: KO-FIN-BEAR-STEEPENING-001 | C2: Bear Steepening Transmission and Real Rate Decoupling | D2: v1.0 | F2: VIDEO-001 Ingestion | G2: Gold price was modeled as inversely correlated with US 10-year real Treasury yields under conventional monetary tightening frameworks. | H2: Bear steepening in mature debt cycles decouples gold from real yield suppression; rising long yields reflect sovereign debt credit risk rather than growth optimism. | I2: Baseline 0.88 (Initial Level 5 Candidate Promotion) | J2: Catalyzed by empirical 10Y real yield advance concurrent with gold +19% breakout in VIDEO-001; refined boundaries to fiscal dominance regime.
A3: EVO-002 | B3: KO-FIN-DEBT-INTEREST-SPIRAL-001 | C3: Sovereign Debt Refinancing Load and Net Interest Revenue Threshold | D3: v1.0 | F3: VIDEO-001 Ingestion | G3: Sovereign debt considered an abstract macroeconomic risk without explicit arithmetic tipping points. | H3: Identified concrete arithmetic insolvency threshold: $40T debt at ~4.8% yields creates $1.2T annual net interest burden, absorbing 20% of federal tax receipts. | I3: Baseline 0.90 (High Confidence Mathematical Anchor) | J3: Catalyzed by Treasury debt rollover schedule analysis; established falsification trigger at 15% revenue absorption.
A4: EVO-003 | B4: KO-FIN-EQUITY-RATIO-VALUATION-001 | C4: Secular Cross-Asset Equity-to-Gold Ratio Valuation Cycle | D4: v1.0 | F4: VIDEO-001 Ingestion | G4: Asset prices evaluated in standalone nominal currency terms without cross-asset ratio normalization. | H4: Gold/S&P 500 ratio at 0.57 vs secular peaks of 4.0-6.0 demonstrates generational undervaluation of monetary reserves relative to paper equity claims. | I4: Baseline 0.82 (Multi-Decade Ratio Model) | J4: Catalyzed by 100-year commodity/equity cycle analysis; rounding bases against tech indices indicate capital rotation onset.
A5: EVO-004 | B5: KO-FIN-MINER-RATIO-BREAKOUT-001 | C5: Mining Equity Operating Leverage Base Breakout Dynamics | D5: v1.0 | F5: VIDEO-001 Ingestion | G5: Mining equities assumed to perpetually lag metal prices due to capital misallocation and cost inflation. | H5: 13-year base breakout in GDX/Gold ratio confirms producer operating margin expansion and multi-year equity operating leverage over metal. | I5: Baseline 0.86 (Resource Economics Anchor) | J5: Catalyzed by multi-year consolidation breakout; boundary set at senior producer AISC margin stability.
A6: EVO-005 | B6: KO-FIN-RATE-HIKE-DISCOUNTING-BOTTOM-001 | C6: Pre-emptive Tightening Discounting and Policy Announcement Bottoms | D6: v1.0 | F6: VIDEO-002 Ingestion | G6: Market consensus assumed tangible asset prices reach their lowest point at the conclusion of a rate hiking cycle. | H6: Empirical evidence demonstrates that bond markets pre-emptively discount tightening (2Y yield surge); physical rate hike announcements mark liquidity exhaustion bottoms. | I6: Baseline 0.78 (Monetary Transmission Model) | J6: Catalyzed by historical 2004, 2015, and 2022 policy cycle comparisons in VIDEO-002; codified sell-the-rumor/buy-the-news discounting.
A7: EVO-006 | B7: KO-FIN-UNDERALLOCATION-BEAR-ROTATION-001 | C7: Institutional Under-Allocation Buffer and Equity Bear Rotation | D7: v1.0 | F7: VIDEO-002 Ingestion | G7: Asset allocation models assumed institutional capital rotations require large-scale active reallocation campaigns. | H7: Extreme institutional under-allocation (<1% portfolio weighting) creates asymmetric upside buffer; marginal 50 bps allocation surge overwhelms physical bullion float. | I7: Baseline 0.76 (Institutional Capital Allocation) | J7: Catalyzed by global pension fund allocation filings and ETF liquidity data in VIDEO-002.
A8: EVO-007 | B8: KO-FIN-PRODUCER-OUTPERFORMANCE-CYCLE-001 | C8: Producer Operating Margin Expansion and Bull Cycle Confirmation | D8: v1.0 | F8: VIDEO-002 Ingestion | G8: Bullion price increases assumed to automatically lift all mining equities equally. | H8: Authentic bull cycle confirmation requires sustained senior producer outperformance over bullion, driven by expanding free cash flow yields and dividend growth. | I8: Baseline 0.80 (Resource Economics & Quality Filter) | J8: Catalyzed by relative strength index divergence between bullion spot and senior gold miners in VIDEO-002.
A9: EVO-008 | B9: KO-MACRO-SUPPLY-SHOCK-POLICY-FAILURE-001 | C9: Inelastic Cost-Push Supply Shock Policy Asymmetry | D9: v1.0 | F9: VIDEO-003 Ingestion | G9: Monetary policy interest rate adjustments believed to be effective in controlling all forms of headline inflation. | H9: Central bank rate hikes fail to resolve inelastic upstream chemical and energy supply shocks (sulfuric acid export bans, Hormuz transit bottlenecks); demand destruction occurs before supply responds. | I9: Baseline 0.78 (Supply Chain Dynamics) | J9: Catalyzed by global fertilizer/sulfur supply chain breakdowns in VIDEO-003; added supply chain rigidity as explicit boundary constraint.
A10: EVO-009 | B10: KO-FIN-DE-DOLLARIZATION-SANCTIONS-001 | C10: Geopolitical Dollar Weaponization and Sovereign Gold Re-anchoring | D10: v1.0 | F10: VIDEO-003 Ingestion | G10: US Treasury bonds viewed as the undisputed, default risk-free asset for all sovereign central bank reserves. | H10: Sanctions weaponization and foreign reserve confiscation transform Treasuries into counterparty liability; non-aligned central banks structurally accumulate physical bullion as sanction-proof neutral reserve. | I10: Baseline 0.85 (Geopolitical Monetary Economics) | J10: Catalyzed by post-2022 central bank gold accumulation data and currency settlement shifts in VIDEO-003.
A11: EVO-010 | B11: KO-FIN-BASIS-TRADE-LEVERAGE-001 | C11: Leveraged Sovereign Debt Basis Trade Systemic Fragility | D11: v1.0 | F11: VIDEO-003 Ingestion | G11: Hedge fund cash-futures basis trades seen as benign market-making arbitrage that enhances Treasury market liquidity. | H11: 50x to 100x leverage on basis trades creates systemic tail risk; repo rate spikes or volatility surges force sudden unwinds, requiring emergency Treasury buybacks to avert auction failure. | I11: Baseline 0.76 (Market Microstructure & Liquidity Risk) | J11: Catalyzed by Treasury buyback program announcements and SEC hedge fund leverage reporting in VIDEO-003.
A12: EVO-011 | B12: KO-FIN-STRUCTURED-SPV-CREDIT-ARBITRAGE-001 | C12: Structured SPV Rating Arbitrage and Syndicated Infrastructure Credit Contagion | D12: v1.0 | F12: VIDEO-004 Ingestion | G12: Special Purpose Vehicle (SPV) financing assumed to cleanly isolate corporate project liabilities from parent balance sheets. | H12: SPV structures create synthetic investment-grade ratings for sub-investment grade infrastructure projects; project delays directly threaten syndicated bank credit stability and corporate solvency. | I12: Baseline 0.82 (Structured Finance & Credit Risk) | J12: Catalyzed by Oracle Project Jupiter $38B syndicated loan analysis in VIDEO-004.
A13: EVO-012 | B13: KO-FIN-COMPUTE-TOKEN-DEFLATION-001 | C13: Capital Expenditure Debt Servicing vs Compute Token Price Deflation | D13: v1.0 | F13: VIDEO-004 Ingestion | G13: Hyperscaler AI capital expenditure viewed as self-funding through exponential revenue expansion. | H13: Fixed coupon debt obligations on multi-billion dollar capex collide with collapsing compute token pricing ($/M tokens falling 80%), creating severe cash flow margin compression. | I13: Baseline 0.80 (Technology Economics & Corporate Debt) | J13: Catalyzed by hyperscaler free cash flow deficit disclosures and compute market pricing collapse in VIDEO-004.
... A19: EVO-018 | B19: KO-ARCH-FAILURE-CODIFICATION-RESILIENCE-001 | C19: Elastic Failure Codification & Generational Resilience Heuristics | D19: v1.0 | F19: VIDEO-005 Ingestion | G19: Organizational risk management focused on avoiding operational mistakes. | H19: Institutional resilience requires systematic codification of generational failures (rubber ball vs glass ball framework), transforming error memory into adaptive survival instincts. | I19: Baseline 0.82 (Knowledge Architecture & Governance) | J19: Catalyzed by generational market cycle trauma transmission and institutional memory frameworks in VIDEO-005.

Sheet DATA_KO_HISTORY
A1: KO_HISTORY_ID | B1: KO_ID | C1: VERSION | D1: DATE | E1: PREVIOUS_CONFIDENCE | F1: NEW_CONFIDENCE | G1: CHANGE_TYPE | H1: TRIGGER_SOURCE | I1: CHANGE_DESCRIPTION | J1: HUMAN_REVIEW_STATUS | K1: CREATED_BY
